Workbook
Name AirRet: Returns!$C$6:INDEX(Returns!$C$6:$C$1000,COUNT(Returns!$A$6:$A$1000))
Name BenchRet: Returns!$I$6:INDEX(Returns!$I$6:$I$1000,COUNT(Returns!$A$6:$A$1000))
Name CipRet: Returns!$F$6:INDEX(Returns!$F$6:$F$1000,COUNT(Returns!$A$6:$A$1000))
Name CompanyNames: Holdings!$C$7:$C$13
Name CurrentPortValue: Drawdown!$X$1005
Name DD_BenchDD: Drawdown!$I$9:INDEX(Drawdown!$I$7:$I$1000,COUNT(Drawdown!$A$7:$A$1000))
Name DD_BenchVal: Drawdown!$G$9:INDEX(Drawdown!$G$7:$G$1000,COUNT(Drawdown!$A$7:$A$1000))
Name DD_ChartBenchDD: Drawdown!$R$7:INDEX(Drawdown!$R$7:$R$1000,COUNT(Drawdown!$A$7:$A$1000))
Name DD_ChartBenchVal: Drawdown!$N$7:INDEX(Drawdown!$N$7:$N$1000,COUNT(Drawdown!$A$7:$A$1000))
Name DD_ChartDates: Drawdown!$L$7:INDEX(Drawdown!$L$7:$L$1000,COUNT(Drawdown!$A$7:$A$1000))
Name DD_ChartDDDates: Drawdown!$P$7:INDEX(Drawdown!$P$7:$P$1000,COUNT(Drawdown!$A$7:$A$1000))
Name DD_ChartPortDD: Drawdown!$Q$7:INDEX(Drawdown!$Q$7:$Q$1000,COUNT(Drawdown!$A$7:$A$1000))
Name DD_ChartPortVal: Drawdown!$M$7:INDEX(Drawdown!$M$7:$M$1000,COUNT(Drawdown!$A$7:$A$1000))
Name DD_Dates: Drawdown!$J$9:INDEX(Drawdown!$J$7:$J$1000,COUNT(Drawdown!$A$7:$A$1000))
Name DD_PortDD: Drawdown!$E$9:INDEX(Drawdown!$E$7:$E$1000,COUNT(Drawdown!$A$7:$A$1000))
Name DD_PortVal: Drawdown!$C$9:INDEX(Drawdown!$C$7:$C$1000,COUNT(Drawdown!$A$7:$A$1000))
Name HclRet: Returns!$H$6:INDEX(Returns!$H$6:$H$1000,COUNT(Returns!$A$6:$A$1000))
Name HdfRet: Returns!$D$6:INDEX(Returns!$D$6:$D$1000,COUNT(Returns!$A$6:$A$1000))
Name IndexBase: Inputs!$B$12
Name LatestObsDate: Drawdown!$X$1009
Name LtRet: Returns!$E$6:INDEX(Returns!$E$6:$E$1000,COUNT(Returns!$A$6:$A$1000))
Name MarRet: Returns!$G$6:INDEX(Returns!$G$6:$G$1000,COUNT(Returns!$A$6:$A$1000))
Name NotionalValue: Inputs!$B$13
Name PortfolioPnL: Drawdown!$X$1006
Name PortRet: Returns!$J$6:INDEX(Returns!$J$6:$J$1000,COUNT(Returns!$A$6:$A$1000))
Name PortValueDates: Drawdown!$T$7:INDEX(Drawdown!$T$7:$T$1000,COUNT(Drawdown!$A$7:$A$1000))
Name PortValueSeries: Drawdown!$U$7:INDEX(Drawdown!$U$7:$U$1000,COUNT(Drawdown!$A$7:$A$1000))
Name RelRet: Returns!$B$6:INDEX(Returns!$B$6:$B$1000,COUNT(Returns!$A$6:$A$1000))
Name RiskFree: Inputs!$B$18
Name StockRets: Returns!$B$6:INDEX(Returns!$B$6:$H$1000,COUNT(Returns!$A$6:$A$1000),7)
Name Thr30: Inputs!$B$37
Name Thr50: Inputs!$B$36
Name Thr80: Inputs!$B$35
Name Tickers: Holdings!$B$7:$B$13
Name WeeksPerYear: Inputs!$B$11
Name Weights: Returns!$B$4:$H$4
Name WeightsCol: Holdings!$E$7:$E$13

Sheet Overview
A1: PERSONAL PORTFOLIO ANALYSIS
A2: Indian Equity Portfolio vs NIFTY 50 · 7 holdings · weekly data · Excel 365
A4: PORTFOLIO OBJECTIVE
A5: Objective | B5: Measure return, risk, risk-adjusted return, systematic risk (beta/alpha), diversification and drawdown for a seven-stock Indian equity book against the NIFTY 50 — from one weekly return series, with every figure a live formula.
A7: KEY FACTS
A8: Benchmark | B8: NIFTY 50 (^NSEI) — price index
A9: Analysis period | B9: ="Weekly, "&TEXT(Inputs!$B$6,"dd-mmm-yyyy")&" to "&TEXT(Inputs!$B$7,"dd-mmm-yyyy")&" ("&TEXT(Inputs!$B$9,"0")&" weekly returns, ≈2 years)" -> Weekly, 09-Sep-2024 to 07-Sep-2026 (104 weekly returns, ≈2 years)
A10: Data frequency | B10: Weekly (Monday week-start), adjusted close
A11: Risk-free rate | B11: =RiskFree -> 0.0695
A12: Holdings / sectors | B12: 7 holdings across 7 sectors, static target weights, no rebalancing drift
A14: PORTFOLIO HOLDINGS & WEIGHTS
A15: # | B15: Ticker | C15: Company | D15: Sector | E15: Weight
A16: 1 | B16: RELIANCE.NS | C16: Reliance Industries | D16: Energy / Conglomerate | E16: =Holdings!$E$7 -> 0.23
A17: 2 | B17: BHARTIARTL.NS | C17: Bharti Airtel | D17: Telecom | E17: =Holdings!$E$8 -> 0.15
A18: 3 | B18: HDFCBANK.NS | C18: HDFC Bank | D18: Banking | E18: =Holdings!$E$9 -> 0.15
A19: 4 | B19: LT.NS | C19: Larsen & Toubro | D19: Industrials / Infrastructure | E19: =Holdings!$E$10 -> 0.14
A20: 5 | B20: CIPLA.NS | C20: Cipla | D20: Pharmaceuticals | E20: =Holdings!$E$11 -> 0.12
A21: 6 | B21: MARUTI.NS | C21: Maruti Suzuki | D21: Automobile | E21: =Holdings!$E$12 -> 0.12
A22: 7 | B22: HCLTECH.NS | C22: HCL Technologies | D22: Information Technology | E22: =Holdings!$E$13 -> 0.09
C23: TOTAL — must equal 100% | E23: =SUM(WeightsCol) -> 1 | G23: =IF(ROUND(SUM(WeightsCol),6)=1,"✓ PASS","✗ FAIL") -> ✓ PASS
A25: METRICS CALCULATED
A26: Return & risk | B26: Weekly return, annualised return (×52), annualised volatility (×√52), cumulative return and growth of ₹100 — for the portfolio and NIFTY 50 alike.
A27: Risk-adjusted | B27: Sharpe, Sortino and Treynor ratios on a documented, editable risk-free rate; beta, R² and CAPM-based Jensen's alpha vs NIFTY 50.
A28: Diversification & drawdown | B28: 7×7 correlation matrix on returns, running-peak drawdown engine, and return / risk contribution by holding via covariance decomposition.
A30: WORKBOOK NAVIGATION
A31: Overview | B31: This page — objective, holdings, methodology snapshot and navigation
A32: Inputs | B32: Every assumption and lever: risk-free rate, annualisation factor, data provenance
A33: Holdings | B33: Holdings table, weight check, sector allocation, full model quality checks
A34: Prices | B34: Rolling ~2-year dynamic price lookup layer (STOCKHISTORY-fed via Market_Data) — no calculations, no hardcoded prices
A35: Returns | B35: Weekly return series per security, benchmark and weighted portfolio — 100% formulas
A36: Risk_Analysis | B36: Return, volatility, Sharpe, Sortino, beta, alpha, Treynor, capture, per-security stats
A37: Correlation | B37: 7×7 matrix, ranked pairwise ladder, diversification diagnostics
A38: Drawdown | B38: Growth of ₹100, running peak and drawdown for portfolio and index
A39: Benchmark | B39: Head-to-head comparison, the six key questions, analyst commentary
A40: Contribution | B40: Return and risk attribution by holding
A41: Dashboard | B41: One-page premium factsheet — KPIs, charts, heatmap, insights
A43: MODEL ASSUMPTIONS
A44: Construction & costs | B44: Static target weights, no rebalancing drift, no transaction costs, taxes or dividend tax. Simple (not log) weekly returns; arithmetic annualisation (×52 / ×√52) shown alongside compounded cumulative return.
A45: Risk-free & benchmark | B45: Risk-free rate is a single editable input (India 10Y G-Sec, documented on Inputs) held constant over the window. NIFTY 50 price index is used, not the TRI — see limitations. Benchmark source is Power Query (primary, once set up — Market_Data §3) with a documented emergency static fallback, never STOCKHISTORY (tested, confirmed not to resolve for this index).
A47: LIMITATIONS
A48: Sample & regime risk | B48: Two years of weekly data is a short, single-regime sample; correlations measured here are a calm-market figure that compresses under stress. Beta and alpha are specific to this window.
A49: Excluded costs & bias | B49: Transaction costs, taxes and slippage are excluded; the NIFTY 50 TRI (not the price index used here) would be a harder, more realistic benchmark. Historical results do not predict future returns.
A51: MODEL STATUS
A52: Quality control | B52: =Holdings!$H$53 -> 0
A54: DATA STATUS
A55: Data source | B55: Equities: Microsoft STOCKHISTORY (Excel 365 connected stock data) — all 7 NSE-listed feeds confirmed resolving. Benchmark (NIFTY 50): Power Query pulling daily closes from Yahoo Finance into Market_Data W:X — set up and loading; it falls back to a labeled emergency static snapshot only if the query ever returns empty.
A56: Analysis window | B56: Rolling ~2 years — the date range itself moves forward every time the workbook recalculates (never a fixed range)
A57: Frequency | B57: Weekly
A58: Data mode | B58: Dynamic / Refreshable Portfolio Analytics Model — NOT real-time. Prices update on open/recalculation with an active Excel 365 + Microsoft 365 connection, not tick-by-tick.
A59: Benchmark (NIFTY 50) mode | B59: =IF(COUNT(Query1[Date])>0,"LIVE — Power Query pulling daily closes from Yahoo Finance (Market_Data W:X), aligned to the weekly axis; "&COUNT(Query1[Date])&" rows loaded.","EMERGENCY STATIC FALLBACK — the Yahoo Finance Power Query table is empty or not refreshed (see Market_Data W:X).") -> LIVE — Power Query pulling daily closes from Yahoo Finance (Market_Data W:X), aligned to the weekly axis; 105 rows loaded.
A60: Weekly observations currently loaded | B60: =Inputs!$B$8&" (of up to 130 buffered rows)" -> 105 (of up to 130 buffered rows)
A61: Latest weekly observation | B61: =TEXT(Inputs!$B$7,"dd-mmm-yyyy") -> 07-Sep-2026
A62: Oldest weekly observation (in window) | B62: =TEXT(Inputs!$B$6,"dd-mmm-yyyy") -> 09-Sep-2024
A63: Price data status | B63: =Holdings!$I$34 -> PASS
A64: Last recalculated | B64: Excel does not expose a stored recalculation timestamp to a formula; the workbook recalculates automatically whenever it is opened or F9 is pressed with a live Microsoft 365 connection. Check File > Info for the last-saved time as a proxy.
A65: DISCLAIMER
A66: Educational portfolio-analytics exercise on public historical market data. A MODEL portfolio only — not an actual holding, investment advice, or a recommendation. Data sourced from Yahoo Finance and Trading Economics, documented on the Inputs tab.

Sheet Inputs
A1: INPUTS & ASSUMPTIONS
A2: All model levers live here. Blue = hardcoded input you may edit · black = formula · green = link to another sheet.
A4: 1 · ANALYSIS PARAMETERS
A5: Parameter | B5: Value | C5: Unit | D5: Source / Basis
A6: Analysis start date | B6: =Prices!$A$4 -> 45544 | C6: date | D6: First weekly observation in source dataset
A7: Analysis end date | B7: =INDEX(Prices!$A$4:$A$133,COUNT(Prices!$A$4:$A$133)) -> 46272 | C7: date | D7: Last COMPLETED weekly observation (in-progress week excluded)
A8: Price observations | B8: =COUNT(Prices!$A$4:$A$133) -> 105 | C8: count | D8: Weekly closes per security, identical dates across all series
A9: Return observations | B9: =COUNT(PortRet) -> 104 | C9: count | D9: = price observations − 1
A10: Data frequency | B10: Weekly (Monday week-start) | C10: text | D10: Weekly reduces noise vs daily while retaining ~104 observations
A11: Periods per year | B11: 52 | C11: weeks | D11: Annualisation factor. Return × 52; volatility × SQRT(52)
A12: Growth index base | B12: 100 | C12: ₹ | D12: Both portfolio and benchmark growth series start at exactly ₹100
A13: Initial notional portfolio value | B13: 1000000 | C13: ₹ | D13: Editable input. Drives Holdings initial allocation (₹) and the weekly Portfolio Value series — NOT an actual investment
A14: Rebalancing assumption | B14: None — static target weights | C14: text | D14: Weights held constant every week; no drift, no transaction costs
A16: 2 · RISK-FREE RATE (editable — all Sharpe / Treynor / alpha outputs update)
A17: Parameter | B17: Value | C17: Unit | D17: Source / Basis
A18: Risk-free rate (annual) | B18: 0.0695 | C18: % p.a. | D18: India 10-Year Government Bond benchmark yield
A19: Rate as at | B19: 46272 | C19: date | D19: Latest quote available at time of build
A20: Source | B20: Trading Economics — India Government Bond 10Y | C20: text | D20: https://tradingeconomics.com/india/government-bond-yield
A21: Note | B21: This is an editable assumption, not a calculated output. Replace the yield above with your own sourced rate and every risk-adjusted metric in the workbook recalculates.
A23: 3 · MARKET DATA SOURCE
A24: Parameter | B24: Value | C24: Unit | D24: Source / Basis
A25: Data provider | B25: Yahoo Finance (chart API v8) | C25: text | D25: Retrieved programmatically; raw dataset preserved in data/prices_backup.csv
A26: Retrieved on | B26: 46273 | C26: date | D26: Snapshot date — dataset is static, not live-linked
A27: Price basis | B27: Adjusted close | C27: text | D27: Adjusted for splits and dividends — required for correct return series
A28: Currency | B28: INR (₹) | C28: text | D28: All securities and the benchmark quote in INR
A29: Exchange | B29: NSE (National Stock Exchange of India) | C29: text | D29: Yahoo suffix .NS
A30: Benchmark | B30: NIFTY 50 (^NSEI) | C30: text | D30: Price index level; NIFTY 50 TRI not used — see limitations
A31: Date alignment | B31: Identical weekly dates across all 8 series | C31: text | D31: Intersection of week-start dates; no forward-filling applied
A33: 4 · CORRELATION INTERPRETATION BANDS
A34: Band | B34: Threshold | C34: Unit | D34: Interpretation
A35: Potentially poor diversification | B35: 0.8 | C35: ρ > | D35: Pair behaves close to a single bet — review for redundancy
A36: Moderate / high relationship | B36: 0.5 | C36: ρ > | D36: Meaningful shared risk driver
A37: Moderate relationship | B37: 0.3 | C37: ρ > | D37: Some shared exposure, still diversifying
A38: Stronger diversification benefit | B38: 0.3 | C38: ρ < | D38: Largely independent return drivers
A40: 5 · FORMATTING CONVENTIONS
A41: Blue font | B41: Hardcoded input or assumption — safe to edit
A42: Black font | B42: Formula calculated within the sheet
A43: Green font | B43: Link to another sheet in this workbook

Sheet Holdings
A1: HOLDINGS — PORTFOLIO CONSTRUCTION
A2: Model portfolio: 7 NSE-listed large caps across 7 sectors, held at fixed target weights. No personal purchase prices or units are assumed.
A4: 1 · HOLDINGS TABLE
A6: # | B6: Ticker | C6: Company | D6: Sector | E6: Target Weight | F6: Latest Price (₹) | G6: Period Return | H6: Annualised Return | I6: Initial Allocation (₹) | J6: Contribution to Period Return
A7: 1 | B7: RELIANCE.NS | C7: Reliance Industries | D7: Energy / Conglomerate | E7: 0.23 | F7: =INDEX(Prices!$B$4:$B$1000,COUNT(Prices!$A$4:$A$1000)) -> 1309.5 | G7: {=IFERROR(INDEX(Prices!$B$4:$B$1000,COUNT(Prices!$A$4:$A$1000))/Prices!$B$4-1,"")} -> -0.11077158 | H7: =Returns!B$1004 -> -0.035825572 | I7: =$E7*NotionalValue -> 230000 | J7: =$E7*$G7 -> -0.025477464
A8: 2 | B8: BHARTIARTL.NS | C8: Bharti Airtel | D8: Telecom | E8: 0.15 | F8: =INDEX(Prices!$C$4:$C$1000,COUNT(Prices!$A$4:$A$1000)) -> 1854 | G8: {=IFERROR(INDEX(Prices!$C$4:$C$1000,COUNT(Prices!$A$4:$A$1000))/Prices!$C$4-1,"")} -> 0.13432653 | H8: =Returns!C$1004 -> 0.081444945 | I8: =$E8*NotionalValue -> 150000 | J8: =$E8*$G8 -> 0.02014898
A9: 3 | B9: HDFCBANK.NS | C9: HDFC Bank | D9: Banking | E9: 0.15 | F9: =INDEX(Prices!$D$4:$D$1000,COUNT(Prices!$A$4:$A$1000)) -> 710.5 | G9: {=IFERROR(INDEX(Prices!$D$4:$D$1000,COUNT(Prices!$A$4:$A$1000))/Prices!$D$4-1,"")} -> -0.14491258 | H9: =Returns!D$1004 -> -0.060606364 | I9: =$E9*NotionalValue -> 150000 | J9: =$E9*$G9 -> -0.021736888
A10: 4 | B10: LT.NS | C10: Larsen & Toubro | D10: Industrials / Infrastructure | E10: 0.14 | F10: =INDEX(Prices!$E$4:$E$1000,COUNT(Prices!$A$4:$A$1000)) -> 3999 | G10: {=IFERROR(INDEX(Prices!$E$4:$E$1000,COUNT(Prices!$A$4:$A$1000))/Prices!$E$4-1,"")} -> 0.10683642 | H10: =Returns!E$1004 -> 0.084524854 | I10: =$E10*NotionalValue -> 140000 | J10: =$E10*$G10 -> 0.014957099
A11: 5 | B11: CIPLA.NS | C11: Cipla | D11: Pharmaceuticals | E11: 0.12 | F11: =INDEX(Prices!$F$4:$F$1000,COUNT(Prices!$A$4:$A$1000)) -> 1395 | G11: {=IFERROR(INDEX(Prices!$F$4:$F$1000,COUNT(Prices!$A$4:$A$1000))/Prices!$F$4-1,"")} -> -0.15948665 | H11: =Returns!F$1004 -> -0.069387743 | I11: =$E11*NotionalValue -> 120000 | J11: =$E11*$G11 -> -0.019138399
A12: 6 | B12: MARUTI.NS | C12: Maruti Suzuki | D12: Automobile | E12: 0.12 | F12: =INDEX(Prices!$G$4:$G$1000,COUNT(Prices!$A$4:$A$1000)) -> 12760 | G12: {=IFERROR(INDEX(Prices!$G$4:$G$1000,COUNT(Prices!$A$4:$A$1000))/Prices!$G$4-1,"")} -> 0.03604646 | H12: =Returns!G$1004 -> 0.04689393 | I12: =$E12*NotionalValue -> 120000 | J12: =$E12*$G12 -> 0.0043255752
A13: 7 | B13: HCLTECH.NS | C13: HCL Technologies | D13: Information Technology | E13: 0.09 | F13: =INDEX(Prices!$H$4:$H$1000,COUNT(Prices!$A$4:$A$1000)) -> 1282.8 | G13: {=IFERROR(INDEX(Prices!$H$4:$H$1000,COUNT(Prices!$A$4:$A$1000))/Prices!$H$4-1,"")} -> -0.28998685 | H13: =Returns!H$1004 -> -0.12948856 | I13: =$E13*NotionalValue -> 90000 | J13: =$E13*$G13 -> -0.026098816
B14: TOTAL PORTFOLIO | E14: =SUM(E7:E13) -> 1 | I14: =SUM(I7:I13) -> 1000000 | J14: =SUM(J7:J13) -> -0.053019912
B16: WEIGHT CHECK | D16: =SUM(WeightsCol) -> 1 | E16: =IF(ROUND(SUM(WeightsCol),6)=1,"✓ PASS — weights sum to exactly 100%","✗ FAIL — weights sum to "&TEXT(SUM(WeightsCol),"0.00%")&", must equal 100%") -> ✓ PASS — weights sum to exactly 100%
A18: 2 · SECTOR ALLOCATION
D19: Sector | E19: Holdings | F19: Weight | G19: Notional (₹)
D20: Energy / Conglomerate | E20: =COUNTIF($D$7:$D$13,$D20) -> 1 | F20: =SUMIF($D$7:$D$13,$D20,$E$7:$E$13) -> 0.23 | G20: =$F20*NotionalValue -> 230000
D21: Telecom | E21: =COUNTIF($D$7:$D$13,$D21) -> 1 | F21: =SUMIF($D$7:$D$13,$D21,$E$7:$E$13) -> 0.15 | G21: =$F21*NotionalValue -> 150000
D22: Banking | E22: =COUNTIF($D$7:$D$13,$D22) -> 1 | F22: =SUMIF($D$7:$D$13,$D22,$E$7:$E$13) -> 0.15 | G22: =$F22*NotionalValue -> 150000
D23: Industrials / Infrastructure | E23: =COUNTIF($D$7:$D$13,$D23) -> 1 | F23: =SUMIF($D$7:$D$13,$D23,$E$7:$E$13) -> 0.14 | G23: =$F23*NotionalValue -> 140000
D24: Pharmaceuticals | E24: =COUNTIF($D$7:$D$13,$D24) -> 1 | F24: =SUMIF($D$7:$D$13,$D24,$E$7:$E$13) -> 0.12 | G24: =$F24*NotionalValue -> 120000
D25: Automobile | E25: =COUNTIF($D$7:$D$13,$D25) -> 1 | F25: =SUMIF($D$7:$D$13,$D25,$E$7:$E$13) -> 0.12 | G25: =$F25*NotionalValue -> 120000
D26: Information Technology | E26: =COUNTIF($D$7:$D$13,$D26) -> 1 | F26: =SUMIF($D$7:$D$13,$D26,$E$7:$E$13) -> 0.09 | G26: =$F26*NotionalValue -> 90000
D27: TOTAL | E27: =SUM(E20:E26) -> 7 | F27: =SUM(F20:F26) -> 1 | G27: =SUM(G20:G26) -> 1000000
A29: 3 · MODEL QUALITY CHECKS
A30: # | B30: Check | G30: Value | I30: Result
A31: 1 | B31: Portfolio weights sum to exactly 100% | G31: =SUM(WeightsCol) -> 1 | I31: =IF(ROUND(SUM(WeightsCol),6)=1,"PASS","FAIL") -> PASS
A32: 2 | B32: All 7 holdings present | G32: =COUNTA($B$7:$B$13) -> 7 | I32: =IF(COUNTA($B$7:$B$13)=7,"PASS","FAIL") -> PASS
A33: 3 | B33: Price observations ≥ 100 (approx. 2 years weekly) | G33: =COUNT(Prices!$A$4:$A$1000) -> 105 | I33: =IF(COUNT(Prices!$A$4:$A$1000)>=100,"PASS","FAIL") -> PASS
A34: 4 | B34: No missing price observations within the populated window (blank cells) | G34: =COUNTBLANK(Prices!$B$4:$I$1000)-COUNTBLANK(Prices!$A$4:$A$1000)*8 -> 0 | I34: =IF(G34=0,"PASS","FAIL") -> PASS
A35: 5 | B35: Price dates aligned and strictly ascending | G35: {=SUMPRODUCT(--(Prices!$A$5:INDEX(Prices!$A$4:$A$1000,COUNT(Prices!$A$4:$A$1000))<=Prices!$A$4:INDEX(Prices!$A$4:$A$1000,COUNT(Prices!$A$4:$A$1000)-1)))} -> 0 | I35: =IF(G35=0,"PASS","FAIL") -> PASS
A36: 6 | B36: Return observations = price observations − 1 | G36: =COUNT(PortRet) -> 104 | I36: =IF(COUNT(PortRet)=COUNT(Prices!$A$4:$A$1000)-1,"PASS","FAIL") -> PASS
A37: 7 | B37: Benchmark observations aligned with portfolio | G37: =COUNT(BenchRet) -> 104 | I37: =IF(COUNT(BenchRet)=COUNT(PortRet),"PASS","FAIL") -> PASS
A38: 8 | B38: Portfolio return uses target weights (recomputed independently) | G38: =SUMPRODUCT(Weights,Returns!$B$6:$H$6)-Returns!$J$6 -> 0 | I38: =IF(ABS(SUMPRODUCT(Weights,Returns!$B$6:$H$6)-Returns!$J$6)<0.0000000001,"PASS","FAIL") -> PASS
A39: 9 | B39: Growth of ₹100 series both start at exactly 100 | G39: =Drawdown!$C$7+Drawdown!$G$7 -> 200 | I39: =IF(AND(Drawdown!$C$7=100,Drawdown!$G$7=100),"PASS","FAIL") -> PASS
A40: 10 | B40: Cumulative return reconciles to growth index | G40: =Risk_Analysis!$B$11-(INDEX(Drawdown!$C$8:$C$1000,COUNT(Drawdown!$A$8:$A$1000))/100-1) -> 0 | I40: =IF(ABS(Risk_Analysis!$B$11-(INDEX(Drawdown!$C$8:$C$1000,COUNT(Drawdown!$A$8:$A$1000))/100-1))<0.0000000001,"PASS","FAIL") -> PASS
A41: 11 | B41: Maximum drawdown is negative or zero | G41: =Risk_Analysis!$B$35 -> -0.17991189 | I41: =IF(Risk_Analysis!$B$35<=0,"PASS","FAIL") -> PASS
A42: 12 | B42: Correlation matrix diagonal equals 1.00 | G42: =SUM(Correlation!$B$7,Correlation!$C$8,Correlation!$D$9,Correlation!$E$10,Correlation!$F$11,Correlation!$G$12,Correlation!$H$13) -> 7 | I42: =IF(ROUND(SUM(Correlation!$B$7,Correlation!$C$8,Correlation!$D$9,Correlation!$E$10,Correlation!$F$11,Correlation!$G$12,Correlation!$H$13),6)=7,"PASS","FAIL") -> PASS
A43: 13 | B43: Correlation matrix symmetric (sum = 7 + 2 x sum of 21 unique pairs) | G43: =SUM(Correlation!$B$7:$H$13)-(7+2*SUM(Correlation!$F$17:$F$37)) -> 0 | I43: =IF(ABS(SUM(Correlation!$B$7:$H$13)-(7+2*SUM(Correlation!$F$17:$F$37)))<0.000001,"PASS","FAIL") -> PASS
A44: 14 | B44: Return contributions sum to portfolio annualised return | G44: =Contribution!$D$14 -> 0 | I44: =IF(ABS(Contribution!$D$14)<0.000001,"PASS","FAIL") -> PASS
A45: 15 | B45: Risk contributions sum to portfolio variance | G45: =Contribution!$E$36 -> 0 | I45: =IF(ABS(Contribution!$E$36)<0.0000001,"PASS","FAIL") -> PASS
A46: 16 | B46: Sector weights reconcile to holding weights | G46: =$F$27-SUM(WeightsCol) -> 0 | I46: =IF(ABS($F$27-SUM(WeightsCol))<0.000001,"PASS","FAIL") -> PASS
A47: 17 | B47: No errors anywhere in the return series | G47: {=SUMPRODUCT(--ISERROR(Returns!$B$6:$J$1000))} -> 0 | I47: {=IF(SUMPRODUCT(--ISERROR(Returns!$B$6:$J$1000))=0,"PASS","FAIL")} -> PASS
A48: 18 | B48: No errors in the drawdown engine | G48: {=SUMPRODUCT(--ISERROR(Drawdown!$B$8:$I$1000))} -> 0 | I48: {=IF(SUMPRODUCT(--ISERROR(Drawdown!$B$8:$I$1000))=0,"PASS","FAIL")} -> PASS
A49: 19 | B49: Risk-free rate is a documented input, not a hardcoded constant | G49: =RiskFree -> 0.0695 | I49: =IF(AND(RiskFree>0,RiskFree<0.2),"PASS","FAIL") -> PASS
A50: 20 | B50: All 7 stock STOCKHISTORY feeds resolving (Market_Data) | G50: =--(Market_Data!B$20="Date")+--(Market_Data!E$20="Date")+--(Market_Data!H$20="Date")+--(Market_Data!K$20="Date")+--(Market_Data!N$20="Date")+--(Market_Data!Q$20="Date")+--(Market_Data!T$20="Date") -> 7 | I50: =IF((--(Market_Data!B$20="Date")+--(Market_Data!E$20="Date")+--(Market_Data!H$20="Date")+--(Market_Data!K$20="Date")+--(Market_Data!N$20="Date")+--(Market_Data!Q$20="Date")+--(Market_Data!T$20="Date"))=7,"PASS","FAIL — see Market_Data status notes; expected blank/FAIL outside Excel 365 with a live Microsoft 365 connection") -> PASS
A51: 21 | B51: NIFTY 50 benchmark mode is explicitly documented (not silently guessed) | G51: =IF(COUNT(Query1[Date])>0,"LIVE — Power Query / Yahoo Finance (Market_Data W:X)","EMERGENCY STATIC FALLBACK") -> LIVE — Power Query / Yahoo Finance (Market_Data W:X) | I51: =IF($G$51<>"","PASS","FAIL") -> PASS
A52: 22 | B52: NIFTY 50 Yahoo Finance Power Query source is live (not the emergency static fallback) | G52: =--(COUNT(Query1[Date])>0) -> 1 | I52: =IF($G$52=1,"PASS — Yahoo Finance Power Query table resolving","EMERGENCY FALLBACK — Yahoo Finance Power Query table empty or not refreshed (see Market_Data W:X)") -> PASS — Yahoo Finance Power Query table resolving
B53: OVERALL MODEL STATUS | G53: =COUNTIF($I$31:$I$52,"PASS*")&" / 22" -> 22 / 22 | I53: =IF(COUNTIF($I$31:$I$52,"PASS*")=22,"✓ ALL CHECKS PASS","✗ "&COUNTIF($I$31:$I$52,"FAIL*")&" CHECK(S) FAILING — see column I") -> ✓ ALL CHECKS PASS

Sheet Prices
A1: PRICES
A2: Ticker → | B2: RELIANCE.NS | C2: BHARTIARTL.NS | D2: HDFCBANK.NS | E2: LT.NS | F2: CIPLA.NS | G2: MARUTI.NS | H2: HCLTECH.NS | I2: ^NSEI
A3: Date | B3: Reliance Industries | C3: Bharti Airtel | D3: HDFC Bank | E3: Larsen & Toubro | F3: Cipla | G3: Maruti Suzuki | H3: HCL Technologies | I3: NIFTY 50
A4: =(TODAY()-730)-WEEKDAY(TODAY()-730,2)+1 -> 45544 | B4: =IF($A4="","",IFERROR(INDEX(Market_Data!$C$21:$C$613,MATCH($A4,Market_Data!$B$21:INDEX(Market_Data!$B$21:$B$613,COUNT(Market_Data!$B$21:$B$613)),1)),"")) -> 1472.625 | C4: =IF($A4="","",IFERROR(INDEX(Market_Data!$F$21:$F$613,MATCH($A4,Market_Data!$E$21:INDEX(Market_Data!$E$21:$E$613,COUNT(Market_Data!$E$21:$E$613)),1)),"")) -> 1634.45 | D4: =IF($A4="","",IFERROR(INDEX(Market_Data!$I$21:$I$613,MATCH($A4,Market_Data!$H$21:INDEX(Market_Data!$H$21:$H$613,COUNT(Market_Data!$H$21:$H$613)),1)),"")) -> 830.9092 | E4: =IF($A4="","",IFERROR(INDEX(Market_Data!$L$21:$L$613,MATCH($A4,Market_Data!$K$21:INDEX(Market_Data!$K$21:$K$613,COUNT(Market_Data!$K$21:$K$613)),1)),"")) -> 3613 | F4: =IF($A4="","",IFERROR(INDEX(Market_Data!$O$21:$O$613,MATCH($A4,Market_Data!$N$21:INDEX(Market_Data!$N$21:$N$613,COUNT(Market_Data!$N$21:$N$613)),1)),"")) -> 1659.7 | G4: =IF($A4="","",IFERROR(INDEX(Market_Data!$R$21:$R$613,MATCH($A4,Market_Data!$Q$21:INDEX(Market_Data!$Q$21:$Q$613,COUNT(Market_Data!$Q$21:$Q$613)),1)),"")) -> 12316.05 | H4: =IF($A4="","",IFERROR(INDEX(Market_Data!$U$21:$U$613,MATCH($A4,Market_Data!$T$21:INDEX(Market_Data!$T$21:$T$613,COUNT(Market_Data!$T$21:$T$613)),1)),"")) -> 1806.7271 | I4: =IF($A4="","",IFERROR(INDEX(Query1[Close],MATCH($A4,Query1[Date],1)),"")) -> 24936.4
A5: =IF($A4="","",IF($A4+7<=TODAY(),$A4+7,"")) -> 45551 | B5: =IF($A5="","",IFERROR(INDEX(Market_Data!$C$21:$C$613,MATCH($A5,Market_Data!$B$21:INDEX(Market_Data!$B$21:$B$613,COUNT(Market_Data!$B$21:$B$613)),1)),"")) -> 1485.925 | C5: =IF($A5="","",IFERROR(INDEX(Market_Data!$F$21:$F$613,MATCH($A5,Market_Data!$E$21:INDEX(Market_Data!$E$21:$E$613,COUNT(Market_Data!$E$21:$E$613)),1)),"")) -> 1711.75 | D5: =IF($A5="","",IFERROR(INDEX(Market_Data!$I$21:$I$613,MATCH($A5,Market_Data!$H$21:INDEX(Market_Data!$H$21:$H$613,COUNT(Market_Data!$H$21:$H$613)),1)),"")) -> 868.4409 | E5: =IF($A5="","",IFERROR(INDEX(Market_Data!$L$21:$L$613,MATCH($A5,Market_Data!$K$21:INDEX(Market_Data!$K$21:$K$613,COUNT(Market_Data!$K$21:$K$613)),1)),"")) -> 3793.9 | F5: =IF($A5="","",IFERROR(INDEX(Market_Data!$O$21:$O$613,MATCH($A5,Market_Data!$N$21:INDEX(Market_Data!$N$21:$N$613,COUNT(Market_Data!$N$21:$N$613)),1)),"")) -> 1638.65 | G5: =IF($A5="","",IFERROR(INDEX(Market_Data!$R$21:$R$613,MATCH($A5,Market_Data!$Q$21:INDEX(Market_Data!$Q$21:$Q$613,COUNT(Market_Data!$Q$21:$Q$613)),1)),"")) -> 12614.5 | H5: =IF($A5="","",IFERROR(INDEX(Market_Data!$U$21:$U$613,MATCH($A5,Market_Data!$T$21:INDEX(Market_Data!$T$21:$T$613,COUNT(Market_Data!$T$21:$T$613)),1)),"")) -> 1754.1538 | I5: =IF($A5="","",IFERROR(INDEX(Query1[Close],MATCH($A5,Query1[Date],1)),"")) -> 25383.75
A6: =IF($A5="","",IF($A5+7<=TODAY(),$A5+7,"")) -> 45558 | B6: =IF($A6="","",IFERROR(INDEX(Market_Data!$C$21:$C$613,MATCH($A6,Market_Data!$B$21:INDEX(Market_Data!$B$21:$B$613,COUNT(Market_Data!$B$21:$B$613)),1)),"")) -> 1526.175 | C6: =IF($A6="","",IFERROR(INDEX(Market_Data!$F$21:$F$613,MATCH($A6,Market_Data!$E$21:INDEX(Market_Data!$E$21:$E$613,COUNT(Market_Data!$E$21:$E$613)),1)),"")) -> 1734.6 | D6: =IF($A6="","",IFERROR(INDEX(Market_Data!$I$21:$I$613,MATCH($A6,Market_Data!$H$21:INDEX(Market_Data!$H$21:$H$613,COUNT(Market_Data!$H$21:$H$613)),1)),"")) -> 874.1517 | E6: =IF($A6="","",IFERROR(INDEX(Market_Data!$L$21:$L$613,MATCH($A6,Market_Data!$K$21:INDEX(Market_Data!$K$21:$K$613,COUNT(Market_Data!$K$21:$K$613)),1)),"")) -> 3705.65 | F6: =IF($A6="","",IFERROR(INDEX(Market_Data!$O$21:$O$613,MATCH($A6,Market_Data!$N$21:INDEX(Market_Data!$N$21:$N$613,COUNT(Market_Data!$N$21:$N$613)),1)),"")) -> 1672.5 | G6: =IF($A6="","",IFERROR(INDEX(Market_Data!$R$21:$R$613,MATCH($A6,Market_Data!$Q$21:INDEX(Market_Data!$Q$21:$Q$613,COUNT(Market_Data!$Q$21:$Q$613)),1)),"")) -> 13495.6 | H6: =IF($A6="","",IFERROR(INDEX(Market_Data!$U$21:$U$613,MATCH($A6,Market_Data!$T$21:INDEX(Market_Data!$T$21:$T$613,COUNT(Market_Data!$T$21:$T$613)),1)),"")) -> 1802.3419 | I6: =IF($A6="","",IFERROR(INDEX(Query1[Close],MATCH($A6,Query1[Date],1)),"")) -> 25939.051
A7: =IF($A6="","",IF($A6+7<=TODAY(),$A6+7,"")) -> 45565 | B7: =IF($A7="","",IFERROR(INDEX(Market_Data!$C$21:$C$613,MATCH($A7,Market_Data!$B$21:INDEX(Market_Data!$B$21:$B$613,COUNT(Market_Data!$B$21:$B$613)),1)),"")) -> 1386.525 | C7: =IF($A7="","",IFERROR(INDEX(Market_Data!$F$21:$F$613,MATCH($A7,Market_Data!$E$21:INDEX(Market_Data!$E$21:$E$613,COUNT(Market_Data!$E$21:$E$613)),1)),"")) -> 1640.9 | D7: =IF($A7="","",IFERROR(INDEX(Market_Data!$I$21:$I$613,MATCH($A7,Market_Data!$H$21:INDEX(Market_Data!$H$21:$H$613,COUNT(Market_Data!$H$21:$H$613)),1)),"")) -> 826.7695 | E7: =IF($A7="","",IFERROR(INDEX(Market_Data!$L$21:$L$613,MATCH($A7,Market_Data!$K$21:INDEX(Market_Data!$K$21:$K$613,COUNT(Market_Data!$K$21:$K$613)),1)),"")) -> 3493.95 | F7: =IF($A7="","",IFERROR(INDEX(Market_Data!$O$21:$O$613,MATCH($A7,Market_Data!$N$21:INDEX(Market_Data!$N$21:$N$613,COUNT(Market_Data!$N$21:$N$613)),1)),"")) -> 1623.3 | G7: =IF($A7="","",IFERROR(INDEX(Market_Data!$R$21:$R$613,MATCH($A7,Market_Data!$Q$21:INDEX(Market_Data!$Q$21:$Q$613,COUNT(Market_Data!$Q$21:$Q$613)),1)),"")) -> 12605.75 | H7: =IF($A7="","",IFERROR(INDEX(Market_Data!$U$21:$U$613,MATCH($A7,Market_Data!$T$21:INDEX(Market_Data!$T$21:$T$613,COUNT(Market_Data!$T$21:$T$613)),1)),"")) -> 1770.6484 | I7: =IF($A7="","",IFERROR(INDEX(Query1[Close],MATCH($A7,Query1[Date],1)),"")) -> 25810.85
A8: =IF($A7="","",IF($A7+7<=TODAY(),$A7+7,"")) -> 45572 | B8: =IF($A8="","",IFERROR(INDEX(Market_Data!$C$21:$C$613,MATCH($A8,Market_Data!$B$21:INDEX(Market_Data!$B$21:$B$613,COUNT(Market_Data!$B$21:$B$613)),1)),"")) -> 1372.1 | C8: =IF($A8="","",IFERROR(INDEX(Market_Data!$F$21:$F$613,MATCH($A8,Market_Data!$E$21:INDEX(Market_Data!$E$21:$E$613,COUNT(Market_Data!$E$21:$E$613)),1)),"")) -> 1687.4 | D8: =IF($A8="","",IFERROR(INDEX(Market_Data!$I$21:$I$613,MATCH($A8,Market_Data!$H$21:INDEX(Market_Data!$H$21:$H$613,COUNT(Market_Data!$H$21:$H$613)),1)),"")) -> 823.4528 | E8: =IF($A8="","",IFERROR(INDEX(Market_Data!$L$21:$L$613,MATCH($A8,Market_Data!$K$21:INDEX(Market_Data!$K$21:$K$613,COUNT(Market_Data!$K$21:$K$613)),1)),"")) -> 3482.55 | F8: =IF($A8="","",IFERROR(INDEX(Market_Data!$O$21:$O$613,MATCH($A8,Market_Data!$N$21:INDEX(Market_Data!$N$21:$N$613,COUNT(Market_Data!$N$21:$N$613)),1)),"")) -> 1595.75 | G8: =IF($A8="","",IFERROR(INDEX(Market_Data!$R$21:$R$613,MATCH($A8,Market_Data!$Q$21:INDEX(Market_Data!$Q$21:$Q$613,COUNT(Market_Data!$Q$21:$Q$613)),1)),"")) -> 12776.65 | H8: =IF($A8="","",IFERROR(INDEX(Market_Data!$U$21:$U$613,MATCH($A8,Market_Data!$T$21:INDEX(Market_Data!$T$21:$T$613,COUNT(Market_Data!$T$21:$T$613)),1)),"")) -> 1833.4872 | I8: =IF($A8="","",IFERROR(INDEX(Query1[Close],MATCH($A8,Query1[Date],1)),"")) -> 24795.75
A9: =IF($A8="","",IF($A8+7<=TODAY(),$A8+7,"")) -> 45579 | B9: =IF($A9="","",IFERROR(INDEX(Market_Data!$C$21:$C$613,MATCH($A9,Market_Data!$B$21:INDEX(Market_Data!$B$21:$B$613,COUNT(Market_Data!$B$21:$B$613)),1)),"")) -> 1359.3 | C9: =IF($A9="","",IFERROR(INDEX(Market_Data!$F$21:$F$613,MATCH($A9,Market_Data!$E$21:INDEX(Market_Data!$E$21:$E$613,COUNT(Market_Data!$E$21:$E$613)),1)),"")) -> 1707.85 | D9: =IF($A9="","",IFERROR(INDEX(Market_Data!$I$21:$I$613,MATCH($A9,Market_Data!$H$21:INDEX(Market_Data!$H$21:$H$613,COUNT(Market_Data!$H$21:$H$613)),1)),"")) -> 838.8395 | E9: =IF($A9="","",IFERROR(INDEX(Market_Data!$L$21:$L$613,MATCH($A9,Market_Data!$K$21:INDEX(Market_Data!$K$21:$K$613,COUNT(Market_Data!$K$21:$K$613)),1)),"")) -> 3577.8 | F9: =IF($A9="","",IFERROR(INDEX(Market_Data!$O$21:$O$613,MATCH($A9,Market_Data!$N$21:INDEX(Market_Data!$N$21:$N$613,COUNT(Market_Data!$N$21:$N$613)),1)),"")) -> 1551.7 | G9: =IF($A9="","",IFERROR(INDEX(Market_Data!$R$21:$R$613,MATCH($A9,Market_Data!$Q$21:INDEX(Market_Data!$Q$21:$Q$613,COUNT(Market_Data!$Q$21:$Q$613)),1)),"")) -> 12105.1 | H9: =IF($A9="","",IFERROR(INDEX(Market_Data!$U$21:$U$613,MATCH($A9,Market_Data!$T$21:INDEX(Market_Data!$T$21:$T$613,COUNT(Market_Data!$T$21:$T$613)),1)),"")) -> 1851.4767 | I9: =IF($A9="","",IFERROR(INDEX(Query1[Close],MATCH($A9,Query1[Date],1)),"")) -> 25127.949
A10: =IF($A9="","",IF($A9+7<=TODAY(),$A9+7,"")) -> 45586 | B10: =IF($A10="","",IFERROR(INDEX(Market_Data!$C$21:$C$613,MATCH($A10,Market_Data!$B$21:INDEX(Market_Data!$B$21:$B$613,COUNT(Market_Data!$B$21:$B$613)),1)),"")) -> 1327.85 | C10: =IF($A10="","",IFERROR(INDEX(Market_Data!$F$21:$F$613,MATCH($A10,Market_Data!$E$21:INDEX(Market_Data!$E$21:$E$613,COUNT(Market_Data!$E$21:$E$613)),1)),"")) -> 1666 | D10: =IF($A10="","",IFERROR(INDEX(Market_Data!$I$21:$I$613,MATCH($A10,Market_Data!$H$21:INDEX(Market_Data!$H$21:$H$613,COUNT(Market_Data!$H$21:$H$613)),1)),"")) -> 869.5382 | E10: =IF($A10="","",IFERROR(INDEX(Market_Data!$L$21:$L$613,MATCH($A10,Market_Data!$K$21:INDEX(Market_Data!$K$21:$K$613,COUNT(Market_Data!$K$21:$K$613)),1)),"")) -> 3326.4 | F10: =IF($A10="","",IFERROR(INDEX(Market_Data!$O$21:$O$613,MATCH($A10,Market_Data!$N$21:INDEX(Market_Data!$N$21:$N$613,COUNT(Market_Data!$N$21:$N$613)),1)),"")) -> 1488.9 | G10: =IF($A10="","",IFERROR(INDEX(Market_Data!$R$21:$R$613,MATCH($A10,Market_Data!$Q$21:INDEX(Market_Data!$Q$21:$Q$613,COUNT(Market_Data!$Q$21:$Q$613)),1)),"")) -> 11502.85 | H10: =IF($A10="","",IFERROR(INDEX(Market_Data!$U$21:$U$613,MATCH($A10,Market_Data!$T$21:INDEX(Market_Data!$T$21:$T$613,COUNT(Market_Data!$T$21:$T$613)),1)),"")) -> 1846.1446 | I10: =IF($A10="","",IFERROR(INDEX(Query1[Close],MATCH($A10,Query1[Date],1)),"")) -> 24781.1
A11: =IF($A10="","",IF($A10+7<=TODAY(),$A10+7,"")) -> 45593 | B11: =IF($A11="","",IFERROR(INDEX(Market_Data!$C$21:$C$613,MATCH($A11,Market_Data!$B$21:INDEX(Market_Data!$B$21:$B$613,COUNT(Market_Data!$B$21:$B$613)),1)),"")) -> 1338.65 | C11: =IF($A11="","",IFERROR(INDEX(Market_Data!$F$21:$F$613,MATCH($A11,Market_Data!$E$21:INDEX(Market_Data!$E$21:$E$613,COUNT(Market_Data!$E$21:$E$613)),1)),"")) -> 1616.45 | D11: =IF($A11="","",IFERROR(INDEX(Market_Data!$I$21:$I$613,MATCH($A11,Market_Data!$H$21:INDEX(Market_Data!$H$21:$H$613,COUNT(Market_Data!$H$21:$H$613)),1)),"")) -> 866.4957 | E11: =IF($A11="","",IFERROR(INDEX(Market_Data!$L$21:$L$613,MATCH($A11,Market_Data!$K$21:INDEX(Market_Data!$K$21:$K$613,COUNT(Market_Data!$K$21:$K$613)),1)),"")) -> 3626.35 | F11: =IF($A11="","",IFERROR(INDEX(Market_Data!$O$21:$O$613,MATCH($A11,Market_Data!$N$21:INDEX(Market_Data!$N$21:$N$613,COUNT(Market_Data!$N$21:$N$613)),1)),"")) -> 1559.55 | G11: =IF($A11="","",IFERROR(INDEX(Market_Data!$R$21:$R$613,MATCH($A11,Market_Data!$Q$21:INDEX(Market_Data!$Q$21:$Q$613,COUNT(Market_Data!$Q$21:$Q$613)),1)),"")) -> 11110 | H11: =IF($A11="","",IFERROR(INDEX(Market_Data!$U$21:$U$613,MATCH($A11,Market_Data!$T$21:INDEX(Market_Data!$T$21:$T$613,COUNT(Market_Data!$T$21:$T$613)),1)),"")) -> 1751.5127 | I11: =IF($A11="","",IFERROR(INDEX(Query1[Close],MATCH($A11,Query1[Date],1)),"")) -> 24339.15
A12: =IF($A11="","",IF($A11+7<=TODAY(),$A11+7,"")) -> 45600 | B12: =IF($A12="","",IFERROR(INDEX(Market_Data!$C$21:$C$613,MATCH($A12,Market_Data!$B$21:INDEX(Market_Data!$B$21:$B$613,COUNT(Market_Data!$B$21:$B$613)),1)),"")) -> 1283.75 | C12: =IF($A12="","",IFERROR(INDEX(Market_Data!$F$21:$F$613,MATCH($A12,Market_Data!$E$21:INDEX(Market_Data!$E$21:$E$613,COUNT(Market_Data!$E$21:$E$613)),1)),"")) -> 1569.9 | D12: =IF($A12="","",IFERROR(INDEX(Market_Data!$I$21:$I$613,MATCH($A12,Market_Data!$H$21:INDEX(Market_Data!$H$21:$H$613,COUNT(Market_Data!$H$21:$H$613)),1)),"")) -> 875.0495 | E12: =IF($A12="","",IFERROR(INDEX(Market_Data!$L$21:$L$613,MATCH($A12,Market_Data!$K$21:INDEX(Market_Data!$K$21:$K$613,COUNT(Market_Data!$K$21:$K$613)),1)),"")) -> 3660.3 | F12: =IF($A12="","",IFERROR(INDEX(Market_Data!$O$21:$O$613,MATCH($A12,Market_Data!$N$21:INDEX(Market_Data!$N$21:$N$613,COUNT(Market_Data!$N$21:$N$613)),1)),"")) -> 1592.6 | G12: =IF($A12="","",IFERROR(INDEX(Market_Data!$R$21:$R$613,MATCH($A12,Market_Data!$Q$21:INDEX(Market_Data!$Q$21:$Q$613,COUNT(Market_Data!$Q$21:$Q$613)),1)),"")) -> 11303 | H12: =IF($A12="","",IFERROR(INDEX(Market_Data!$U$21:$U$613,MATCH($A12,Market_Data!$T$21:INDEX(Market_Data!$T$21:$T$613,COUNT(Market_Data!$T$21:$T$613)),1)),"")) -> 1831.3444 | I12: =IF($A12="","",IFERROR(INDEX(Query1[Close],MATCH($A12,Query1[Date],1)),"")) -> 23995.35
A13: =IF($A12="","",IF($A12+7<=TODAY(),$A12+7,"")) -> 45607 | B13: =IF($A13="","",IFERROR(INDEX(Market_Data!$C$21:$C$613,MATCH($A13,Market_Data!$B$21:INDEX(Market_Data!$B$21:$B$613,COUNT(Market_Data!$B$21:$B$613)),1)),"")) -> 1267.6 | C13: =IF($A13="","",IFERROR(INDEX(Market_Data!$F$21:$F$613,MATCH($A13,Market_Data!$E$21:INDEX(Market_Data!$E$21:$E$613,COUNT(Market_Data!$E$21:$E$613)),1)),"")) -> 1550.5 | D13: =IF($A13="","",IFERROR(INDEX(Market_Data!$I$21:$I$613,MATCH($A13,Market_Data!$H$21:INDEX(Market_Data!$H$21:$H$613,COUNT(Market_Data!$H$21:$H$613)),1)),"")) -> 844.276 | E13: =IF($A13="","",IFERROR(INDEX(Market_Data!$L$21:$L$613,MATCH($A13,Market_Data!$K$21:INDEX(Market_Data!$K$21:$K$613,COUNT(Market_Data!$K$21:$K$613)),1)),"")) -> 3526.25 | F13: =IF($A13="","",IFERROR(INDEX(Market_Data!$O$21:$O$613,MATCH($A13,Market_Data!$N$21:INDEX(Market_Data!$N$21:$N$613,COUNT(Market_Data!$N$21:$N$613)),1)),"")) -> 1499.75 | G13: =IF($A13="","",IFERROR(INDEX(Market_Data!$R$21:$R$613,MATCH($A13,Market_Data!$Q$21:INDEX(Market_Data!$Q$21:$Q$613,COUNT(Market_Data!$Q$21:$Q$613)),1)),"")) -> 11006.05 | H13: =IF($A13="","",IFERROR(INDEX(Market_Data!$U$21:$U$613,MATCH($A13,Market_Data!$T$21:INDEX(Market_Data!$T$21:$T$613,COUNT(Market_Data!$T$21:$T$613)),1)),"")) -> 1852.7225 | I13: =IF($A13="","",IFERROR(INDEX(Query1[Close],MATCH($A13,Query1[Date],1)),"")) -> 24141.301
A14: =IF($A13="","",IF($A13+7<=TODAY(),$A13+7,"")) -> 45614 | B14: =IF($A14="","",IFERROR(INDEX(Market_Data!$C$21:$C$613,MATCH($A14,Market_Data!$B$21:INDEX(Market_Data!$B$21:$B$613,COUNT(Market_Data!$B$21:$B$613)),1)),"")) -> 1265.4 | C14: =IF($A14="","",IFERROR(INDEX(Market_Data!$F$21:$F$613,MATCH($A14,Market_Data!$E$21:INDEX(Market_Data!$E$21:$E$613,COUNT(Market_Data!$E$21:$E$613)),1)),"")) -> 1569.3 | D14: =IF($A14="","",IFERROR(INDEX(Market_Data!$I$21:$I$613,MATCH($A14,Market_Data!$H$21:INDEX(Market_Data!$H$21:$H$613,COUNT(Market_Data!$H$21:$H$613)),1)),"")) -> 870.6355 | E14: =IF($A14="","",IFERROR(INDEX(Market_Data!$L$21:$L$613,MATCH($A14,Market_Data!$K$21:INDEX(Market_Data!$K$21:$K$613,COUNT(Market_Data!$K$21:$K$613)),1)),"")) -> 3603.5 | F14: =IF($A14="","",IFERROR(INDEX(Market_Data!$O$21:$O$613,MATCH($A14,Market_Data!$N$21:INDEX(Market_Data!$N$21:$N$613,COUNT(Market_Data!$N$21:$N$613)),1)),"")) -> 1486.5 | G14: =IF($A14="","",IFERROR(INDEX(Market_Data!$R$21:$R$613,MATCH($A14,Market_Data!$Q$21:INDEX(Market_Data!$Q$21:$Q$613,COUNT(Market_Data!$Q$21:$Q$613)),1)),"")) -> 11063.6 | H14: =IF($A14="","",IFERROR(INDEX(Market_Data!$U$21:$U$613,MATCH($A14,Market_Data!$T$21:INDEX(Market_Data!$T$21:$T$613,COUNT(Market_Data!$T$21:$T$613)),1)),"")) -> 1892.0404 | I14: =IF($A14="","",IFERROR(INDEX(Query1[Close],MATCH($A14,Query1[Date],1)),"")) -> 23453.801
A15: =IF($A14="","",IF($A14+7<=TODAY(),$A14+7,"")) -> 45621 | B15: =IF($A15="","",IFERROR(INDEX(Market_Data!$C$21:$C$613,MATCH($A15,Market_Data!$B$21:INDEX(Market_Data!$B$21:$B$613,COUNT(Market_Data!$B$21:$B$613)),1)),"")) -> 1292.2 | C15: =IF($A15="","",IFERROR(INDEX(Market_Data!$F$21:$F$613,MATCH($A15,Market_Data!$E$21:INDEX(Market_Data!$E$21:$E$613,COUNT(Market_Data!$E$21:$E$613)),1)),"")) -> 1627.15 | D15: =IF($A15="","",IFERROR(INDEX(Market_Data!$I$21:$I$613,MATCH($A15,Market_Data!$H$21:INDEX(Market_Data!$H$21:$H$613,COUNT(Market_Data!$H$21:$H$613)),1)),"")) -> 895.7979 | E15: =IF($A15="","",IFERROR(INDEX(Market_Data!$L$21:$L$613,MATCH($A15,Market_Data!$K$21:INDEX(Market_Data!$K$21:$K$613,COUNT(Market_Data!$K$21:$K$613)),1)),"")) -> 3724.8 | F15: =IF($A15="","",IFERROR(INDEX(Market_Data!$O$21:$O$613,MATCH($A15,Market_Data!$N$21:INDEX(Market_Data!$N$21:$N$613,COUNT(Market_Data!$N$21:$N$613)),1)),"")) -> 1533.9 | G15: =IF($A15="","",IFERROR(INDEX(Market_Data!$R$21:$R$613,MATCH($A15,Market_Data!$Q$21:INDEX(Market_Data!$Q$21:$Q$613,COUNT(Market_Data!$Q$21:$Q$613)),1)),"")) -> 11074.2 | H15: =IF($A15="","",IFERROR(INDEX(Market_Data!$U$21:$U$613,MATCH($A15,Market_Data!$T$21:INDEX(Market_Data!$T$21:$T$613,COUNT(Market_Data!$T$21:$T$613)),1)),"")) -> 1841.859 | I15: =IF($A15="","",IFERROR(INDEX(Query1[Close],MATCH($A15,Query1[Date],1)),"")) -> 24221.9
A16: =IF($A15="","",IF($A15+7<=TODAY(),$A15+7,"")) -> 45628 | B16: =IF($A16="","",IFERROR(INDEX(Market_Data!$C$21:$C$613,MATCH($A16,Market_Data!$B$21:INDEX(Market_Data!$B$21:$B$613,COUNT(Market_Data!$B$21:$B$613)),1)),"")) -> 1311.55 | C16: =IF($A16="","",IFERROR(INDEX(Market_Data!$F$21:$F$613,MATCH($A16,Market_Data!$E$21:INDEX(Market_Data!$E$21:$E$613,COUNT(Market_Data!$E$21:$E$613)),1)),"")) -> 1597.85 | D16: =IF($A16="","",IFERROR(INDEX(Market_Data!$I$21:$I$613,MATCH($A16,Market_Data!$H$21:INDEX(Market_Data!$H$21:$H$613,COUNT(Market_Data!$H$21:$H$613)),1)),"")) -> 925.6237 | E16: =IF($A16="","",IFERROR(INDEX(Market_Data!$L$21:$L$613,MATCH($A16,Market_Data!$K$21:INDEX(Market_Data!$K$21:$K$613,COUNT(Market_Data!$K$21:$K$613)),1)),"")) -> 3866.7 | F16: =IF($A16="","",IFERROR(INDEX(Market_Data!$O$21:$O$613,MATCH($A16,Market_Data!$N$21:INDEX(Market_Data!$N$21:$N$613,COUNT(Market_Data!$N$21:$N$613)),1)),"")) -> 1477.4 | G16: =IF($A16="","",IFERROR(INDEX(Market_Data!$R$21:$R$613,MATCH($A16,Market_Data!$Q$21:INDEX(Market_Data!$Q$21:$Q$613,COUNT(Market_Data!$Q$21:$Q$613)),1)),"")) -> 11317.95 | H16: =IF($A16="","",IFERROR(INDEX(Market_Data!$U$21:$U$613,MATCH($A16,Market_Data!$T$21:INDEX(Market_Data!$T$21:$T$613,COUNT(Market_Data!$T$21:$T$613)),1)),"")) -> 1916.259 | I16: =IF($A16="","",IFERROR(INDEX(Query1[Close],MATCH($A16,Query1[Date],1)),"")) -> 24276.051
... A1000: =IF($A999="","",IF($A999+7<=TODAY(),$A999+7,"")) | B1000: =IF($A1000="","",IFERROR(INDEX(Market_Data!$C$21:$C$613,MATCH($A1000,Market_Data!$B$21:INDEX(Market_Data!$B$21:$B$613,COUNT(Market_Data!$B$21:$B$613)),1)),"")) | C1000: =IF($A1000="","",IFERROR(INDEX(Market_Data!$F$21:$F$613,MATCH($A1000,Market_Data!$E$21:INDEX(Market_Data!$E$21:$E$613,COUNT(Market_Data!$E$21:$E$613)),1)),"")) | D1000: =IF($A1000="","",IFERROR(INDEX(Market_Data!$I$21:$I$613,MATCH($A1000,Market_Data!$H$21:INDEX(Market_Data!$H$21:$H$613,COUNT(Market_Data!$H$21:$H$613)),1)),"")) | E1000: =IF($A1000="","",IFERROR(INDEX(Market_Data!$L$21:$L$613,MATCH($A1000,Market_Data!$K$21:INDEX(Market_Data!$K$21:$K$613,COUNT(Market_Data!$K$21:$K$613)),1)),"")) | F1000: =IF($A1000="","",IFERROR(INDEX(Market_Data!$O$21:$O$613,MATCH($A1000,Market_Data!$N$21:INDEX(Market_Data!$N$21:$N$613,COUNT(Market_Data!$N$21:$N$613)),1)),"")) | G1000: =IF($A1000="","",IFERROR(INDEX(Market_Data!$R$21:$R$613,MATCH($A1000,Market_Data!$Q$21:INDEX(Market_Data!$Q$21:$Q$613,COUNT(Market_Data!$Q$21:$Q$613)),1)),"")) | H1000: =IF($A1000="","",IFERROR(INDEX(Market_Data!$U$21:$U$613,MATCH($A1000,Market_Data!$T$21:INDEX(Market_Data!$T$21:$T$613,COUNT(Market_Data!$T$21:$T$613)),1)),"")) | I1000: =IF($A1000="","",IFERROR(INDEX(Query1[Close],MATCH($A1000,Query1[Date],1)),""))
A1002: ="Data-quality check: "&COUNT($A$4:$A$1000)&" weekly observations populated (formulas live through row 1000) · Blank price cells within populated window: "&(COUNTBLANK($B$4:$I$1000)-COUNTBLANK($A$4:$A$1000)*8)&" · "&IF((COUNTBLANK($B$4:$I$1000)-COUNTBLANK($A$4:$A$1000)*8)=0,"OK — no gaps within the populated window","REVIEW — some securities missing data within the populated window") -> Data-quality check: 105 weekly observations populated (formulas live through row 1000) · Blank price cells within populated window: 0 · OK — no gaps within the populated window

Sheet Market_Data
A1: MARKET DATA — DYNAMIC PRICE FEED (STOCKHISTORY)
A2: Every live price in this workbook is pulled here, once, via Excel's STOCKHISTORY function. Prices reads from this sheet through lookup formulas — no raw spill range is ever referenced directly by an analytical sheet.
A3: REQUIRES Microsoft Excel 365 (Windows/Mac) with an active Microsoft 365 subscription + internet access. STOCKHISTORY will show blank in LibreOffice, Google Sheets, older Excel, or Excel without a signed-in Microsoft 365 account — that is expected, not a bug.
A5: 1 · SECURITY IDENTIFIERS
A6: Edit the STOCKHISTORY identifier below and re-open if a security fails to resolve. Identifiers use the XNSE: MIC-code prefix — the National Stock Exchange of India's ISO 10383 exchange code — the same convention you personally confirmed works for XNSE:RELIANCE. Note: the 7 live stock formulas in Section 2 use each identifier typed directly into the formula (this is the exact form that resolved successfully for you), not a cell reference — if a feed ever needs a new identifier, edit its STOCKHISTORY formula in Section 2 directly. NIFTY 50 is no longer part of this STOCKHISTORY table at all — see Section 3 for how it's sourced now.
A8: Company | C8: Model ticker (.NS) | D8: STOCKHISTORY identifier | F8: Confidence / status
A9: Reliance Industries | C9: RELIANCE.NS | D9: XNSE:RELIANCE | F9: CONFIRMED — you personally tested this exact identifier in Excel.
A10: Bharti Airtel | C10: BHARTIARTL.NS | D10: XNSE:BHARTIARTL | F10: CONFIRMED — resolved successfully with real data in your Excel (105 weekly observations through 07-Sep-2026, verified before this update). Re-verify after any long gap without opening the file.
A11: HDFC Bank | C11: HDFCBANK.NS | D11: XNSE:HDFCBANK | F11: CONFIRMED — resolved successfully with real data in your Excel (105 weekly observations through 07-Sep-2026, verified before this update). Re-verify after any long gap without opening the file.
A12: Larsen & Toubro | C12: LT.NS | D12: XNSE:LT | F12: CONFIRMED — resolved successfully with real data in your Excel (105 weekly observations through 07-Sep-2026, verified before this update). Re-verify after any long gap without opening the file.
A13: Cipla | C13: CIPLA.NS | D13: XNSE:CIPLA | F13: CONFIRMED — resolved successfully with real data in your Excel (105 weekly observations through 07-Sep-2026, verified before this update). Re-verify after any long gap without opening the file.
A14: Maruti Suzuki | C14: MARUTI.NS | D14: XNSE:MARUTI | F14: CONFIRMED — resolved successfully with real data in your Excel (105 weekly observations through 07-Sep-2026, verified before this update). Re-verify after any long gap without opening the file.
A15: HCL Technologies | C15: HCLTECH.NS | D15: XNSE:HCLTECH | F15: CONFIRMED — resolved successfully with real data in your Excel (105 weekly observations through 07-Sep-2026, verified before this update). Re-verify after any long gap without opening the file.
A16: NIFTY 50 | C16: NIFTY 50 | D16: Power Query / Yahoo Finance
A17: 2 · LIVE STOCKHISTORY FEEDS (rolling ~2 years, weekly interval, Date + Close)
A18: STOCKHISTORY(identifier, TODAY()-730, TODAY(), 1, 1, 0, 1) · 1=weekly interval · 1=show headers · 0,1 = Date, Close. Each block spills downward from its anchor cell — do not type anything else into these columns below this point; leave the space empty so the spill has room to grow.
B19: Reliance Industries | E19: Bharti Airtel | H19: HDFC Bank | K19: Larsen & Toubro | N19: Cipla | Q19: Maruti Suzuki | T19: HCL Technologies | W19: NIFTY 50
B20: {=_xlfn.STOCKHISTORY("XNSE:RELIANCE",TODAY()-730,TODAY(),1,1,0,1)} -> Date | C20: Close | E20: {=_xlfn.STOCKHISTORY("XNSE:BHARTIARTL",TODAY()-730,TODAY(),1,1,0,1)} -> Date | F20: Close | H20: {=_xlfn.STOCKHISTORY("XNSE:HDFCBANK",TODAY()-730,TODAY(),1,1,0,1)} -> Date | I20: Close | K20: {=_xlfn.STOCKHISTORY("XNSE:LT",TODAY()-730,TODAY(),1,1,0,1)} -> Date | L20: Close | N20: {=_xlfn.STOCKHISTORY("XNSE:CIPLA",TODAY()-730,TODAY(),1,1,0,1)} -> Date | O20: Close | Q20: {=_xlfn.STOCKHISTORY("XNSE:MARUTI",TODAY()-730,TODAY(),1,1,0,1)} -> Date | R20: Close | T20: {=_xlfn.STOCKHISTORY("XNSE:HCLTECH",TODAY()-730,TODAY(),1,1,0,1)} -> Date | U20: Close | W20: Date | X20: Close
B21: 45544 | C21: 1472.625 | E21: 45544 | F21: 1634.45 | H21: 45544 | I21: 830.9092 | K21: 45544 | L21: 3613 | N21: 45544 | O21: 1659.7 | Q21: 45544 | R21: 12316.05 | T21: 45544 | U21: 1806.7271 | W21: 45544 | X21: 24936.4
B22: 45551 | C22: 1485.925 | E22: 45551 | F22: 1711.75 | H22: 45551 | I22: 868.4409 | K22: 45551 | L22: 3793.9 | N22: 45551 | O22: 1638.65 | Q22: 45551 | R22: 12614.5 | T22: 45551 | U22: 1754.1538 | W22: 45551 | X22: 25383.75
B23: 45558 | C23: 1526.175 | E23: 45558 | F23: 1734.6 | H23: 45558 | I23: 874.1517 | K23: 45558 | L23: 3705.65 | N23: 45558 | O23: 1672.5 | Q23: 45558 | R23: 13495.6 | T23: 45558 | U23: 1802.3419 | W23: 45558 | X23: 25939.051
B24: 45565 | C24: 1386.525 | E24: 45565 | F24: 1640.9 | H24: 45565 | I24: 826.7695 | K24: 45565 | L24: 3493.95 | N24: 45565 | O24: 1623.3 | Q24: 45565 | R24: 12605.75 | T24: 45565 | U24: 1770.6484 | W24: 45565 | X24: 25810.85
B25: 45572 | C25: 1372.1 | E25: 45572 | F25: 1687.4 | H25: 45572 | I25: 823.4528 | K25: 45572 | L25: 3482.55 | N25: 45572 | O25: 1595.75 | Q25: 45572 | R25: 12776.65 | T25: 45572 | U25: 1833.4872 | W25: 45572 | X25: 24795.75
B26: 45579 | C26: 1359.3 | E26: 45579 | F26: 1707.85 | H26: 45579 | I26: 838.8395 | K26: 45579 | L26: 3577.8 | N26: 45579 | O26: 1551.7 | Q26: 45579 | R26: 12105.1 | T26: 45579 | U26: 1851.4767 | W26: 45579 | X26: 25127.949
B27: 45586 | C27: 1327.85 | E27: 45586 | F27: 1666 | H27: 45586 | I27: 869.5382 | K27: 45586 | L27: 3326.4 | N27: 45586 | O27: 1488.9 | Q27: 45586 | R27: 11502.85 | T27: 45586 | U27: 1846.1446 | W27: 45586 | X27: 24781.1
B28: 45593 | C28: 1338.65 | E28: 45593 | F28: 1616.45 | H28: 45593 | I28: 866.4957 | K28: 45593 | L28: 3626.35 | N28: 45593 | O28: 1559.55 | Q28: 45593 | R28: 11110 | T28: 45593 | U28: 1751.5127 | W28: 45593 | X28: 24339.15
B29: 45600 | C29: 1283.75 | E29: 45600 | F29: 1569.9 | H29: 45600 | I29: 875.0495 | K29: 45600 | L29: 3660.3 | N29: 45600 | O29: 1592.6 | Q29: 45600 | R29: 11303 | T29: 45600 | U29: 1831.3444 | W29: 45600 | X29: 23995.35
B30: 45607 | C30: 1267.6 | E30: 45607 | F30: 1550.5 | H30: 45607 | I30: 844.276 | K30: 45607 | L30: 3526.25 | N30: 45607 | O30: 1499.75 | Q30: 45607 | R30: 11006.05 | T30: 45607 | U30: 1852.7225 | W30: 45607 | X30: 24141.301
B31: 45614 | C31: 1265.4 | E31: 45614 | F31: 1569.3 | H31: 45614 | I31: 870.6355 | K31: 45614 | L31: 3603.5 | N31: 45614 | O31: 1486.5 | Q31: 45614 | R31: 11063.6 | T31: 45614 | U31: 1892.0404 | W31: 45614 | X31: 23453.801
B32: 45621 | C32: 1292.2 | E32: 45621 | F32: 1627.15 | H32: 45621 | I32: 895.7979 | K32: 45621 | L32: 3724.8 | N32: 45621 | O32: 1533.9 | Q32: 45621 | R32: 11074.2 | T32: 45621 | U32: 1841.859 | W32: 45621 | X32: 24221.9
... B125: 46272 | C125: 1309.5 | E125: 46272 | F125: 1854 | H125: 46272 | I125: 710.5 | K125: 46272 | L125: 3999 | N125: 46272 | O125: 1395 | Q125: 46272 | R125: 12760 | T125: 46272 | U125: 1282.8 | W125: 46272 | X125: 23779.15

Sheet Returns
A1: RETURNS — WEEKLY SIMPLE RETURN SERIES
A2: Everything downstream in this workbook flows from these two series: column J (portfolio) and column I (NIFTY 50). | L2: MODEL CHECKS | M2: STATUS
A3: Stock / index return: = Price(t) / Price(t−1) − 1 · Portfolio return: = SUMPRODUCT(Weights, StockReturns(t)) — target weights, NOT a simple average of the seven stocks. | L3: Weights | M3: =SUM(Weights) -> 1
A4: Target weight → | B4: =Holdings!$E$7 -> 0.23 | C4: =Holdings!$E$8 -> 0.15 | D4: =Holdings!$E$9 -> 0.15 | E4: =Holdings!$E$10 -> 0.14 | F4: =Holdings!$E$11 -> 0.12 | G4: =Holdings!$E$12 -> 0.12 | H4: =Holdings!$E$13 -> 0.09 | J4: =SUM($B$4:$H$4) -> 1 | L4: Weekly observations | M4: =COUNT(PortRet) -> 104
A5: Date | B5: Reliance Industries | C5: Bharti Airtel | D5: HDFC Bank | E5: Larsen & Toubro | F5: Cipla | G5: Maruti Suzuki | H5: HCL Technologies | I5: NIFTY 50 | J5: Portfolio | L5: Missing returns | M5: =COUNTBLANK($B$6:INDEX($J$6:$J$1000,COUNT($A$6:$A$1000))) -> 0
A6: =Prices!$A$5 -> 45551 | B6: =IFERROR(Prices!B5/Prices!B4-1,"") -> 0.0090314914 | C6: =IFERROR(Prices!C5/Prices!C4-1,"") -> 0.047294197 | D6: =IFERROR(Prices!D5/Prices!D4-1,"") -> 0.045169436 | E6: =IFERROR(Prices!E5/Prices!E4-1,"") -> 0.050069195 | F6: =IFERROR(Prices!F5/Prices!F4-1,"") -> -0.012683015 | G6: =IFERROR(Prices!G5/Prices!G4-1,"") -> 0.024232607 | H6: =IFERROR(Prices!H5/Prices!H4-1,"") -> -0.029098639 | I6: =IFERROR(Prices!I5/Prices!I4-1,"") -> 0.017939622 | J6: =IFERROR(SUMPRODUCT(Weights,$B6:$H6),"") -> 0.021723549 | L6: Benchmark aligned | M6: =IF(COUNT(BenchRet)=COUNT(PortRet),"YES","CHECK") -> YES
A7: =Prices!$A$6 -> 45558 | B7: =IFERROR(Prices!B6/Prices!B5-1,"") -> 0.027087504 | C7: =IFERROR(Prices!C6/Prices!C5-1,"") -> 0.013348912 | D7: =IFERROR(Prices!D6/Prices!D5-1,"") -> 0.0065759224 | E7: =IFERROR(Prices!E6/Prices!E5-1,"") -> -0.023261024 | F7: =IFERROR(Prices!F6/Prices!F5-1,"") -> 0.020657248 | G7: =IFERROR(Prices!G6/Prices!G5-1,"") -> 0.069848191 | H7: =IFERROR(Prices!H6/Prices!H5-1,"") -> 0.027470852 | I7: =IFERROR(Prices!I6/Prices!I5-1,"") -> 0.021876231 | J7: =IFERROR(SUMPRODUCT(Weights,$B7:$H7),"") -> 0.019295337
A8: =Prices!$A$7 -> 45565 | B8: =IFERROR(Prices!B7/Prices!B6-1,"") -> -0.091503268 | C8: =IFERROR(Prices!C7/Prices!C6-1,"") -> -0.054018217 | D8: =IFERROR(Prices!D7/Prices!D6-1,"") -> -0.054203635 | E8: =IFERROR(Prices!E7/Prices!E6-1,"") -> -0.057128979 | F8: =IFERROR(Prices!F7/Prices!F6-1,"") -> -0.02941704 | G8: =IFERROR(Prices!G7/Prices!G6-1,"") -> -0.065936305 | H8: =IFERROR(Prices!H7/Prices!H6-1,"") -> -0.017584621 | I8: =IFERROR(Prices!I7/Prices!I6-1,"") -> -0.0049424003 | J8: =IFERROR(SUMPRODUCT(Weights,$B8:$H8),"") -> -0.058302104
A9: =Prices!$A$8 -> 45572 | B9: =IFERROR(Prices!B8/Prices!B7-1,"") -> -0.010403707 | C9: =IFERROR(Prices!C8/Prices!C7-1,"") -> 0.028338107 | D9: =IFERROR(Prices!D8/Prices!D7-1,"") -> -0.0040116381 | E9: =IFERROR(Prices!E8/Prices!E7-1,"") -> -0.0032627828 | F9: =IFERROR(Prices!F8/Prices!F7-1,"") -> -0.016971601 | G9: =IFERROR(Prices!G8/Prices!G7-1,"") -> 0.013557305 | H9: =IFERROR(Prices!H8/Prices!H7-1,"") -> 0.035489146 | I9: =IFERROR(Prices!I8/Prices!I7-1,"") -> -0.039328407 | J9: =IFERROR(SUMPRODUCT(Weights,$B9:$H9),"") -> 0.0035836358
A10: =Prices!$A$9 -> 45579 | B10: =IFERROR(Prices!B9/Prices!B8-1,"") -> -0.0093287661 | C10: =IFERROR(Prices!C9/Prices!C8-1,"") -> 0.012119237 | D10: =IFERROR(Prices!D9/Prices!D8-1,"") -> 0.018685588 | E10: =IFERROR(Prices!E9/Prices!E8-1,"") -> 0.027350648 | F10: =IFERROR(Prices!F9/Prices!F8-1,"") -> -0.027604575 | G10: =IFERROR(Prices!G9/Prices!G8-1,"") -> -0.052560726 | H10: =IFERROR(Prices!H9/Prices!H8-1,"") -> 0.0098116311 | I10: =IFERROR(Prices!I9/Prices!I8-1,"") -> 0.013397426 | J10: =IFERROR(SUMPRODUCT(Weights,$B10:$H10),"") -> -0.002432591
A11: =Prices!$A$10 -> 45586 | B11: =IFERROR(Prices!B10/Prices!B9-1,"") -> -0.023136909 | C11: =IFERROR(Prices!C10/Prices!C9-1,"") -> -0.024504494 | D11: =IFERROR(Prices!D10/Prices!D9-1,"") -> 0.036596631 | E11: =IFERROR(Prices!E10/Prices!E9-1,"") -> -0.070266644 | F11: =IFERROR(Prices!F10/Prices!F9-1,"") -> -0.040471741 | G11: =IFERROR(Prices!G10/Prices!G9-1,"") -> -0.049751758 | H11: =IFERROR(Prices!H10/Prices!H9-1,"") -> -0.0028799174 | I11: =IFERROR(Prices!I10/Prices!I9-1,"") -> -0.013803339 | J11: =IFERROR(SUMPRODUCT(Weights,$B11:$H11),"") -> -0.024431011
A12: =Prices!$A$11 -> 45593 | B12: =IFERROR(Prices!B11/Prices!B10-1,"") -> 0.0081334488 | C12: =IFERROR(Prices!C11/Prices!C10-1,"") -> -0.029741897 | D12: =IFERROR(Prices!D11/Prices!D10-1,"") -> -0.0034989837 | E12: =IFERROR(Prices!E11/Prices!E10-1,"") -> 0.090172559 | F12: =IFERROR(Prices!F11/Prices!F10-1,"") -> 0.047451138 | G12: =IFERROR(Prices!G11/Prices!G10-1,"") -> -0.034152406 | H12: =IFERROR(Prices!H11/Prices!H10-1,"") -> -0.051259203 | I12: =IFERROR(Prices!I11/Prices!I10-1,"") -> -0.017834125 | J12: =IFERROR(SUMPRODUCT(Weights,$B12:$H12),"") -> 0.0064912391
A13: =Prices!$A$12 -> 45600 | B13: =IFERROR(Prices!B12/Prices!B11-1,"") -> -0.041011467 | C13: =IFERROR(Prices!C12/Prices!C11-1,"") -> -0.028797674 | D13: =IFERROR(Prices!D12/Prices!D11-1,"") -> 0.0098717166 | E13: =IFERROR(Prices!E12/Prices!E11-1,"") -> 0.0093620307 | F13: =IFERROR(Prices!F12/Prices!F11-1,"") -> 0.021192011 | G13: =IFERROR(Prices!G12/Prices!G11-1,"") -> 0.017371737 | H13: =IFERROR(Prices!H12/Prices!H11-1,"") -> 0.045578716 | I13: =IFERROR(Prices!I12/Prices!I11-1,"") -> -0.014125422 | J13: =IFERROR(SUMPRODUCT(Weights,$B13:$H13),"") -> -0.0022311125
A14: =Prices!$A$13 -> 45607 | B14: =IFERROR(Prices!B13/Prices!B12-1,"") -> -0.012580331 | C14: =IFERROR(Prices!C13/Prices!C12-1,"") -> -0.012357475 | D14: =IFERROR(Prices!D13/Prices!D12-1,"") -> -0.035167725 | E14: =IFERROR(Prices!E13/Prices!E12-1,"") -> -0.036622681 | F14: =IFERROR(Prices!F13/Prices!F12-1,"") -> -0.058300892 | G14: =IFERROR(Prices!G13/Prices!G12-1,"") -> -0.026271786 | H14: =IFERROR(Prices!H13/Prices!H12-1,"") -> 0.011673446 | I14: =IFERROR(Prices!I13/Prices!I12-1,"") -> 0.0060824774 | J14: =IFERROR(SUMPRODUCT(Weights,$B14:$H14),"") -> -0.024247543
A15: =Prices!$A$14 -> 45614 | B15: =IFERROR(Prices!B14/Prices!B13-1,"") -> -0.0017355633 | C15: =IFERROR(Prices!C14/Prices!C13-1,"") -> 0.012125121 | D15: =IFERROR(Prices!D14/Prices!D13-1,"") -> 0.031221425 | E15: =IFERROR(Prices!E14/Prices!E13-1,"") -> 0.021907125 | F15: =IFERROR(Prices!F14/Prices!F13-1,"") -> -0.0088348058 | G15: =IFERROR(Prices!G14/Prices!G13-1,"") -> 0.0052289423 | H15: =IFERROR(Prices!H14/Prices!H13-1,"") -> 0.021221689 | I15: =IFERROR(Prices!I14/Prices!I13-1,"") -> -0.028478167 | J15: =IFERROR(SUMPRODUCT(Weights,$B15:$H15),"") -> 0.010647048
A16: =Prices!$A$15 -> 45621 | B16: =IFERROR(Prices!B15/Prices!B14-1,"") -> 0.021179074 | C16: =IFERROR(Prices!C15/Prices!C14-1,"") -> 0.03686357 | D16: =IFERROR(Prices!D15/Prices!D14-1,"") -> 0.028901188 | E16: =IFERROR(Prices!E15/Prices!E14-1,"") -> 0.033661718 | F16: =IFERROR(Prices!F15/Prices!F14-1,"") -> 0.031886983 | G16: =IFERROR(Prices!G15/Prices!G14-1,"") -> 0.00095809682 | H16: =IFERROR(Prices!H15/Prices!H14-1,"") -> -0.026522372 | I16: =IFERROR(Prices!I15/Prices!I14-1,"") -> 0.032749473 | J16: =IFERROR(SUMPRODUCT(Weights,$B16:$H16),"") -> 0.021002937
A17: =Prices!$A$16 -> 45628 | B17: =IFERROR(Prices!B16/Prices!B15-1,"") -> 0.014974462 | C17: =IFERROR(Prices!C16/Prices!C15-1,"") -> -0.018006945 | D17: =IFERROR(Prices!D16/Prices!D15-1,"") -> 0.033295233 | E17: =IFERROR(Prices!E16/Prices!E15-1,"") -> 0.038096005 | F17: =IFERROR(Prices!F16/Prices!F15-1,"") -> -0.036834213 | G17: =IFERROR(Prices!G16/Prices!G15-1,"") -> 0.022010619 | H17: =IFERROR(Prices!H16/Prices!H15-1,"") -> 0.040393972 | I17: =IFERROR(Prices!I16/Prices!I15-1,"") -> 0.0022355963 | J17: =IFERROR(SUMPRODUCT(Weights,$B17:$H17),"") -> 0.012927436
A18: =Prices!$A$17 -> 45635 | B18: =IFERROR(Prices!B17/Prices!B16-1,"") -> -0.029507072 | C18: =IFERROR(Prices!C17/Prices!C16-1,"") -> 0.052508058 | D18: =IFERROR(Prices!D17/Prices!D16-1,"") -> 0.0085675205 | E18: =IFERROR(Prices!E17/Prices!E16-1,"") -> 0.0052499547 | F18: =IFERROR(Prices!F17/Prices!F16-1,"") -> -0.020373629 | G18: =IFERROR(Prices!G17/Prices!G16-1,"") -> -0.0040113271 | H18: =IFERROR(Prices!H17/Prices!H16-1,"") -> 0.023976665 | I18: =IFERROR(Prices!I17/Prices!I16-1,"") -> 0.01412706 | J18: =IFERROR(SUMPRODUCT(Weights,$B18:$H18),"") -> 0.0023414089
A19: =Prices!$A$18 -> 45642 | B19: =IFERROR(Prices!B18/Prices!B17-1,"") -> -0.053069883 | C19: =IFERROR(Prices!C18/Prices!C17-1,"") -> -0.061632228 | D19: =IFERROR(Prices!D18/Prices!D17-1,"") -> -0.053559516 | E19: =IFERROR(Prices!E18/Prices!E17-1,"") -> -0.066156419 | F19: =IFERROR(Prices!F18/Prices!F17-1,"") -> 0.017100808 | G19: =IFERROR(Prices!G18/Prices!G17-1,"") -> -0.032956163 | H19: =IFERROR(Prices!H18/Prices!H17-1,"") -> -0.02918019 | I19: =IFERROR(Prices!I18/Prices!I17-1,"") -> 0.0020004874 | J19: =IFERROR(SUMPRODUCT(Weights,$B19:$H19),"") -> -0.043275593
A20: =Prices!$A$19 -> 45649 | B20: =IFERROR(Prices!B19/Prices!B18-1,"") -> 0.013067286 | C20: =IFERROR(Prices!C19/Prices!C18-1,"") -> 0.013782397 | D20: =IFERROR(Prices!D19/Prices!D18-1,"") -> 0.015100277 | E20: =IFERROR(Prices!E19/Prices!E18-1,"") -> -0.0059919831 | F20: =IFERROR(Prices!F19/Prices!F18-1,"") -> 0.02347067 | G20: =IFERROR(Prices!G19/Prices!G18-1,"") -> 0.0036693713 | H20: =IFERROR(Prices!H19/Prices!H18-1,"") -> -0.010123746 | I20: =IFERROR(Prices!I19/Prices!I18-1,"") -> -0.037084138 | J20: =IFERROR(SUMPRODUCT(Weights,$B20:$H20),"") -> 0.0088446671
A21: =Prices!$A$20 -> 45656 | B21: =IFERROR(Prices!B20/Prices!B19-1,"") -> 0.024650915 | C21: =IFERROR(Prices!C20/Prices!C19-1,"") -> -0.0006250586 | D21: =IFERROR(Prices!D20/Prices!D19-1,"") -> -0.027276542 | E21: =IFERROR(Prices!E20/Prices!E19-1,"") -> 0.014356587 | F21: =IFERROR(Prices!F20/Prices!F19-1,"") -> 0.0030864198 | G21: =IFERROR(Prices!G20/Prices!G19-1,"") -> 0.090777393 | H21: =IFERROR(Prices!H20/Prices!H19-1,"") -> 0.028884766 | I21: =IFERROR(Prices!I20/Prices!I19-1,"") -> -0.0045698133 | J21: =IFERROR(SUMPRODUCT(Weights,$B21:$H21),"") -> 0.017357679
A22: =Prices!$A$21 -> 45663 | B22: =IFERROR(Prices!B21/Prices!B20-1,"") -> -0.0073931983 | C22: =IFERROR(Prices!C21/Prices!C20-1,"") -> 0.010663915 | D22: =IFERROR(Prices!D21/Prices!D20-1,"") -> -0.052852776 | E22: =IFERROR(Prices!E21/Prices!E20-1,"") -> -0.033812399 | F22: =IFERROR(Prices!F21/Prices!F20-1,"") -> -0.02808933 | G22: =IFERROR(Prices!G21/Prices!G20-1,"") -> -0.02540168 | H22: =IFERROR(Prices!H21/Prices!H20-1,"") -> 0.024888916 | I22: =IFERROR(Prices!I21/Prices!I20-1,"") -> -0.0012201197 | J22: =IFERROR(SUMPRODUCT(Weights,$B22:$H22),"") -> -0.016941419
A23: =Prices!$A$22 -> 45670 | B23: =IFERROR(Prices!B22/Prices!B21-1,"") -> 0.048675417 | C23: =IFERROR(Prices!C22/Prices!C21-1,"") -> 0.007178662 | D23: =IFERROR(Prices!D22/Prices!D21-1,"") -> -0.012071828 | E23: =IFERROR(Prices!E22/Prices!E21-1,"") -> 0.0091907866 | F23: =IFERROR(Prices!F22/Prices!F21-1,"") -> -0.018041939 | G23: =IFERROR(Prices!G22/Prices!G21-1,"") -> 0.043439571 | H23: =IFERROR(Prices!H22/Prices!H21-1,"") -> -0.10033935 | I23: =IFERROR(Prices!I22/Prices!I21-1,"") -> -0.022446664 | J23: =IFERROR(SUMPRODUCT(Weights,$B23:$H23),"") -> 0.0057652559
A24: =Prices!$A$23 -> 45677 | B24: =IFERROR(Prices!B23/Prices!B22-1,"") -> -0.043037586 | C24: =IFERROR(Prices!C23/Prices!C22-1,"") -> 0.0106298 | D24: =IFERROR(Prices!D23/Prices!D22-1,"") -> 0.0079730957 | E24: =IFERROR(Prices!E23/Prices!E22-1,"") -> -0.030950079 | F24: =IFERROR(Prices!F23/Prices!F22-1,"") -> -0.021424114 | G24: =IFERROR(Prices!G23/Prices!G22-1,"") -> -0.013879791 | H24: =IFERROR(Prices!H23/Prices!H22-1,"") -> 0.0022080608 | I24: =IFERROR(Prices!I23/Prices!I22-1,"") -> 0.011210316 | J24: =IFERROR(SUMPRODUCT(Weights,$B24:$H24),"") -> -0.015478965
A25: =Prices!$A$24 -> 45684 | B25: =IFERROR(Prices!B24/Prices!B23-1,"") -> 0.014683463 | C25: =IFERROR(Prices!C24/Prices!C23-1,"") -> -0.013101897 | D25: =IFERROR(Prices!D24/Prices!D23-1,"") -> 0.02494245 | E25: =IFERROR(Prices!E24/Prices!E23-1,"") -> -0.0030940952 | F25: =IFERROR(Prices!F24/Prices!F23-1,"") -> 0.01990931 | G25: =IFERROR(Prices!G24/Prices!G23-1,"") -> 0.079262026 | H25: =IFERROR(Prices!H24/Prices!H23-1,"") -> -0.055135678 | I25: =IFERROR(Prices!I24/Prices!I23-1,"") -> -0.02208632 | J25: =IFERROR(SUMPRODUCT(Weights,$B25:$H25),"") -> 0.011658455
A26: =Prices!$A$25 -> 45691 | B26: =IFERROR(Prices!B25/Prices!B24-1,"") -> 0.0016606041 | C26: =IFERROR(Prices!C25/Prices!C24-1,"") -> 0.032958571 | D26: =IFERROR(Prices!D25/Prices!D24-1,"") -> 0.024719871 | E26: =IFERROR(Prices!E25/Prices!E24-1,"") -> -0.032081218 | F26: =IFERROR(Prices!F25/Prices!F24-1,"") -> 0.022750955 | G26: =IFERROR(Prices!G25/Prices!G24-1,"") -> 0.010296907 | H26: =IFERROR(Prices!H25/Prices!H24-1,"") -> 0.018683589 | I26: =IFERROR(Prices!I25/Prices!I24-1,"") -> 0.023299176 | J26: =IFERROR(SUMPRODUCT(Weights,$B26:$H26),"") -> 0.010189601
A27: =Prices!$A$26 -> 45698 | B27: =IFERROR(Prices!B26/Prices!B25-1,"") -> -0.039038446 | C27: =IFERROR(Prices!C26/Prices!C25-1,"") -> 0.024034591 | D27: =IFERROR(Prices!D26/Prices!D25-1,"") -> -0.021872741 | E27: =IFERROR(Prices!E26/Prices!E25-1,"") -> -0.029743175 | F27: =IFERROR(Prices!F26/Prices!F25-1,"") -> -0.0086941756 | G27: =IFERROR(Prices!G26/Prices!G25-1,"") -> -0.028296103 | H27: =IFERROR(Prices!H26/Prices!H25-1,"") -> -0.0083446817 | I27: =IFERROR(Prices!I26/Prices!I25-1,"") -> 0.00087961917 | J27: =IFERROR(SUMPRODUCT(Weights,$B27:$H27),"") -> -0.018008464
A28: =Prices!$A$27 -> 45705 | B28: =IFERROR(Prices!B27/Prices!B26-1,"") -> 0.0089546108 | C28: =IFERROR(Prices!C27/Prices!C26-1,"") -> -0.045310271 | D28: =IFERROR(Prices!D27/Prices!D26-1,"") -> -0.0013865699 | E28: =IFERROR(Prices!E27/Prices!E26-1,"") -> 0.023921672 | F28: =IFERROR(Prices!F27/Prices!F26-1,"") -> 0.011168591 | G28: =IFERROR(Prices!G27/Prices!G26-1,"") -> -0.028138246 | H28: =IFERROR(Prices!H27/Prices!H26-1,"") -> -0.006165084 | I28: =IFERROR(Prices!I27/Prices!I26-1,"") -> -0.01805264 | J28: =IFERROR(SUMPRODUCT(Weights,$B28:$H28),"") -> -0.0041871478
A29: =Prices!$A$28 -> 45712 | B29: =IFERROR(Prices!B28/Prices!B27-1,"") -> -0.02283923 | C29: =IFERROR(Prices!C28/Prices!C27-1,"") -> -0.042122922 | D29: =IFERROR(Prices!D28/Prices!D27-1,"") -> 0.023574565 | E29: =IFERROR(Prices!E28/Prices!E27-1,"") -> -0.045624566 | F29: =IFERROR(Prices!F28/Prices!F27-1,"") -> -0.046247671 | G29: =IFERROR(Prices!G28/Prices!G27-1,"") -> -0.03064077 | H29: =IFERROR(Prices!H28/Prices!H27-1,"") -> -0.073881343 | I29: =IFERROR(Prices!I28/Prices!I27-1,"") -> -0.017689862 | J29: =IFERROR(SUMPRODUCT(Weights,$B29:$H29),"") -> -0.030298649
A30: =Prices!$A$29 -> 45719 | B30: =IFERROR(Prices!B29/Prices!B28-1,"") -> 0.041413216 | C30: =IFERROR(Prices!C29/Prices!C28-1,"") -> 0.038530124 | D30: =IFERROR(Prices!D29/Prices!D28-1,"") -> -0.02490765 | E30: =IFERROR(Prices!E29/Prices!E28-1,"") -> 0.025554309 | F30: =IFERROR(Prices!F29/Prices!F28-1,"") -> 0.036198934 | G30: =IFERROR(Prices!G29/Prices!G28-1,"") -> -0.023581411 | H30: =IFERROR(Prices!H29/Prices!H28-1,"") -> -0.010856798 | I30: =IFERROR(Prices!I29/Prices!I28-1,"") -> -0.019245426 | J30: =IFERROR(SUMPRODUCT(Weights,$B30:$H30),"") -> 0.015683005
A31: =Prices!$A$30 -> 45726 | B31: =IFERROR(Prices!B30/Prices!B29-1,"") -> -0.0015202432 | C31: =IFERROR(Prices!C30/Prices!C29-1,"") -> 0.0011038204 | D31: =IFERROR(Prices!D30/Prices!D29-1,"") -> 0.010270847 | E31: =IFERROR(Prices!E30/Prices!E29-1,"") -> -0.017690387 | F31: =IFERROR(Prices!F30/Prices!F29-1,"") -> 0.002365525 | G31: =IFERROR(Prices!G30/Prices!G29-1,"") -> -0.012889923 | H31: =IFERROR(Prices!H30/Prices!H29-1,"") -> -0.014891364 | I31: =IFERROR(Prices!I30/Prices!I29-1,"") -> 0.015416401 | J31: =IFERROR(SUMPRODUCT(Weights,$B31:$H31),"") -> -0.0037232606
A32: =Prices!$A$31 -> 45733 | B32: =IFERROR(Prices!B31/Prices!B30-1,"") -> 0.022798301 | C32: =IFERROR(Prices!C31/Prices!C30-1,"") -> 0.057151608 | D32: =IFERROR(Prices!D31/Prices!D30-1,"") -> 0.037355034 | E32: =IFERROR(Prices!E31/Prices!E30-1,"") -> 0.071737835 | F32: =IFERROR(Prices!F31/Prices!F30-1,"") -> 0.04237636 | G32: =IFERROR(Prices!G31/Prices!G30-1,"") -> 0.019020653 | H32: =IFERROR(Prices!H31/Prices!H30-1,"") -> 0.020817723 | I32: =IFERROR(Prices!I31/Prices!I30-1,"") -> 0.0021571046 | J32: =IFERROR(SUMPRODUCT(Weights,$B32:$H32),"") -> 0.038704139
A33: =Prices!$A$32 -> 45740 | B33: =IFERROR(Prices!B32/Prices!B31-1,"") -> -0.00097935519 | C33: =IFERROR(Prices!C32/Prices!C31-1,"") -> 0.0044037548 | D33: =IFERROR(Prices!D32/Prices!D31-1,"") -> 0.032677078 | E33: =IFERROR(Prices!E32/Prices!E31-1,"") -> 0.02235103 | F33: =IFERROR(Prices!F32/Prices!F31-1,"") -> -0.053581389 | G33: =IFERROR(Prices!G32/Prices!G31-1,"") -> -0.017953941 | H33: =IFERROR(Prices!H32/Prices!H31-1,"") -> 0.016467735 | I33: =IFERROR(Prices!I32/Prices!I31-1,"") -> 0.051073454 | J33: =IFERROR(SUMPRODUCT(Weights,$B33:$H33),"") -> 0.0013638739
A34: =Prices!$A$33 -> 45747 | B34: =IFERROR(Prices!B33/Prices!B32-1,"") -> 0 | C34: =IFERROR(Prices!C33/Prices!C32-1,"") -> 0 | D34: =IFERROR(Prices!D33/Prices!D32-1,"") -> 0 | E34: =IFERROR(Prices!E33/Prices!E32-1,"") -> 0 | F34: =IFERROR(Prices!F33/Prices!F32-1,"") -> 0 | G34: =IFERROR(Prices!G33/Prices!G32-1,"") -> 0 | H34: =IFERROR(Prices!H33/Prices!H32-1,"") -> 0 | I34: =IFERROR(Prices!I33/Prices!I32-1,"") -> -0.020823532 | J34: =IFERROR(SUMPRODUCT(Weights,$B34:$H34),"") -> 0
A35: =Prices!$A$34 -> 45754 | B35: =IFERROR(Prices!B34/Prices!B33-1,"") -> -0.044035762 | C35: =IFERROR(Prices!C34/Prices!C33-1,"") -> 0.013384101 | D35: =IFERROR(Prices!D34/Prices!D33-1,"") -> -0.01173285 | E35: =IFERROR(Prices!E34/Prices!E33-1,"") -> -0.10776566 | F35: =IFERROR(Prices!F34/Prices!F33-1,"") -> 0.014457079 | G35: =IFERROR(Prices!G34/Prices!G33-1,"") -> 0.0066741016 | H35: =IFERROR(Prices!H34/Prices!H33-1,"") -> -0.12681319 | I35: =IFERROR(Prices!I34/Prices!I33-1,"") -> -0.043344239 | J35: =IFERROR(SUMPRODUCT(Weights,$B35:$H35),"") -> -0.033845175
A36: =Prices!$A$35 -> 45761 | B36: =IFERROR(Prices!B35/Prices!B34-1,"") -> 0 | C36: =IFERROR(Prices!C35/Prices!C34-1,"") -> 0 | D36: =IFERROR(Prices!D35/Prices!D34-1,"") -> 0 | E36: =IFERROR(Prices!E35/Prices!E34-1,"") -> 0 | F36: =IFERROR(Prices!F35/Prices!F34-1,"") -> 0 | G36: =IFERROR(Prices!G35/Prices!G34-1,"") -> 0 | H36: =IFERROR(Prices!H35/Prices!H34-1,"") -> 0 | I36: =IFERROR(Prices!I35/Prices!I34-1,"") -> 0.05265645 | J36: =IFERROR(SUMPRODUCT(Weights,$B36:$H36),"") -> 0
A37: =Prices!$A$36 -> 45768 | B37: =IFERROR(Prices!B36/Prices!B35-1,"") -> 0.066819804 | C37: =IFERROR(Prices!C36/Prices!C35-1,"") -> 0.034498463 | D37: =IFERROR(Prices!D36/Prices!D35-1,"") -> 0.057811008 | E37: =IFERROR(Prices!E36/Prices!E35-1,"") -> 0.050113128 | F37: =IFERROR(Prices!F36/Prices!F35-1,"") -> 0.042958204 | G37: =IFERROR(Prices!G36/Prices!G35-1,"") -> 0.0085308711 | H37: =IFERROR(Prices!H36/Prices!H35-1,"") -> 0.1349466 | I37: =IFERROR(Prices!I36/Prices!I35-1,"") -> 0.034164145 | J37: =IFERROR(SUMPRODUCT(Weights,$B37:$H37),"") -> 0.054554697
A38: =Prices!$A$37 -> 45775 | B38: =IFERROR(Prices!B37/Prices!B36-1,"") -> 0.093817287 | C38: =IFERROR(Prices!C37/Prices!C36-1,"") -> 0.019095311 | D38: =IFERROR(Prices!D37/Prices!D36-1,"") -> 0.0072206071 | E38: =IFERROR(Prices!E37/Prices!E36-1,"") -> 0.017633935 | F38: =IFERROR(Prices!F37/Prices!F36-1,"") -> -0.00019660528 | G38: =IFERROR(Prices!G37/Prices!G36-1,"") -> 0.060523166 | H38: =IFERROR(Prices!H37/Prices!H36-1,"") -> -0.0010771765 | I38: =IFERROR(Prices!I37/Prices!I36-1,"") -> 0.0084122108 | J38: =IFERROR(SUMPRODUCT(Weights,$B38:$H38),"") -> 0.035136356
A39: =Prices!$A$38 -> 45782 | B39: =IFERROR(Prices!B38/Prices!B37-1,"") -> -0.031777278 | C39: =IFERROR(Prices!C38/Prices!C37-1,"") -> -0.0018899509 | D39: =IFERROR(Prices!D38/Prices!D37-1,"") -> -0.018337633 | E39: =IFERROR(Prices!E38/Prices!E37-1,"") -> 0.034266322 | F39: =IFERROR(Prices!F38/Prices!F37-1,"") -> -0.029889879 | G39: =IFERROR(Prices!G38/Prices!G37-1,"") -> -0.012574561 | H39: =IFERROR(Prices!H38/Prices!H37-1,"") -> -0.0045036473 | I39: =IFERROR(Prices!I38/Prices!I37-1,"") -> 0.0054524689 | J39: =IFERROR(SUMPRODUCT(Weights,$B39:$H39),"") -> -0.011046687
A40: =Prices!$A$39 -> 45789 | B40: =IFERROR(Prices!B39/Prices!B38-1,"") -> 0.057507987 | C40: =IFERROR(Prices!C39/Prices!C38-1,"") -> -0.01861069 | D40: =IFERROR(Prices!D39/Prices!D38-1,"") -> 0.023813303 | E40: =IFERROR(Prices!E39/Prices!E38-1,"") -> 0.046691251 | F40: =IFERROR(Prices!F39/Prices!F38-1,"") -> 0.013445946 | G40: =IFERROR(Prices!G39/Prices!G38-1,"") -> 0.060816327 | H40: =IFERROR(Prices!H39/Prices!H38-1,"") -> 0.05766535 | I40: =IFERROR(Prices!I39/Prices!I38-1,"") -> 0.01895041 | J40: =IFERROR(SUMPRODUCT(Weights,$B40:$H40),"") -> 0.034645358
A41: =Prices!$A$40 -> 45796 | B41: =IFERROR(Prices!B40/Prices!B39-1,"") -> -0.020324087 | C41: =IFERROR(Prices!C40/Prices!C39-1,"") -> 0.0097574421 | D41: =IFERROR(Prices!D40/Prices!D39-1,"") -> -0.00056862991 | E41: =IFERROR(Prices!E40/Prices!E39-1,"") -> -0.0013315949 | F41: =IFERROR(Prices!F40/Prices!F39-1,"") -> -0.010467364 | G41: =IFERROR(Prices!G40/Prices!G39-1,"") -> -0.041708349 | H41: =IFERROR(Prices!H40/Prices!H39-1,"") -> -0.0070486174 | I41: =IFERROR(Prices!I40/Prices!I39-1,"") -> 0.00083250754 | J41: =IFERROR(SUMPRODUCT(Weights,$B41:$H41),"") -> -0.010378103
A42: =Prices!$A$41 -> 45803 | B42: =IFERROR(Prices!B41/Prices!B40-1,"") -> -0.0041351276 | C42: =IFERROR(Prices!C41/Prices!C40-1,"") -> 0.013375553 | D42: =IFERROR(Prices!D41/Prices!D40-1,"") -> 0.0058440342 | E42: =IFERROR(Prices!E41/Prices!E40-1,"") -> 0.020889469 | F42: =IFERROR(Prices!F41/Prices!F40-1,"") -> -0.012464627 | G42: =IFERROR(Prices!G41/Prices!G40-1,"") -> -0.010760459 | H42: =IFERROR(Prices!H41/Prices!H40-1,"") -> -0.0070379808 | I42: =IFERROR(Prices!I41/Prices!I40-1,"") -> 0.0022329192 | J42: =IFERROR(SUMPRODUCT(Weights,$B42:$H42),"") -> 0.0014359557
A43: =Prices!$A$42 -> 45810 | B43: =IFERROR(Prices!B42/Prices!B41-1,"") -> 0.015905412 | C43: =IFERROR(Prices!C42/Prices!C41-1,"") -> 0.0075422907 | D43: =IFERROR(Prices!D42/Prices!D41-1,"") -> 0.017378798 | E43: =IFERROR(Prices!E42/Prices!E41-1,"") -> -0.0051155071 | F43: =IFERROR(Prices!F42/Prices!F41-1,"") -> 0.026267313 | G43: =IFERROR(Prices!G42/Prices!G41-1,"") -> 0.011608085 | H43: =IFERROR(Prices!H42/Prices!H41-1,"") -> 0.00067212514 | I43: =IFERROR(Prices!I42/Prices!I41-1,"") -> -0.011381508 | J43: =IFERROR(SUMPRODUCT(Weights,$B43:$H43),"") -> 0.011285776
A44: =Prices!$A$43 -> 45817 | B44: =IFERROR(Prices!B43/Prices!B42-1,"") -> -0.010807066 | C44: =IFERROR(Prices!C43/Prices!C42-1,"") -> -0.015934125 | D44: =IFERROR(Prices!D43/Prices!D42-1,"") -> -0.030878824 | E44: =IFERROR(Prices!E43/Prices!E42-1,"") -> -0.018844187 | F44: =IFERROR(Prices!F43/Prices!F42-1,"") -> 0.00066480521 | G44: =IFERROR(Prices!G43/Prices!G42-1,"") -> -0.0043331728 | H44: =IFERROR(Prices!H43/Prices!H42-1,"") -> 0.035171277 | I44: =IFERROR(Prices!I43/Prices!I42-1,"") -> 0.015641294 | J44: =IFERROR(SUMPRODUCT(Weights,$B44:$H44),"") -> -0.0094205428
A45: =Prices!$A$44 -> 45824 | B45: =IFERROR(Prices!B44/Prices!B43-1,"") -> 0.026822607 | C45: =IFERROR(Prices!C44/Prices!C43-1,"") -> 0.052325581 | D45: =IFERROR(Prices!D44/Prices!D43-1,"") -> 0.024561956 | E45: =IFERROR(Prices!E44/Prices!E43-1,"") -> 0.020795005 | F45: =IFERROR(Prices!F44/Prices!F43-1,"") -> -0.0036539995 | G45: =IFERROR(Prices!G44/Prices!G43-1,"") -> 0.030867182 | H45: =IFERROR(Prices!H44/Prices!H43-1,"") -> 0.026308028 | I45: =IFERROR(Prices!I44/Prices!I43-1,"") -> -0.0062422011 | J45: =IFERROR(SUMPRODUCT(Weights,$B45:$H45),"") -> 0.026246935
A46: =Prices!$A$45 -> 45831 | B46: =IFERROR(Prices!B45/Prices!B44-1,"") -> 0.033556131 | C46: =IFERROR(Prices!C45/Prices!C44-1,"") -> 0.046677338 | D46: =IFERROR(Prices!D45/Prices!D44-1,"") -> 0.025550921 | E46: =IFERROR(Prices!E45/Prices!E44-1,"") -> 0.0046968869 | F46: =IFERROR(Prices!F45/Prices!F44-1,"") -> 0.0018003601 | G46: =IFERROR(Prices!G45/Prices!G44-1,"") -> -0.011648816 | H46: =IFERROR(Prices!H45/Prices!H44-1,"") -> -0.0095407782 | I46: =IFERROR(Prices!I45/Prices!I44-1,"") -> 0.0010181946 | J46: =IFERROR(SUMPRODUCT(Weights,$B46:$H46),"") -> 0.017169229
A47: =Prices!$A$46 -> 45838 | B47: =IFERROR(Prices!B46/Prices!B45-1,"") -> 0.0078527122 | C47: =IFERROR(Prices!C46/Prices!C45-1,"") -> -0.0048838242 | D47: =IFERROR(Prices!D46/Prices!D45-1,"") -> -0.01270529 | E47: =IFERROR(Prices!E46/Prices!E45-1,"") -> -0.022994129 | F47: =IFERROR(Prices!F46/Prices!F45-1,"") -> 0.0072550586 | G47: =IFERROR(Prices!G46/Prices!G45-1,"") -> 0.00031640563 | H47: =IFERROR(Prices!H46/Prices!H45-1,"") -> 0.0015087332 | I47: =IFERROR(Prices!I46/Prices!I45-1,"") -> 0.021830553 | J47: =IFERROR(SUMPRODUCT(Weights,$B47:$H47),"") -> -0.0030070597
A48: =Prices!$A$47 -> 45845 | B48: =IFERROR(Prices!B47/Prices!B46-1,"") -> -0.021017482 | C48: =IFERROR(Prices!C47/Prices!C46-1,"") -> -0.047243704 | D48: =IFERROR(Prices!D47/Prices!D46-1,"") -> -0.0028151048 | E48: =IFERROR(Prices!E47/Prices!E46-1,"") -> -0.015022534 | F48: =IFERROR(Prices!F47/Prices!F46-1,"") -> -0.018700852 | G48: =IFERROR(Prices!G47/Prices!G46-1,"") -> -0.0056934999 | H48: =IFERROR(Prices!H47/Prices!H46-1,"") -> -0.050756127 | I48: =IFERROR(Prices!I47/Prices!I46-1,"") -> -0.0021848136 | J48: =IFERROR(SUMPRODUCT(Weights,$B48:$H48),"") -> -0.021941371
A49: =Prices!$A$48 -> 45852 | B49: =IFERROR(Prices!B48/Prices!B47-1,"") -> -0.012841091 | C49: =IFERROR(Prices!C48/Prices!C47-1,"") -> -0.010874655 | D49: =IFERROR(Prices!D48/Prices!D47-1,"") -> -0.013258065 | E49: =IFERROR(Prices!E48/Prices!E47-1,"") -> -0.021408801 | F49: =IFERROR(Prices!F48/Prices!F47-1,"") -> -0.0018181818 | G49: =IFERROR(Prices!G48/Prices!G47-1,"") -> -0.012327024 | H49: =IFERROR(Prices!H48/Prices!H47-1,"") -> -0.054629799 | I49: =IFERROR(Prices!I48/Prices!I47-1,"") -> -0.014885335 | J49: =IFERROR(SUMPRODUCT(Weights,$B49:$H49),"") -> -0.016184698
A50: =Prices!$A$49 -> 45859 | B50: =IFERROR(Prices!B49/Prices!B48-1,"") -> -0.057113821 | C50: =IFERROR(Prices!C49/Prices!C48-1,"") -> 0.019410836 | D50: =IFERROR(Prices!D49/Prices!D48-1,"") -> 0.026659761 | E50: =IFERROR(Prices!E49/Prices!E48-1,"") -> -0.0063207112 | F50: =IFERROR(Prices!F49/Prices!F48-1,"") -> 0.033866289 | G50: =IFERROR(Prices!G49/Prices!G48-1,"") -> -0.0012078267 | H50: =IFERROR(Prices!H49/Prices!H48-1,"") -> -0.03790031 | I50: =IFERROR(Prices!I49/Prices!I48-1,"") -> 0.00033483521 | J50: =IFERROR(SUMPRODUCT(Weights,$B50:$H50),"") -> -0.0066025012
A51: =Prices!$A$50 -> 45866 | B51: =IFERROR(Prices!B50/Prices!B49-1,"") -> 0.0014370913 | C51: =IFERROR(Prices!C50/Prices!C49-1,"") -> -0.027607204 | D51: =IFERROR(Prices!D50/Prices!D49-1,"") -> 0.0037912801 | E51: =IFERROR(Prices!E50/Prices!E49-1,"") -> 0.041941387 | F51: =IFERROR(Prices!F50/Prices!F49-1,"") -> -0.019380098 | G51: =IFERROR(Prices!G50/Prices!G49-1,"") -> -0.0082231538 | H51: =IFERROR(Prices!H50/Prices!H49-1,"") -> -0.025501644 | I51: =IFERROR(Prices!I50/Prices!I49-1,"") -> -0.016332699 | J51: =IFERROR(SUMPRODUCT(Weights,$B51:$H51),"") -> -0.0029776016
A52: =Prices!$A$51 -> 45873 | B52: =IFERROR(Prices!B51/Prices!B50-1,"") -> -0.018583626 | C52: =IFERROR(Prices!C51/Prices!C50-1,"") -> -0.013691361 | D52: =IFERROR(Prices!D51/Prices!D50-1,"") -> -0.019033893 | E52: =IFERROR(Prices!E51/Prices!E50-1,"") -> 0.0056588521 | F52: =IFERROR(Prices!F51/Prices!F50-1,"") -> -0.011312217 | G52: =IFERROR(Prices!G51/Prices!G50-1,"") -> 0.023410828 | H52: =IFERROR(Prices!H51/Prices!H50-1,"") -> 0.016252324 | I52: =IFERROR(Prices!I51/Prices!I50-1,"") -> 0.0016956273 | J52: =IFERROR(SUMPRODUCT(Weights,$B52:$H52),"") -> -0.0054762404
A53: =Prices!$A$52 -> 45880 | B53: =IFERROR(Prices!B52/Prices!B51-1,"") -> 0.0043866062 | C53: =IFERROR(Prices!C52/Prices!C51-1,"") -> 0.0081781986 | D53: =IFERROR(Prices!D52/Prices!D51-1,"") -> 0.008713714 | E53: =IFERROR(Prices!E52/Prices!E51-1,"") -> 0.019237166 | F53: =IFERROR(Prices!F52/Prices!F51-1,"") -> 0.052631579 | G53: =IFERROR(Prices!G52/Prices!G51-1,"") -> 0.027482129 | H53: =IFERROR(Prices!H52/Prices!H51-1,"") -> 0.0095547876 | I53: =IFERROR(Prices!I52/Prices!I51-1,"") -> -0.0055697371 | J53: =IFERROR(SUMPRODUCT(Weights,$B53:$H53),"") -> 0.016709485
A54: =Prices!$A$53 -> 45887 | B54: =IFERROR(Prices!B53/Prices!B52-1,"") -> 0.025767943 | C54: =IFERROR(Prices!C53/Prices!C52-1,"") -> 0.031753656 | D54: =IFERROR(Prices!D53/Prices!D52-1,"") -> -0.013309226 | E54: =IFERROR(Prices!E53/Prices!E52-1,"") -> -0.02208322 | F54: =IFERROR(Prices!F53/Prices!F52-1,"") -> 0.018414322 | G54: =IFERROR(Prices!G53/Prices!G52-1,"") -> 0.10923006 | H54: =IFERROR(Prices!H53/Prices!H52-1,"") -> -0.015773929 | I54: =IFERROR(Prices!I53/Prices!I52-1,"") -> 0.011873005 | J54: =IFERROR(SUMPRODUCT(Weights,$B54:$H54),"") -> 0.019499312
A55: =Prices!$A$54 -> 45894 | B55: =IFERROR(Prices!B54/Prices!B53-1,"") -> -0.036900369 | C55: =IFERROR(Prices!C54/Prices!C53-1,"") -> -0.023017638 | D55: =IFERROR(Prices!D54/Prices!D53-1,"") -> -0.031253181 | E55: =IFERROR(Prices!E54/Prices!E53-1,"") -> 0.0014461316 | F55: =IFERROR(Prices!F54/Prices!F53-1,"") -> -0.0021346057 | G55: =IFERROR(Prices!G54/Prices!G53-1,"") -> 0.03080354 | H55: =IFERROR(Prices!H54/Prices!H53-1,"") -> -0.0078428698 | I55: =IFERROR(Prices!I54/Prices!I53-1,"") -> 0.0036499966 | J55: =IFERROR(SUMPRODUCT(Weights,$B55:$H55),"") -> -0.013690836
A56: =Prices!$A$55 -> 45901 | B56: =IFERROR(Prices!B55/Prices!B54-1,"") -> 0.013115237 | C56: =IFERROR(Prices!C55/Prices!C54-1,"") -> 0.0034413384 | D56: =IFERROR(Prices!D55/Prices!D54-1,"") -> 0.012400168 | E56: =IFERROR(Prices!E55/Prices!E54-1,"") -> -0.01316301 | F56: =IFERROR(Prices!F55/Prices!F54-1,"") -> -0.022650057 | G56: =IFERROR(Prices!G55/Prices!G54-1,"") -> 0.0070313028 | H56: =IFERROR(Prices!H55/Prices!H54-1,"") -> -0.024608194 | I56: =IFERROR(Prices!I55/Prices!I54-1,"") -> -0.013725675 | J56: =IFERROR(SUMPRODUCT(Weights,$B56:$H56),"") -> -0.00053907876
A57: =Prices!$A$56 -> 45908 | B57: =IFERROR(Prices!B56/Prices!B55-1,"") -> 0.014545455 | C57: =IFERROR(Prices!C56/Prices!C55-1,"") -> 0.003851633 | D57: =IFERROR(Prices!D56/Prices!D55-1,"") -> 0.0040481628 | E57: =IFERROR(Prices!E56/Prices!E55-1,"") -> 0.007372805 | F57: =IFERROR(Prices!F56/Prices!F55-1,"") -> 0.013647483 | G57: =IFERROR(Prices!G56/Prices!G55-1,"") -> 0.028868748 | H57: =IFERROR(Prices!H56/Prices!H55-1,"") -> 0.033967583 | I57: =IFERROR(Prices!I56/Prices!I55-1,"") -> 0.0060141849 | J57: =IFERROR(SUMPRODUCT(Weights,$B57:$H57),"") -> 0.013721647
A58: =Prices!$A$57 -> 45915 | B58: =IFERROR(Prices!B57/Prices!B56-1,"") -> 0.0088888889 | C58: =IFERROR(Prices!C57/Prices!C56-1,"") -> 0.031430674 | D58: =IFERROR(Prices!D57/Prices!D56-1,"") -> -0.00041352218 | E58: =IFERROR(Prices!E57/Prices!E56-1,"") -> 0.026705403 | F58: =IFERROR(Prices!F57/Prices!F56-1,"") -> 0.00076209831 | G58: =IFERROR(Prices!G57/Prices!G56-1,"") -> 0.035171289 | H58: =IFERROR(Prices!H57/Prices!H56-1,"") -> 0.00013631407 | I58: =IFERROR(Prices!I57/Prices!I56-1,"") -> 0.011950391 | J58: =IFERROR(SUMPRODUCT(Weights,$B58:$H58),"") -> 0.014760048
A59: =Prices!$A$58 -> 45922 | B59: =IFERROR(Prices!B58/Prices!B57-1,"") -> -0.021173796 | C59: =IFERROR(Prices!C58/Prices!C57-1,"") -> -0.023338769 | D59: =IFERROR(Prices!D58/Prices!D57-1,"") -> -0.022597994 | E59: =IFERROR(Prices!E58/Prices!E57-1,"") -> 0.014719486 | F59: =IFERROR(Prices!F58/Prices!F57-1,"") -> -0.04848331 | G59: =IFERROR(Prices!G58/Prices!G57-1,"") -> 0.026601109 | H59: =IFERROR(Prices!H58/Prices!H57-1,"") -> -0.049134524 | I59: =IFERROR(Prices!I58/Prices!I57-1,"") -> 0.0053113141 | J59: =IFERROR(SUMPRODUCT(Weights,$B59:$H59),"") -> -0.01674773
A60: =Prices!$A$59 -> 45929 | B60: =IFERROR(Prices!B59/Prices!B58-1,"") -> -0.010307782 | C60: =IFERROR(Prices!C59/Prices!C58-1,"") -> -0.01038297 | D60: =IFERROR(Prices!D59/Prices!D58-1,"") -> 0.021268716 | E60: =IFERROR(Prices!E59/Prices!E58-1,"") -> 0.00096527685 | F60: =IFERROR(Prices!F59/Prices!F58-1,"") -> 0.012204882 | G60: =IFERROR(Prices!G59/Prices!G58-1,"") -> -0.029473167 | H60: =IFERROR(Prices!H59/Prices!H58-1,"") -> -0.0012900452 | I60: =IFERROR(Prices!I59/Prices!I58-1,"") -> -0.022515727 | J60: =IFERROR(SUMPRODUCT(Weights,$B60:$H60),"") -> -0.0027910874
A61: =Prices!$A$60 -> 45936 | B61: =IFERROR(Prices!B60/Prices!B59-1,"") -> 0.013422327 | C61: =IFERROR(Prices!C60/Prices!C59-1,"") -> 0.022776401 | D61: =IFERROR(Prices!D60/Prices!D59-1,"") -> 0.016318707 | E61: =IFERROR(Prices!E60/Prices!E59-1,"") -> 0.013634781 | F61: =IFERROR(Prices!F60/Prices!F59-1,"") -> 0.029057126 | G61: =IFERROR(Prices!G60/Prices!G59-1,"") -> 0.029039605 | H61: =IFERROR(Prices!H60/Prices!H59-1,"") -> 0.073196986 | I61: =IFERROR(Prices!I60/Prices!I59-1,"") -> 0.01797247 | J61: =IFERROR(SUMPRODUCT(Weights,$B61:$H61),"") -> 0.024419607
A62: =Prices!$A$61 -> 45943 | B62: =IFERROR(Prices!B61/Prices!B60-1,"") -> 0.025403488 | C62: =IFERROR(Prices!C61/Prices!C60-1,"") -> 0.037166864 | D62: =IFERROR(Prices!D61/Prices!D60-1,"") -> 0.022071567 | E62: =IFERROR(Prices!E61/Prices!E60-1,"") -> 0.014640592 | F62: =IFERROR(Prices!F61/Prices!F60-1,"") -> 0.010116532 | G62: =IFERROR(Prices!G61/Prices!G60-1,"") -> 0.0083615125 | H62: =IFERROR(Prices!H61/Prices!H60-1,"") -> -0.006218656 | I62: =IFERROR(Prices!I61/Prices!I60-1,"") -> 0.0059694276 | J62: =IFERROR(SUMPRODUCT(Weights,$B62:$H62),"") -> 0.018435936
A63: =Prices!$A$62 -> 45950 | B63: =IFERROR(Prices!B62/Prices!B61-1,"") -> 0.024562394 | C63: =IFERROR(Prices!C62/Prices!C61-1,"") -> 0.0085984095 | D63: =IFERROR(Prices!D62/Prices!D61-1,"") -> -0.0077801606 | E63: =IFERROR(Prices!E62/Prices!E61-1,"") -> 0.017059957 | F63: =IFERROR(Prices!F62/Prices!F61-1,"") -> 0.0043103448 | G63: =IFERROR(Prices!G62/Prices!G61-1,"") -> -0.0077434303 | H63: =IFERROR(Prices!H62/Prices!H61-1,"") -> 0.025299421 | I63: =IFERROR(Prices!I62/Prices!I61-1,"") -> 0.024410047 | J63: =IFERROR(SUMPRODUCT(Weights,$B63:$H63),"") -> 0.01002546
A64: =Prices!$A$63 -> 45957 | B64: =IFERROR(Prices!B63/Prices!B62-1,"") -> 0.023973546 | C64: =IFERROR(Prices!C63/Prices!C62-1,"") -> 0.012418075 | D64: =IFERROR(Prices!D63/Prices!D62-1,"") -> -0.0074893189 | E64: =IFERROR(Prices!E63/Prices!E62-1,"") -> 0.032267152 | F64: =IFERROR(Prices!F63/Prices!F62-1,"") -> -0.052448877 | G64: =IFERROR(Prices!G63/Prices!G62-1,"") -> -0.0054073983 | H64: =IFERROR(Prices!H63/Prices!H62-1,"") -> 0.011615698 | I64: =IFERROR(Prices!I63/Prices!I62-1,"") -> 0.0047556273 | J64: =IFERROR(SUMPRODUCT(Weights,$B64:$H64),"") -> 0.0048732901
A65: =Prices!$A$64 -> 45964 | B65: =IFERROR(Prices!B64/Prices!B63-1,"") -> -0.0056512379 | C65: =IFERROR(Prices!C64/Prices!C63-1,"") -> -0.025943052 | D65: =IFERROR(Prices!D64/Prices!D63-1,"") -> -0.0050643168 | E65: =IFERROR(Prices!E64/Prices!E63-1,"") -> -0.036815599 | F65: =IFERROR(Prices!F64/Prices!F63-1,"") -> 0.0029307933 | G65: =IFERROR(Prices!G64/Prices!G63-1,"") -> -0.043679723 | H65: =IFERROR(Prices!H64/Prices!H63-1,"") -> -0.018877717 | I65: =IFERROR(Prices!I64/Prices!I63-1,"") -> -0.007806392 | J65: =IFERROR(SUMPRODUCT(Weights,$B65:$H65),"") -> -0.01769394
A66: =Prices!$A$65 -> 45971 | B66: =IFERROR(Prices!B65/Prices!B64-1,"") -> 0.02767253 | C66: =IFERROR(Prices!C65/Prices!C64-1,"") -> 0.049720168 | D66: =IFERROR(Prices!D65/Prices!D64-1,"") -> 0.0074315382 | E66: =IFERROR(Prices!E65/Prices!E64-1,"") -> 0.031397296 | F66: =IFERROR(Prices!F65/Prices!F64-1,"") -> 0.017533373 | G66: =IFERROR(Prices!G65/Prices!G64-1,"") -> 0.01324375 | H66: =IFERROR(Prices!H65/Prices!H64-1,"") -> 0.054350701 | I66: =IFERROR(Prices!I65/Prices!I64-1,"") -> -0.0073360026 | J66: =IFERROR(SUMPRODUCT(Weights,$B66:$H66),"") -> 0.027917877
A67: =Prices!$A$66 -> 45978 | B67: =IFERROR(Prices!B66/Prices!B65-1,"") -> 0.018236882 | C67: =IFERROR(Prices!C66/Prices!C65-1,"") -> 0.029513972 | D67: =IFERROR(Prices!D66/Prices!D65-1,"") -> 0.0085388036 | E67: =IFERROR(Prices!E66/Prices!E65-1,"") -> 0.0051193687 | F67: =IFERROR(Prices!F66/Prices!F65-1,"") -> -0.013249788 | G67: =IFERROR(Prices!G66/Prices!G65-1,"") -> 0.018681459 | H67: =IFERROR(Prices!H66/Prices!H65-1,"") -> 0.0084033613 | I67: =IFERROR(Prices!I66/Prices!I65-1,"") -> 0.017169532 | J67: =IFERROR(SUMPRODUCT(Weights,$B67:$H67),"") -> 0.012027214
A68: =Prices!$A$67 -> 45985 | B68: =IFERROR(Prices!B67/Prices!B66-1,"") -> 0.013513514 | C68: =IFERROR(Prices!C67/Prices!C66-1,"") -> -0.028251722 | D68: =IFERROR(Prices!D67/Prices!D66-1,"") -> 0.0095686589 | E68: =IFERROR(Prices!E67/Prices!E66-1,"") -> 0.011105866 | F68: =IFERROR(Prices!F67/Prices!F66-1,"") -> 0.012898532 | G68: =IFERROR(Prices!G67/Prices!G66-1,"") -> -0.0048194279 | H68: =IFERROR(Prices!H67/Prices!H66-1,"") -> 0.010074627 | I68: =IFERROR(Prices!I67/Prices!I66-1,"") -> -0.0020738972 | J68: =IFERROR(SUMPRODUCT(Weights,$B68:$H68),"") -> 0.0037366787
A69: =Prices!$A$68 -> 45992 | B69: =IFERROR(Prices!B68/Prices!B67-1,"") -> -0.017161085 | C69: =IFERROR(Prices!C68/Prices!C67-1,"") -> 0.0034259612 | D69: =IFERROR(Prices!D68/Prices!D67-1,"") -> -0.0042675665 | E69: =IFERROR(Prices!E68/Prices!E67-1,"") -> -0.007715746 | F69: =IFERROR(Prices!F68/Prices!F67-1,"") -> -0.006856919 | G69: =IFERROR(Prices!G68/Prices!G67-1,"") -> 0.024025157 | H69: =IFERROR(Prices!H68/Prices!H67-1,"") -> 0.036202438 | I69: =IFERROR(Prices!I68/Prices!I67-1,"") -> 0.0083302837 | J69: =IFERROR(SUMPRODUCT(Weights,$B69:$H69),"") -> 0.00016491334
A70: =Prices!$A$69 -> 45999 | B70: =IFERROR(Prices!B69/Prices!B68-1,"") -> 0.010320654 | C70: =IFERROR(Prices!C69/Prices!C68-1,"") -> -0.012044765 | D70: =IFERROR(Prices!D69/Prices!D68-1,"") -> -0.0017940795 | E70: =IFERROR(Prices!E69/Prices!E68-1,"") -> 0.0088900995 | F70: =IFERROR(Prices!F69/Prices!F68-1,"") -> -0.0022356654 | G70: =IFERROR(Prices!G69/Prices!G68-1,"") -> 0.014740204 | H70: =IFERROR(Prices!H69/Prices!H68-1,"") -> -0.0058229352 | I70: =IFERROR(Prices!I69/Prices!I68-1,"") -> -0.0082213201 | J70: =IFERROR(SUMPRODUCT(Weights,$B70:$H70),"") -> 0.0025190182
A71: =Prices!$A$70 -> 46006 | B71: =IFERROR(Prices!B70/Prices!B69-1,"") -> 0.0055252168 | C71: =IFERROR(Prices!C70/Prices!C69-1,"") -> 0.0068637804 | D71: =IFERROR(Prices!D70/Prices!D69-1,"") -> -0.015976036 | E71: =IFERROR(Prices!E70/Prices!E69-1,"") -> -0.00014727179 | F71: =IFERROR(Prices!F70/Prices!F69-1,"") -> -0.0001977066 | G71: =IFERROR(Prices!G70/Prices!G69-1,"") -> -0.0065367389 | H71: =IFERROR(Prices!H70/Prices!H69-1,"") -> -0.018407841 | I71: =IFERROR(Prices!I70/Prices!I69-1,"") -> 0.0025712089 | J71: =IFERROR(SUMPRODUCT(Weights,$B71:$H71),"") -> -0.0025814957
A72: =Prices!$A$71 -> 46013 | B72: =IFERROR(Prices!B71/Prices!B70-1,"") -> -0.0037697272 | C72: =IFERROR(Prices!C71/Prices!C70-1,"") -> 0.0036706869 | D72: =IFERROR(Prices!D71/Prices!D70-1,"") -> 0.0066971081 | E72: =IFERROR(Prices!E71/Prices!E70-1,"") -> -0.0064318154 | F72: =IFERROR(Prices!F71/Prices!F70-1,"") -> -0.0073165909 | G72: =IFERROR(Prices!G71/Prices!G70-1,"") -> 0.011088096 | H72: =IFERROR(Prices!H71/Prices!H70-1,"") -> 0.011264004 | I72: =IFERROR(Prices!I71/Prices!I70-1,"") -> 0.0055749004 | J72: =IFERROR(SUMPRODUCT(Weights,$B72:$H72),"") -> 0.0012540188
A73: =Prices!$A$72 -> 46020 | B73: =IFERROR(Prices!B72/Prices!B71-1,"") -> 0.021228835 | C73: =IFERROR(Prices!C72/Prices!C71-1,"") -> 0.00042747221 | D73: =IFERROR(Prices!D72/Prices!D71-1,"") -> 0.0095756476 | E73: =IFERROR(Prices!E72/Prices!E71-1,"") -> 0.028685791 | F73: =IFERROR(Prices!F72/Prices!F71-1,"") -> 0.0037184595 | G73: =IFERROR(Prices!G72/Prices!G71-1,"") -> 0.021932996 | H73: =IFERROR(Prices!H72/Prices!H71-1,"") -> -0.012463122 | I73: =IFERROR(Prices!I72/Prices!I71-1,"") -> -0.0087993756 | J73: =IFERROR(SUMPRODUCT(Weights,$B73:$H73),"") -> 0.012355604
A74: =Prices!$A$73 -> 46027 | B74: =IFERROR(Prices!B73/Prices!B72-1,"") -> -0.073478616 | C74: =IFERROR(Prices!C73/Prices!C72-1,"") -> -0.037601481 | D74: =IFERROR(Prices!D73/Prices!D72-1,"") -> -0.0625 | E74: =IFERROR(Prices!E73/Prices!E72-1,"") -> -0.033194024 | F74: =IFERROR(Prices!F73/Prices!F72-1,"") -> -0.030365176 | G74: =IFERROR(Prices!G73/Prices!G72-1,"") -> -0.027063679 | H74: =IFERROR(Prices!H73/Prices!H72-1,"") -> 0.012925253 | I74: =IFERROR(Prices!I73/Prices!I72-1,"") -> 0.011880348 | J74: =IFERROR(SUMPRODUCT(Weights,$B74:$H74),"") -> -0.042290657
A75: =Prices!$A$74 -> 46034 | B75: =IFERROR(Prices!B74/Prices!B73-1,"") -> -0.011794211 | C75: =IFERROR(Prices!C74/Prices!C73-1,"") -> -0.0052784766 | D75: =IFERROR(Prices!D74/Prices!D73-1,"") -> -0.0084132055 | E75: =IFERROR(Prices!E74/Prices!E73-1,"") -> -0.041935804 | F75: =IFERROR(Prices!F74/Prices!F73-1,"") -> -0.046530668 | G75: =IFERROR(Prices!G74/Prices!G73-1,"") -> -0.038906733 | H75: =IFERROR(Prices!H74/Prices!H73-1,"") -> 0.022029614 | I75: =IFERROR(Prices!I74/Prices!I73-1,"") -> -0.017525543 | J75: =IFERROR(SUMPRODUCT(Weights,$B75:$H75),"") -> -0.018907256
A76: =Prices!$A$75 -> 46041 | B76: =IFERROR(Prices!B75/Prices!B74-1,"") -> -0.04924892 | C76: =IFERROR(Prices!C75/Prices!C74-1,"") -> -0.015721087 | D76: =IFERROR(Prices!D75/Prices!D74-1,"") -> -0.016109977 | E76: =IFERROR(Prices!E75/Prices!E74-1,"") -> -0.029198216 | F76: =IFERROR(Prices!F75/Prices!F74-1,"") -> -0.059033989 | G76: =IFERROR(Prices!G75/Prices!G74-1,"") -> -0.024591714 | H76: =IFERROR(Prices!H75/Prices!H74-1,"") -> 0.0053003534 | I76: =IFERROR(Prices!I75/Prices!I74-1,"") -> -0.0079390467 | J76: =IFERROR(SUMPRODUCT(Weights,$B76:$H76),"") -> -0.029747714
A77: =Prices!$A$76 -> 46048 | B77: =IFERROR(Prices!B76/Prices!B75-1,"") -> 0 | C77: =IFERROR(Prices!C76/Prices!C75-1,"") -> 0 | D77: =IFERROR(Prices!D76/Prices!D75-1,"") -> 0 | E77: =IFERROR(Prices!E76/Prices!E75-1,"") -> 0 | F77: =IFERROR(Prices!F76/Prices!F75-1,"") -> 0 | G77: =IFERROR(Prices!G76/Prices!G75-1,"") -> 0 | H77: =IFERROR(Prices!H76/Prices!H75-1,"") -> 0 | I77: =IFERROR(Prices!I76/Prices!I75-1,"") -> -0.016028595 | J77: =IFERROR(SUMPRODUCT(Weights,$B77:$H77),"") -> 0
A78: =Prices!$A$77 -> 46055 | B78: =IFERROR(Prices!B77/Prices!B76-1,"") -> 0.046677729 | C78: =IFERROR(Prices!C77/Prices!C76-1,"") -> 0.027056986 | D78: =IFERROR(Prices!D77/Prices!D76-1,"") -> 0.027289597 | E78: =IFERROR(Prices!E77/Prices!E76-1,"") -> 0.086623217 | F78: =IFERROR(Prices!F77/Prices!F76-1,"") -> 0.011406844 | G78: =IFERROR(Prices!G77/Prices!G76-1,"") -> -0.030512638 | H78: =IFERROR(Prices!H77/Prices!H76-1,"") -> -0.066373755 | I78: =IFERROR(Prices!I77/Prices!I76-1,"") -> -0.0034557544 | J78: =IFERROR(SUMPRODUCT(Weights,$B78:$H78),"") -> 0.022748782
A79: =Prices!$A$78 -> 46062 | B79: =IFERROR(Prices!B78/Prices!B77-1,"") -> -0.021505376 | C79: =IFERROR(Prices!C78/Prices!C77-1,"") -> -0.016532575 | D79: =IFERROR(Prices!D78/Prices!D77-1,"") -> -0.039528212 | E79: =IFERROR(Prices!E78/Prices!E77-1,"") -> 0.026007227 | F79: =IFERROR(Prices!F78/Prices!F77-1,"") -> 0.0011278195 | G79: =IFERROR(Prices!G78/Prices!G77-1,"") -> 0.016003201 | H79: =IFERROR(Prices!H78/Prices!H77-1,"") -> -0.086904687 | I79: =IFERROR(Prices!I78/Prices!I77-1,"") -> 0.031046236 | J79: =IFERROR(SUMPRODUCT(Weights,$B79:$H79),"") -> -0.015480042
A80: =Prices!$A$79 -> 46069 | B80: =IFERROR(Prices!B79/Prices!B78-1,"") -> -0.00014088476 | C80: =IFERROR(Prices!C79/Prices!C78-1,"") -> -0.013617998 | D80: =IFERROR(Prices!D79/Prices!D78-1,"") -> 0.0087952207 | E80: =IFERROR(Prices!E79/Prices!E78-1,"") -> 0.04952203 | F80: =IFERROR(Prices!F79/Prices!F78-1,"") -> 0.0072099136 | G80: =IFERROR(Prices!G79/Prices!G78-1,"") -> -0.017063726 | H80: =IFERROR(Prices!H79/Prices!H78-1,"") -> -0.012850467 | I80: =IFERROR(Prices!I79/Prices!I78-1,"") -> -0.0071345203 | J80: =IFERROR(SUMPRODUCT(Weights,$B80:$H80),"") -> 0.0038382645
A81: =Prices!$A$80 -> 46076 | B81: =IFERROR(Prices!B80/Prices!B79-1,"") -> -0.017965337 | C81: =IFERROR(Prices!C80/Prices!C79-1,"") -> -0.0496106 | D81: =IFERROR(Prices!D80/Prices!D79-1,"") -> -0.026429786 | E81: =IFERROR(Prices!E80/Prices!E79-1,"") -> -0.023352965 | F81: =IFERROR(Prices!F80/Prices!F79-1,"") -> 0.0052941615 | G81: =IFERROR(Prices!G80/Prices!G79-1,"") -> -0.0080122855 | H81: =IFERROR(Prices!H80/Prices!H79-1,"") -> -0.032996867 | I81: =IFERROR(Prices!I80/Prices!I79-1,"") -> 0.0011778334 | J81: =IFERROR(SUMPRODUCT(Weights,$B81:$H81),"") -> -0.022103394
A82: =Prices!$A$81 -> 46083 | B82: =IFERROR(Prices!B81/Prices!B80-1,"") -> 0.0078197862 | C82: =IFERROR(Prices!C81/Prices!C80-1,"") -> -0.0045229607 | D82: =IFERROR(Prices!D81/Prices!D80-1,"") -> -0.034581808 | E82: =IFERROR(Prices!E81/Prices!E80-1,"") -> -0.076782834 | F82: =IFERROR(Prices!F81/Prices!F80-1,"") -> -0.020026702 | G82: =IFERROR(Prices!G81/Prices!G80-1,"") -> -0.046981221 | H82: =IFERROR(Prices!H81/Prices!H80-1,"") -> -0.023324455 | I82: =IFERROR(Prices!I81/Prices!I80-1,"") -> -0.032952234 | J82: =IFERROR(SUMPRODUCT(Weights,$B82:$H82),"") -> -0.024956913
A83: =Prices!$A$82 -> 46090 | B83: =IFERROR(Prices!B82/Prices!B81-1,"") -> -0.017155467 | C83: =IFERROR(Prices!C82/Prices!C81-1,"") -> -0.036027368 | D83: =IFERROR(Prices!D82/Prices!D81-1,"") -> -0.046730062 | E83: =IFERROR(Prices!E82/Prices!E81-1,"") -> -0.129323 | F83: =IFERROR(Prices!F82/Prices!F81-1,"") -> -0.0049197699 | G83: =IFERROR(Prices!G82/Prices!G81-1,"") -> -0.11074228 | H83: =IFERROR(Prices!H82/Prices!H81-1,"") -> -0.023070686 | I83: =IFERROR(Prices!I82/Prices!I81-1,"") -> -0.033686905 | J83: =IFERROR(SUMPRODUCT(Weights,$B83:$H83),"") -> -0.050420401
A84: =Prices!$A$83 -> 46097 | B84: =IFERROR(Prices!B83/Prices!B82-1,"") -> 0.024407909 | C84: =IFERROR(Prices!C83/Prices!C82-1,"") -> 0.023677498 | D84: =IFERROR(Prices!D83/Prices!D82-1,"") -> -0.044736842 | E84: =IFERROR(Prices!E83/Prices!E82-1,"") -> -0.0012212853 | F84: =IFERROR(Prices!F83/Prices!F82-1,"") -> -0.044344717 | G84: =IFERROR(Prices!G83/Prices!G82-1,"") -> 0.00079421809 | H84: =IFERROR(Prices!H83/Prices!H82-1,"") -> 0.0062622604 | I84: =IFERROR(Prices!I83/Prices!I82-1,"") -> -0.025771962 | J84: =IFERROR(SUMPRODUCT(Weights,$B84:$H84),"") -> -0.0023785189
A85: =Prices!$A$84 -> 46104 | B85: =IFERROR(Prices!B84/Prices!B83-1,"") -> -0.046875 | C85: =IFERROR(Prices!C84/Prices!C83-1,"") -> -0.0011917014 | D85: =IFERROR(Prices!D84/Prices!D83-1,"") -> -0.031071818 | E85: =IFERROR(Prices!E84/Prices!E83-1,"") -> 0.037644113 | F85: =IFERROR(Prices!F84/Prices!F83-1,"") -> -0.011222541 | G85: =IFERROR(Prices!G84/Prices!G83-1,"") -> -0.016824062 | H85: =IFERROR(Prices!H84/Prices!H83-1,"") -> 0.02301867 | I85: =IFERROR(Prices!I84/Prices!I83-1,"") -> -0.038282627 | J85: =IFERROR(SUMPRODUCT(Weights,$B85:$H85),"") -> -0.011644514
A86: =Prices!$A$85 -> 46111 | B86: =IFERROR(Prices!B85/Prices!B84-1,"") -> 0.0017802834 | C86: =IFERROR(Prices!C85/Prices!C84-1,"") -> -0.029394219 | D86: =IFERROR(Prices!D85/Prices!D84-1,"") -> -0.0070087278 | E86: =IFERROR(Prices!E85/Prices!E84-1,"") -> 0.013748211 | F86: =IFERROR(Prices!F85/Prices!F84-1,"") -> -0.040167431 | G86: =IFERROR(Prices!G85/Prices!G84-1,"") -> 0.019533457 | H86: =IFERROR(Prices!H85/Prices!H84-1,"") -> 0.027704485 | I86: =IFERROR(Prices!I85/Prices!I84-1,"") -> -0.0080510289 | J86: =IFERROR(SUMPRODUCT(Weights,$B86:$H86),"") -> -0.0031089005
A87: =Prices!$A$86 -> 46118 | B87: =IFERROR(Prices!B86/Prices!B85-1,"") -> -0.00022213995 | C87: =IFERROR(Prices!C86/Prices!C85-1,"") -> 0.044867855 | D87: =IFERROR(Prices!D86/Prices!D85-1,"") -> 0.079105074 | E87: =IFERROR(Prices!E86/Prices!E85-1,"") -> 0.095984058 | F87: =IFERROR(Prices!F86/Prices!F85-1,"") -> 0.03111372 | G87: =IFERROR(Prices!G86/Prices!G85-1,"") -> 0.085345578 | H87: =IFERROR(Prices!H86/Prices!H85-1,"") -> 0.034945086 | I87: =IFERROR(Prices!I86/Prices!I85-1,"") -> 0.028518122 | J87: =IFERROR(SUMPRODUCT(Weights,$B87:$H87),"") -> 0.049102789
A88: =Prices!$A$87 -> 46125 | B88: =IFERROR(Prices!B87/Prices!B86-1,"") -> 0.010961339 | C88: =IFERROR(Prices!C87/Prices!C86-1,"") -> -0.012352941 | D88: =IFERROR(Prices!D87/Prices!D86-1,"") -> -0.012834753 | E88: =IFERROR(Prices!E87/Prices!E86-1,"") -> 0.034394808 | F88: =IFERROR(Prices!F87/Prices!F86-1,"") -> 0.0091907279 | G88: =IFERROR(Prices!G87/Prices!G86-1,"") -> -0.018673864 | H88: =IFERROR(Prices!H87/Prices!H86-1,"") -> -0.0061328556 | I88: =IFERROR(Prices!I87/Prices!I86-1,"") -> 0.038069961 | J88: =IFERROR(SUMPRODUCT(Weights,$B88:$H88),"") -> 0.0018682937
A89: =Prices!$A$88 -> 46132 | B89: =IFERROR(Prices!B88/Prices!B87-1,"") -> -0.027252747 | C89: =IFERROR(Prices!C88/Prices!C87-1,"") -> -0.01754291 | D89: =IFERROR(Prices!D88/Prices!D87-1,"") -> -0.018814852 | E89: =IFERROR(Prices!E88/Prices!E87-1,"") -> -0.019970216 | F89: =IFERROR(Prices!F88/Prices!F87-1,"") -> 0.043681496 | G89: =IFERROR(Prices!G88/Prices!G87-1,"") -> -0.030104809 | H89: =IFERROR(Prices!H88/Prices!H87-1,"") -> -0.16577688 | I89: =IFERROR(Prices!I88/Prices!I87-1,"") -> 0.021901895 | J89: =IFERROR(SUMPRODUCT(Weights,$B89:$H89),"") -> -0.027808343
A90: =Prices!$A$89 -> 46139 | B90: =IFERROR(Prices!B89/Prices!B88-1,"") -> 0.077571923 | C90: =IFERROR(Prices!C89/Prices!C88-1,"") -> 0.039845688 | D90: =IFERROR(Prices!D89/Prices!D88-1,"") -> -0.016754794 | E90: =IFERROR(Prices!E89/Prices!E88-1,"") -> -7.473283e-05 | F90: =IFERROR(Prices!F89/Prices!F88-1,"") -> 0.011274131 | G90: =IFERROR(Prices!G89/Prices!G88-1,"") -> 0.020386266 | H90: =IFERROR(Prices!H89/Prices!H88-1,"") -> -0.0034075798 | I90: =IFERROR(Prices!I89/Prices!I88-1,"") -> -0.011169796 | J90: =IFERROR(SUMPRODUCT(Weights,$B90:$H90),"") -> 0.024787279
A91: =Prices!$A$90 -> 46146 | B91: =IFERROR(Prices!B90/Prices!B89-1,"") -> 0.0030752027 | C91: =IFERROR(Prices!C90/Prices!C89-1,"") -> -0.027718889 | D91: =IFERROR(Prices!D90/Prices!D89-1,"") -> 0.011856939 | E91: =IFERROR(Prices!E90/Prices!E89-1,"") -> -0.009840558 | F91: =IFERROR(Prices!F90/Prices!F89-1,"") -> 0.028558338 | G91: =IFERROR(Prices!G90/Prices!G89-1,"") -> 0.03094487 | H91: =IFERROR(Prices!H90/Prices!H89-1,"") -> -0.00058377116 | I91: =IFERROR(Prices!I90/Prices!I89-1,"") -> 0.0011041338 | J91: =IFERROR(SUMPRODUCT(Weights,$B91:$H91),"") -> 0.0040381716
A92: =Prices!$A$91 -> 46153 | B92: =IFERROR(Prices!B91/Prices!B90-1,"") -> -0.06884058 | C92: =IFERROR(Prices!C91/Prices!C90-1,"") -> 0.038648133 | D92: =IFERROR(Prices!D91/Prices!D90-1,"") -> -0.017096754 | E92: =IFERROR(Prices!E91/Prices!E90-1,"") -> -0.01648006 | F92: =IFERROR(Prices!F91/Prices!F90-1,"") -> 0.063177431 | G92: =IFERROR(Prices!G91/Prices!G90-1,"") -> -0.036791491 | H92: =IFERROR(Prices!H91/Prices!H90-1,"") -> -0.054906542 | I92: =IFERROR(Prices!I91/Prices!I90-1,"") -> -0.012581259 | J92: =IFERROR(SUMPRODUCT(Weights,$B92:$H92),"") -> -0.016683111
A93: =Prices!$A$92 -> 46160 | B93: =IFERROR(Prices!B92/Prices!B91-1,"") -> 0.013543849 | C93: =IFERROR(Prices!C92/Prices!C91-1,"") -> -0.017844022 | D93: =IFERROR(Prices!D92/Prices!D91-1,"") -> -0.00091205212 | E93: =IFERROR(Prices!E92/Prices!E91-1,"") -> 0.0045024303 | F93: =IFERROR(Prices!F92/Prices!F91-1,"") -> -0.022973256 | G93: =IFERROR(Prices!G92/Prices!G91-1,"") -> -0.017699115 | H93: =IFERROR(Prices!H92/Prices!H91-1,"") -> 0.027723821 | I93: =IFERROR(Prices!I92/Prices!I91-1,"") -> -0.0069659657 | J93: =IFERROR(SUMPRODUCT(Weights,$B93:$H93),"") -> -0.0014535262
A94: =Prices!$A$93 -> 46167 | B94: =IFERROR(Prices!B93/Prices!B92-1,"") -> -0.024584718 | C94: =IFERROR(Prices!C93/Prices!C92-1,"") -> -0.022656834 | D94: =IFERROR(Prices!D93/Prices!D92-1,"") -> -0.029016693 | E94: =IFERROR(Prices!E93/Prices!E92-1,"") -> 0.038175521 | F94: =IFERROR(Prices!F93/Prices!F92-1,"") -> 0.0012864494 | G94: =IFERROR(Prices!G93/Prices!G92-1,"") -> 0.010780011 | H94: =IFERROR(Prices!H93/Prices!H92-1,"") -> 0.017010309 | I94: =IFERROR(Prices!I93/Prices!I92-1,"") -> 0.016141684 | J94: =IFERROR(SUMPRODUCT(Weights,$B94:$H94),"") -> -0.0050820382
A95: =Prices!$A$94 -> 46174 | B95: =IFERROR(Prices!B94/Prices!B93-1,"") -> -0.022858008 | C95: =IFERROR(Prices!C94/Prices!C93-1,"") -> -0.016839803 | D95: =IFERROR(Prices!D94/Prices!D93-1,"") -> 0.0033577329 | E95: =IFERROR(Prices!E94/Prices!E93-1,"") -> -0.030246535 | F95: =IFERROR(Prices!F94/Prices!F93-1,"") -> 0.00021413276 | G95: =IFERROR(Prices!G94/Prices!G93-1,"") -> -0.0058657728 | H95: =IFERROR(Prices!H94/Prices!H93-1,"") -> -0.024581855 | I95: =IFERROR(Prices!I94/Prices!I93-1,"") -> -0.027010142 | J95: =IFERROR(SUMPRODUCT(Weights,$B95:$H95),"") -> -0.014404731
A96: =Prices!$A$95 -> 46181 | B96: =IFERROR(Prices!B95/Prices!B94-1,"") -> 0.0015491867 | C96: =IFERROR(Prices!C95/Prices!C94-1,"") -> 0.013513514 | D96: =IFERROR(Prices!D95/Prices!D94-1,"") -> 0.034000402 | E96: =IFERROR(Prices!E95/Prices!E94-1,"") -> 0.02430942 | F96: =IFERROR(Prices!F95/Prices!F94-1,"") -> -0.0084921145 | G96: =IFERROR(Prices!G95/Prices!G94-1,"") -> 0.024214559 | H96: =IFERROR(Prices!H95/Prices!H94-1,"") -> -0.039057764 | I96: =IFERROR(Prices!I95/Prices!I94-1,"") -> -0.011102256 | J96: =IFERROR(SUMPRODUCT(Weights,$B96:$H96),"") -> 0.0092582137
A97: =Prices!$A$96 -> 46188 | B97: =IFERROR(Prices!B96/Prices!B95-1,"") -> 0.012761021 | C97: =IFERROR(Prices!C96/Prices!C95-1,"") -> 0.048449931 | D97: =IFERROR(Prices!D96/Prices!D95-1,"") -> 0.009515179 | E97: =IFERROR(Prices!E96/Prices!E95-1,"") -> 0.039537698 | F97: =IFERROR(Prices!F96/Prices!F95-1,"") -> -0.027062041 | G97: =IFERROR(Prices!G96/Prices!G95-1,"") -> 0.0021696843 | H97: =IFERROR(Prices!H96/Prices!H95-1,"") -> 0.019917087 | I97: =IFERROR(Prices!I96/Prices!I95-1,"") -> 0.031609237 | J97: =IFERROR(SUMPRODUCT(Weights,$B97:$H97),"") -> 0.015970534
A98: =Prices!$A$97 -> 46195 | B98: =IFERROR(Prices!B97/Prices!B96-1,"") -> 0.0065673921 | C98: =IFERROR(Prices!C97/Prices!C96-1,"") -> -0.031452795 | D98: =IFERROR(Prices!D97/Prices!D96-1,"") -> 0.021159272 | E98: =IFERROR(Prices!E97/Prices!E96-1,"") -> 0.0016629448 | F98: =IFERROR(Prices!F97/Prices!F96-1,"") -> 0.065320314 | G98: =IFERROR(Prices!G97/Prices!G96-1,"") -> 0.026129153 | H98: =IFERROR(Prices!H97/Prices!H96-1,"") -> -0.027392418 | I98: =IFERROR(Prices!I97/Prices!I96-1,"") -> 0.010438544 | J98: =IFERROR(SUMPRODUCT(Weights,$B98:$H98),"") -> 0.0087079023
A99: =Prices!$A$98 -> 46202 | B99: =IFERROR(Prices!B98/Prices!B97-1,"") -> -0.010697216 | C99: =IFERROR(Prices!C98/Prices!C97-1,"") -> 0.032258065 | D99: =IFERROR(Prices!D98/Prices!D97-1,"") -> 0.0059650885 | E99: =IFERROR(Prices!E98/Prices!E97-1,"") -> -0.045014704 | F99: =IFERROR(Prices!F98/Prices!F97-1,"") -> 0.012568572 | G99: =IFERROR(Prices!G98/Prices!G97-1,"") -> 0.045180065 | H99: =IFERROR(Prices!H98/Prices!H97-1,"") -> 0.034796039 | I99: =IFERROR(Prices!I98/Prices!I97-1,"") -> -0.006499234 | J99: =IFERROR(SUMPRODUCT(Weights,$B99:$H99),"") -> 0.0070325347
A100: =Prices!$A$99 -> 46209 | B100: =IFERROR(Prices!B99/Prices!B98-1,"") -> 0.0029141104 | C100: =IFERROR(Prices!C99/Prices!C98-1,"") -> 0.0052345059 | D100: =IFERROR(Prices!D99/Prices!D98-1,"") -> 0.02983584 | E100: =IFERROR(Prices!E99/Prices!E98-1,"") -> -0.020066557 | F100: =IFERROR(Prices!F99/Prices!F98-1,"") -> -0.012892607 | G100: =IFERROR(Prices!G99/Prices!G98-1,"") -> -0.035639705 | H100: =IFERROR(Prices!H99/Prices!H98-1,"") -> 0.022036874 | I100: =IFERROR(Prices!I99/Prices!I98-1,"") -> 0.020216093 | J100: =IFERROR(SUMPRODUCT(Weights,$B100:$H100),"") -> -0.00071907945
...

Sheet Risk_Analysis
A1: RISK & RETURN ANALYSIS
A2: Every figure below is a live formula over the weekly return series on the Returns sheet. No calculated output is hardcoded anywhere in this workbook.
A4: 1 · RETURN & RISK SUMMARY
A5: Metric | B5: Portfolio | C5: NIFTY 50 | D5: Difference | J5: Excel formula used | K5: Interpretation note
A6: Observations (weekly returns) | B6: =COUNT(PortRet) -> 104 | C6: =COUNT(BenchRet) -> 104 | D6: — | J6: =COUNT(PortRet) | K6: 104 weekly observations ≈ 2 years
A7: Mean weekly return | B7: =AVERAGE(PortRet) -> -0.00014680466 | C7: =AVERAGE(BenchRet) -> -0.00028069112 | D7: =B7-C7 -> 0.00013388647 | J7: =AVERAGE(PortRet) | K7: Arithmetic mean of weekly simple returns
A8: Weekly volatility | B8: =_xlfn.STDEV.S(PortRet) -> 0.019667497 | C8: =_xlfn.STDEV.S(BenchRet) -> 0.018883574 | D8: =B8-C8 -> 0.00078392294 | J8: =STDEV.S(PortRet) | K8: Sample standard deviation — correct choice for a return sample
A9: Annualised return | B9: =AVERAGE(PortRet)*WeeksPerYear -> -0.0076338423 | C9: =AVERAGE(BenchRet)*WeeksPerYear -> -0.014595938 | D9: =B9-C9 -> 0.0069620962 | J9: =AVERAGE(PortRet)*52 | K9: Mean weekly return scaled by 52 weeks
A10: Annualised volatility | B10: =_xlfn.STDEV.S(PortRet)*SQRT(WeeksPerYear) -> 0.14182434 | C10: =_xlfn.STDEV.S(BenchRet)*SQRT(WeeksPerYear) -> 0.13617139 | D10: =B10-C10 -> 0.0056529487 | J10: =STDEV.S(PortRet)*SQRT(52) | K10: Variance scales with time, so σ scales with √time
A11: Cumulative return (full period) | B11: =Drawdown!$B$1011 -> -0.034623975 | C11: =Drawdown!$C$1011 -> -0.046408061 | D11: =B11-C11 -> 0.011784086 | J11: =Drawdown value / 100 − 1 | K11: Actual compounded return, not the annualised approximation
A12: Growth of ₹100 | B12: =Drawdown!$B$1010 -> 96.537602 | C12: =Drawdown!$C$1010 -> 95.359194 | D12: =B12-C12 -> 1.1784086 | J12: =100 × Π(1 + weekly return) | K12: Both series start at exactly ₹100
A13: Best week | B13: =MAX(PortRet) -> 0.054554697 | C13: =MAX(BenchRet) -> 0.05265645 | D13: =B13-C13 -> 0.0018982464 | J13: =MAX(PortRet) | K13: Largest single-week gain
A14: Worst week | B14: =MIN(PortRet) -> -0.058302104 | C14: =MIN(BenchRet) -> -0.043344239 | D14: =B14-C14 -> -0.014957865 | J14: =MIN(PortRet) | K14: Largest single-week loss
A15: Positive weeks | B15: =COUNTIF(PortRet,">0")/COUNT(PortRet) -> 0.49038462 | C15: =COUNTIF(BenchRet,">0")/COUNT(BenchRet) -> 0.5 | D15: =B15-C15 -> -0.0096153846 | J15: =COUNTIF(PortRet,">0")/COUNT(PortRet) | K15: Hit rate — share of weeks with a positive return
A17: 2 · RISK-ADJUSTED PERFORMANCE
A18: Metric | B18: Portfolio | C18: NIFTY 50 | D18: Difference | J18: Excel formula used | K18: Interpretation note
A19: Risk-free rate (annual) | B19: =RiskFree -> 0.0695 | C19: =RiskFree -> 0.0695 | D19: — | J19: =RiskFree (named range → Inputs tab) | K19: India 10Y G-Sec, documented on the Inputs sheet
A20: Excess return over risk-free | B20: =B9-RiskFree -> -0.077133842 | C20: =C9-RiskFree -> -0.084095938 | D20: =B20-C20 -> 0.0069620962 | J20: =AnnualReturn − RiskFree | K20: Numerator of the Sharpe ratio
A21: Sharpe ratio | B21: =IFERROR((B9-RiskFree)/B10,"n.m.") -> -0.54386887 | C21: =IFERROR((C9-RiskFree)/C10,"n.m.") -> -0.61757422 | D21: =B21-C21 -> 0.073705344 | J21: =(AnnReturn − RiskFree)/AnnVol | K21: Excess return per unit of TOTAL risk
A22: Downside deviation (annualised) | B22: =SQRT(SUMPRODUCT((PortRet<0)*(PortRet^2))/(COUNT(PortRet)-1))*SQRT(WeeksPerYear) -> 0.10233382 | C22: =SQRT(SUMPRODUCT((BenchRet<0)*(BenchRet^2))/(COUNT(BenchRet)-1))*SQRT(WeeksPerYear) -> 0.093637086 | D22: =B22-C22 -> 0.0086967303 | J22: =SQRT(SUMPRODUCT((r<0)*r^2)/(n−1))*√52 | K22: Volatility of negative weeks only
A23: Sortino ratio | B23: =IFERROR((B9-RiskFree)/B22,"n.m.") -> -0.75374734 | C23: =IFERROR((C9-RiskFree)/C22,"n.m.") -> -0.89810503 | D23: =B23-C23 -> 0.14435769 | J23: =(AnnReturn − RiskFree)/DownsideDev | K23: Sharpe's fix for penalising upside volatility
A25: 3 · SYSTEMATIC RISK — BETA, ALPHA AND MARKET SENSITIVITY
A26: Metric | B26: Portfolio | C26: NIFTY 50 | D26: Difference | J26: Excel formula used | K26: Interpretation note
A27: Beta vs NIFTY 50 | B27: =SLOPE(PortRet,BenchRet) -> 0.28058366 | C27: 1 | D27: — | J27: =SLOPE(PortRet,BenchRet) | K27: Regression slope of portfolio returns on benchmark returns
A28: Correlation vs NIFTY 50 | B28: =CORREL(PortRet,BenchRet) -> 0.26939993 | C28: 1 | D28: — | J28: =CORREL(PortRet,BenchRet) | K28: How closely the portfolio tracks the index week to week
A29: R² (variance explained by market) | B29: =RSQ(PortRet,BenchRet) -> 0.072576323 | C29: 1 | D29: — | J29: =RSQ(PortRet,BenchRet) | K29: Share of portfolio variance attributable to market movement
A30: Regression intercept (weekly) | B30: =INTERCEPT(PortRet,BenchRet) -> -6.8047316e-05 | C30: — | D30: — | J30: =INTERCEPT(PortRet,BenchRet) | K30: Weekly return unexplained by market exposure
A31: Raw excess return vs NIFTY | B31: =B9-C9 -> 0.0069620962 | C31: — | D31: — | J31: =PortAnnRet − BenchAnnRet | K31: NOT alpha — makes no adjustment for risk taken
A32: CAPM expected return | B32: =RiskFree+B27*(C9-RiskFree) -> 0.045904054 | C32: — | D32: — | J32: =Rf + β × (Rb − Rf) | K32: What the portfolio's market exposure alone should have delivered
A33: Jensen's alpha (annualised) | B33: =B9-(RiskFree+B27*(C9-RiskFree)) -> -0.053537896 | C33: — | D33: — | J33: =Rp − [Rf + β(Rb − Rf)] | K33: Return above what market exposure predicts — the real test of skill
A34: Treynor ratio | B34: =IFERROR((B9-RiskFree)/B27,"n.m.") -> -0.27490497 | C34: =IFERROR((C9-RiskFree)/1,"n.m.") -> -0.084095938 | D34: — | J34: =(Rp − Rf)/β | K34: Excess return per unit of SYSTEMATIC risk
A35: Maximum drawdown | B35: =Drawdown!$B$1004 -> -0.17991189 | C35: =Drawdown!$C$1004 -> -0.14928973 | D35: =B35-C35 -> -0.03062216 | J35: =MIN(DrawdownRange) | K35: Worst peak-to-trough loss — the number practitioners feel
A36: Upside capture vs NIFTY | B36: =IFERROR(AVERAGEIF(BenchRet,">0",PortRet)/AVERAGEIF(BenchRet,">0",BenchRet),"n.m.") -> 0.19929123 | C36: — | D36: — | J36: =AVERAGEIF(BenchRet,">0",PortRet)/AVERAGEIF(BenchRet,">0",BenchRet) | K36: Share of the index's average up-week captured
A37: Downside capture vs NIFTY | B37: =IFERROR(AVERAGEIF(BenchRet,"<0",PortRet)/AVERAGEIF(BenchRet,"<0",BenchRet),"n.m.") -> 0.2114364 | C37: — | D37: — | J37: =AVERAGEIF(BenchRet,"<0",PortRet)/AVERAGEIF(BenchRet,"<0",BenchRet) | K37: Share of the index's average down-week suffered (lower is better)
A39: 4 · INDIVIDUAL SECURITY STATISTICS
A40: Security | B40: Weight | C40: Annualised Return | D40: Annualised Volatility | E40: Beta vs NIFTY | F40: Correlation vs NIFTY | G40: Sharpe Ratio | H40: Cumulative Return
A41: Reliance Industries | B41: =Holdings!$E$7 -> 0.23 | C41: =Returns!B$1004 -> -0.035825572 | D41: =Returns!B$1005 -> 0.21444734 | E41: =SLOPE(RelRet,BenchRet) -> 0.2014755 | F41: =CORREL(RelRet,BenchRet) -> 0.12793443 | G41: =IFERROR(($C41-RiskFree)/$D41,"n.m.") -> -0.49114889 | H41: =Holdings!$G$7 -> -0.11077158
A42: Bharti Airtel | B42: =Holdings!$E$8 -> 0.15 | C42: =Returns!C$1004 -> 0.081444945 | D42: =Returns!C$1005 -> 0.19285184 | E42: =SLOPE(AirRet,BenchRet) -> 0.21867351 | F42: =CORREL(AirRet,BenchRet) -> 0.1544039 | G42: =IFERROR(($C42-RiskFree)/$D42,"n.m.") -> 0.061938455 | H42: =Holdings!$G$8 -> 0.13432653
A43: HDFC Bank | B43: =Holdings!$E$9 -> 0.15 | C43: =Returns!D$1004 -> -0.060606364 | D43: =Returns!D$1005 -> 0.18779841 | E43: =SLOPE(HdfRet,BenchRet) -> 0.23044953 | F43: =CORREL(HdfRet,BenchRet) -> 0.16709743 | G43: =IFERROR(($C43-RiskFree)/$D43,"n.m.") -> -0.69279801 | H43: =Holdings!$G$9 -> -0.14491258
A44: Larsen & Toubro | B44: =Holdings!$E$10 -> 0.14 | C44: =Returns!E$1004 -> 0.084524854 | D44: =Returns!E$1005 -> 0.25949054 | E44: =SLOPE(LtRet,BenchRet) -> 0.56640664 | F44: =CORREL(LtRet,BenchRet) -> 0.29723002 | G44: =IFERROR(($C44-RiskFree)/$D44,"n.m.") -> 0.057901357 | H44: =Holdings!$G$10 -> 0.10683642
A45: Cipla | B45: =Holdings!$E$11 -> 0.12 | C45: =Returns!F$1004 -> -0.069387743 | D45: =Returns!F$1005 -> 0.18743964 | E45: =SLOPE(CipRet,BenchRet) -> 0.0722946 | F45: =CORREL(CipRet,BenchRet) -> 0.052520674 | G45: =IFERROR(($C45-RiskFree)/$D45,"n.m.") -> -0.74097318 | H45: =Holdings!$G$11 -> -0.15948665
A46: Maruti Suzuki | B46: =Holdings!$E$12 -> 0.12 | C46: =Returns!G$1004 -> 0.04689393 | D46: =Returns!G$1005 -> 0.24367071 | E46: =SLOPE(MarRet,BenchRet) -> 0.31007669 | F46: =CORREL(MarRet,BenchRet) -> 0.17328128 | G46: =IFERROR(($C46-RiskFree)/$D46,"n.m.") -> -0.092773028 | H46: =Holdings!$G$12 -> 0.03604646
A47: HCL Technologies | B47: =Holdings!$E$13 -> 0.09 | C47: =Returns!H$1004 -> -0.12948856 | D47: =Returns!H$1005 -> 0.28549268 | E47: =SLOPE(HclRet,BenchRet) -> 0.46327061 | F47: =CORREL(HclRet,BenchRet) -> 0.22096609 | G47: =IFERROR(($C47-RiskFree)/$D47,"n.m.") -> -0.69700055 | H47: =Holdings!$G$13 -> -0.28998685
A48: PORTFOLIO (weighted) | B48: =SUM(B41:B47) -> 1 | C48: =B9 -> -0.0076338423 | D48: =B10 -> 0.14182434 | E48: =B27 -> 0.28058366 | F48: =B28 -> 0.26939993 | G48: =B21 -> -0.54386887 | H48: =B11 -> -0.034623975
A50: 5 · INTERPRETATION (auto-generated from the calculations above)
A51: ="BETA — The portfolio's beta of "&TEXT(B27,"0.00")&" means that for a 1% move in the NIFTY 50, the portfolio moved about "&TEXT(B27,"0.00")&"% on average. "&IF(B27>1.05,"Beta above 1.0 indicates a MORE market-sensitive (aggressive) book — outperformance in a rising market is expected and is not, on its own, evidence of skill.",IF(B27<0.95,"Beta below 1.0 indicates a DEFENSIVE book — it should lag a rising market and cushion a falling one.","Beta of approximately 1.0 indicates MARKET-LIKE exposure — the portfolio carries essentially the same systematic risk as the index, so any return difference is not explained by leverage on market direction.")) -> BETA — The portfolio's beta of 0.28 means that for a 1% move in the NIFTY 50, the portfolio moved about 0.28% on average. Beta below 1.0 indicates a DEFENSIVE book — it should lag a rising market and cushion a falling one.
A52: ="ALPHA — Jensen's alpha of "&TEXT(B33,"0.00%")&" p.a. is the return earned above the CAPM benchmark of "&TEXT(B32,"0.00%")&" implied by a beta of "&TEXT(B27,"0.00")&". Raw excess return vs the index was "&TEXT(B31,"0.00%")&". "&IF(B33>0,"Alpha is POSITIVE: the portfolio delivered more than its market exposure alone would predict.","Alpha is NEGATIVE: the portfolio delivered less than its market exposure alone would predict.")&" Note that alpha and raw excess return are close here precisely because beta is near 1.0." -> ALPHA — Jensen's alpha of -5.35% p.a. is the return earned above the CAPM benchmark of 4.59% implied by a beta of 0.28. Raw excess return vs the index was 0.70%. Alpha is NEGATIVE: the portfolio delivered less than its market exposure alone would predict. Note that alpha and raw excess return are close here precisely because beta is near 1.0.
A53: ="SHARPE — Portfolio Sharpe of "&TEXT(B21,"0.00")&" vs NIFTY 50 "&TEXT(C21,"0.00")&". "&IF(B21>C21,"The portfolio produced a BETTER return per unit of total risk than the index.","The portfolio produced a WORSE return per unit of total risk than the index.")&IF(B21<0," Both figures are negative because the annualised return sits below the "&TEXT(RiskFree,"0.00%")&" risk-free rate — over this window, government bonds outperformed equity on a risk-adjusted basis. A negative Sharpe should be read as a ranking, not a ratio: less negative is better.","") -> SHARPE — Portfolio Sharpe of -0.54 vs NIFTY 50 -0.62. The portfolio produced a BETTER return per unit of total risk than the index. Both figures are negative because the annualised return sits below the 6.95% risk-free rate — over this window, government bonds outperformed equity on a risk-adjusted basis. A negative Sharpe should be read as a ranking, not a ratio: less negative is better.
A54: ="RISK — Annualised volatility of "&TEXT(B10,"0.00%")&" vs the index at "&TEXT(C10,"0.00%")&"; maximum drawdown "&TEXT(B35,"0.00%")&" vs "&TEXT(C35,"0.00%")&". Upside capture "&TEXT(B36,"0.0%")&" and downside capture "&TEXT(B37,"0.0%")&" — "&IF(B36>B37,"the portfolio captured more of the index's up-weeks than its down-weeks, the asymmetry a manager wants.","the portfolio suffered more of the index's down-weeks than it captured of its up-weeks — an unfavourable asymmetry.") -> RISK — Annualised volatility of 14.18% vs the index at 13.62%; maximum drawdown -17.99% vs -14.93%. Upside capture 19.9% and downside capture 21.1% — the portfolio suffered more of the index's down-weeks than it captured of its up-weeks — an unfavourable asymmetry.
A55: ="MARKET DEPENDENCE — R² of "&TEXT(B29,"0.0%")&" means roughly "&TEXT(B29,"0%")&_xlfn._LONGTEXT(" of the portfolio's weekly variance is explained by NIFTY 50 movement; the remainder is stock-specific. A single-country, long-only equity book of seven large caps will always be dominated by market beta — which is exactly why alpha, not raw return, is th","e honest scorecard.") -> MARKET DEPENDENCE — R² of 7.3% means roughly 7% of the portfolio's weekly variance is explained by NIFTY 50 movement; the remainder is stock-specific. A single-country, long-only equity book of seven large caps will always be dominated by market beta — which is exactly why alpha, not raw return, is the honest scorecard.

Sheet Correlation
A1: CORRELATION — DIVERSIFICATION DIAGNOSTICS
A2: Pairwise correlation of WEEKLY RETURNS (not price levels). Low correlation is the mechanism by which a portfolio's volatility falls below the average volatility of its holdings.
A3: Matrix cell: =CORREL(Returns!<column A>, Returns!<column B>) — direct column ranges on the Returns sheet, robust across Excel versions (no INDEX/MATCH array extraction).
A5: 1 · 7 × 7 CORRELATION MATRIX (weekly returns)
B6: Reliance Industries | C6: Bharti Airtel | D6: HDFC Bank | E6: Larsen & Toubro | F6: Cipla | G6: Maruti Suzuki | H6: HCL Technologies
A7: Reliance Industries | B7: =CORREL(RelRet,RelRet) -> 1 | C7: =CORREL(RelRet,AirRet) -> 0.39814714 | D7: =CORREL(RelRet,HdfRet) -> 0.39330991 | E7: =CORREL(RelRet,LtRet) -> 0.42911332 | F7: =CORREL(RelRet,CipRet) -> 0.19182907 | G7: =CORREL(RelRet,MarRet) -> 0.41736088 | H7: =CORREL(RelRet,HclRet) -> 0.21879104
A8: Bharti Airtel | B8: =CORREL(AirRet,RelRet) -> 0.39814714 | C8: =CORREL(AirRet,AirRet) -> 1 | D8: =CORREL(AirRet,HdfRet) -> 0.39908705 | E8: =CORREL(AirRet,LtRet) -> 0.33335131 | F8: =CORREL(AirRet,CipRet) -> 0.22807051 | G8: =CORREL(AirRet,MarRet) -> 0.34271126 | H8: =CORREL(AirRet,HclRet) -> 0.24743999
A9: HDFC Bank | B9: =CORREL(HdfRet,RelRet) -> 0.39330991 | C9: =CORREL(HdfRet,AirRet) -> 0.39908705 | D9: =CORREL(HdfRet,HdfRet) -> 1 | E9: =CORREL(HdfRet,LtRet) -> 0.42568372 | F9: =CORREL(HdfRet,CipRet) -> 0.2452787 | G9: =CORREL(HdfRet,MarRet) -> 0.32132267 | H9: =CORREL(HdfRet,HclRet) -> 0.14603492
A10: Larsen & Toubro | B10: =CORREL(LtRet,RelRet) -> 0.42911332 | C10: =CORREL(LtRet,AirRet) -> 0.33335131 | D10: =CORREL(LtRet,HdfRet) -> 0.42568372 | E10: =CORREL(LtRet,LtRet) -> 1 | F10: =CORREL(LtRet,CipRet) -> 0.22740707 | G10: =CORREL(LtRet,MarRet) -> 0.37306295 | H10: =CORREL(LtRet,HclRet) -> 0.22900743
A11: Cipla | B11: =CORREL(CipRet,RelRet) -> 0.19182907 | C11: =CORREL(CipRet,AirRet) -> 0.22807051 | D11: =CORREL(CipRet,HdfRet) -> 0.2452787 | E11: =CORREL(CipRet,LtRet) -> 0.22740707 | F11: =CORREL(CipRet,CipRet) -> 1 | G11: =CORREL(CipRet,MarRet) -> 0.30138072 | H11: =CORREL(CipRet,HclRet) -> -0.044990875
A12: Maruti Suzuki | B12: =CORREL(MarRet,RelRet) -> 0.41736088 | C12: =CORREL(MarRet,AirRet) -> 0.34271126 | D12: =CORREL(MarRet,HdfRet) -> 0.32132267 | E12: =CORREL(MarRet,LtRet) -> 0.37306295 | F12: =CORREL(MarRet,CipRet) -> 0.30138072 | G12: =CORREL(MarRet,MarRet) -> 1 | H12: =CORREL(MarRet,HclRet) -> 0.20278159
A13: HCL Technologies | B13: =CORREL(HclRet,RelRet) -> 0.21879104 | C13: =CORREL(HclRet,AirRet) -> 0.24743999 | D13: =CORREL(HclRet,HdfRet) -> 0.14603492 | E13: =CORREL(HclRet,LtRet) -> 0.22900743 | F13: =CORREL(HclRet,CipRet) -> -0.044990875 | G13: =CORREL(HclRet,MarRet) -> 0.20278159 | H13: =CORREL(HclRet,HclRet) -> 1
A14: Heatmap: green = lower correlation (diversifying) · white = moderate · red = higher correlation (shared risk driver). Diagonal is 1.00 by construction.
A15: 2 · PAIRWISE CORRELATION LADDER (21 unique pairs, ranked)
A16: Rank | B16: Security A | D16: Security B | F16: Correlation | G16: Band | I16: Interpretation
A17: =RANK($F17,$F$17:$F$37,0) -> 5 | B17: Reliance Industries | D17: Bharti Airtel | F17: =CORREL(RelRet,AirRet) -> 0.39814714 | G17: =IF($F17>THR80,"> 0.80 Poor diversification",IF($F17>THR50,"0.50 – 0.80 Moderate / high",IF($F17>THR30,"0.30 – 0.50 Moderate","< 0.30 Strong diversification"))) -> > 0.80 Poor diversification | I17: =IF($F17>THR80,"Pair behaves close to one bet — review for redundancy",IF($F17>THR50,"Meaningful shared risk driver — monitor combined weight",IF($F17>THR30,"Some shared exposure; still adds diversification","Largely independent return drivers — diversifying"))) -> Pair behaves close to one bet — review for redundancy
A18: =RANK($F18,$F$17:$F$37,0) -> 6 | B18: Reliance Industries | D18: HDFC Bank | F18: =CORREL(RelRet,HdfRet) -> 0.39330991 | G18: =IF($F18>THR80,"> 0.80 Poor diversification",IF($F18>THR50,"0.50 – 0.80 Moderate / high",IF($F18>THR30,"0.30 – 0.50 Moderate","< 0.30 Strong diversification"))) -> > 0.80 Poor diversification | I18: =IF($F18>THR80,"Pair behaves close to one bet — review for redundancy",IF($F18>THR50,"Meaningful shared risk driver — monitor combined weight",IF($F18>THR30,"Some shared exposure; still adds diversification","Largely independent return drivers — diversifying"))) -> Pair behaves close to one bet — review for redundancy
A19: =RANK($F19,$F$17:$F$37,0) -> 1 | B19: Reliance Industries | D19: Larsen & Toubro | F19: =CORREL(RelRet,LtRet) -> 0.42911332 | G19: =IF($F19>THR80,"> 0.80 Poor diversification",IF($F19>THR50,"0.50 – 0.80 Moderate / high",IF($F19>THR30,"0.30 – 0.50 Moderate","< 0.30 Strong diversification"))) -> > 0.80 Poor diversification | I19: =IF($F19>THR80,"Pair behaves close to one bet — review for redundancy",IF($F19>THR50,"Meaningful shared risk driver — monitor combined weight",IF($F19>THR30,"Some shared exposure; still adds diversification","Largely independent return drivers — diversifying"))) -> Pair behaves close to one bet — review for redundancy
A20: =RANK($F20,$F$17:$F$37,0) -> 19 | B20: Reliance Industries | D20: Cipla | F20: =CORREL(RelRet,CipRet) -> 0.19182907 | G20: =IF($F20>THR80,"> 0.80 Poor diversification",IF($F20>THR50,"0.50 – 0.80 Moderate / high",IF($F20>THR30,"0.30 – 0.50 Moderate","< 0.30 Strong diversification"))) -> > 0.80 Poor diversification | I20: =IF($F20>THR80,"Pair behaves close to one bet — review for redundancy",IF($F20>THR50,"Meaningful shared risk driver — monitor combined weight",IF($F20>THR30,"Some shared exposure; still adds diversification","Largely independent return drivers — diversifying"))) -> Pair behaves close to one bet — review for redundancy
A21: =RANK($F21,$F$17:$F$37,0) -> 3 | B21: Reliance Industries | D21: Maruti Suzuki | F21: =CORREL(RelRet,MarRet) -> 0.41736088 | G21: =IF($F21>THR80,"> 0.80 Poor diversification",IF($F21>THR50,"0.50 – 0.80 Moderate / high",IF($F21>THR30,"0.30 – 0.50 Moderate","< 0.30 Strong diversification"))) -> > 0.80 Poor diversification | I21: =IF($F21>THR80,"Pair behaves close to one bet — review for redundancy",IF($F21>THR50,"Meaningful shared risk driver — monitor combined weight",IF($F21>THR30,"Some shared exposure; still adds diversification","Largely independent return drivers — diversifying"))) -> Pair behaves close to one bet — review for redundancy
A22: =RANK($F22,$F$17:$F$37,0) -> 17 | B22: Reliance Industries | D22: HCL Technologies | F22: =CORREL(RelRet,HclRet) -> 0.21879104 | G22: =IF($F22>THR80,"> 0.80 Poor diversification",IF($F22>THR50,"0.50 – 0.80 Moderate / high",IF($F22>THR30,"0.30 – 0.50 Moderate","< 0.30 Strong diversification"))) -> > 0.80 Poor diversification | I22: =IF($F22>THR80,"Pair behaves close to one bet — review for redundancy",IF($F22>THR50,"Meaningful shared risk driver — monitor combined weight",IF($F22>THR30,"Some shared exposure; still adds diversification","Largely independent return drivers — diversifying"))) -> Pair behaves close to one bet — review for redundancy
A23: =RANK($F23,$F$17:$F$37,0) -> 4 | B23: Bharti Airtel | D23: HDFC Bank | F23: =CORREL(AirRet,HdfRet) -> 0.39908705 | G23: =IF($F23>THR80,"> 0.80 Poor diversification",IF($F23>THR50,"0.50 – 0.80 Moderate / high",IF($F23>THR30,"0.30 – 0.50 Moderate","< 0.30 Strong diversification"))) -> > 0.80 Poor diversification | I23: =IF($F23>THR80,"Pair behaves close to one bet — review for redundancy",IF($F23>THR50,"Meaningful shared risk driver — monitor combined weight",IF($F23>THR30,"Some shared exposure; still adds diversification","Largely independent return drivers — diversifying"))) -> Pair behaves close to one bet — review for redundancy
A24: =RANK($F24,$F$17:$F$37,0) -> 9 | B24: Bharti Airtel | D24: Larsen & Toubro | F24: =CORREL(AirRet,LtRet) -> 0.33335131 | G24: =IF($F24>THR80,"> 0.80 Poor diversification",IF($F24>THR50,"0.50 – 0.80 Moderate / high",IF($F24>THR30,"0.30 – 0.50 Moderate","< 0.30 Strong diversification"))) -> > 0.80 Poor diversification | I24: =IF($F24>THR80,"Pair behaves close to one bet — review for redundancy",IF($F24>THR50,"Meaningful shared risk driver — monitor combined weight",IF($F24>THR30,"Some shared exposure; still adds diversification","Largely independent return drivers — diversifying"))) -> Pair behaves close to one bet — review for redundancy
A25: =RANK($F25,$F$17:$F$37,0) -> 15 | B25: Bharti Airtel | D25: Cipla | F25: =CORREL(AirRet,CipRet) -> 0.22807051 | G25: =IF($F25>THR80,"> 0.80 Poor diversification",IF($F25>THR50,"0.50 – 0.80 Moderate / high",IF($F25>THR30,"0.30 – 0.50 Moderate","< 0.30 Strong diversification"))) -> > 0.80 Poor diversification | I25: =IF($F25>THR80,"Pair behaves close to one bet — review for redundancy",IF($F25>THR50,"Meaningful shared risk driver — monitor combined weight",IF($F25>THR30,"Some shared exposure; still adds diversification","Largely independent return drivers — diversifying"))) -> Pair behaves close to one bet — review for redundancy
A26: =RANK($F26,$F$17:$F$37,0) -> 8 | B26: Bharti Airtel | D26: Maruti Suzuki | F26: =CORREL(AirRet,MarRet) -> 0.34271126 | G26: =IF($F26>THR80,"> 0.80 Poor diversification",IF($F26>THR50,"0.50 – 0.80 Moderate / high",IF($F26>THR30,"0.30 – 0.50 Moderate","< 0.30 Strong diversification"))) -> > 0.80 Poor diversification | I26: =IF($F26>THR80,"Pair behaves close to one bet — review for redundancy",IF($F26>THR50,"Meaningful shared risk driver — monitor combined weight",IF($F26>THR30,"Some shared exposure; still adds diversification","Largely independent return drivers — diversifying"))) -> Pair behaves close to one bet — review for redundancy
A27: =RANK($F27,$F$17:$F$37,0) -> 12 | B27: Bharti Airtel | D27: HCL Technologies | F27: =CORREL(AirRet,HclRet) -> 0.24743999 | G27: =IF($F27>THR80,"> 0.80 Poor diversification",IF($F27>THR50,"0.50 – 0.80 Moderate / high",IF($F27>THR30,"0.30 – 0.50 Moderate","< 0.30 Strong diversification"))) -> > 0.80 Poor diversification | I27: =IF($F27>THR80,"Pair behaves close to one bet — review for redundancy",IF($F27>THR50,"Meaningful shared risk driver — monitor combined weight",IF($F27>THR30,"Some shared exposure; still adds diversification","Largely independent return drivers — diversifying"))) -> Pair behaves close to one bet — review for redundancy
A28: =RANK($F28,$F$17:$F$37,0) -> 2 | B28: HDFC Bank | D28: Larsen & Toubro | F28: =CORREL(HdfRet,LtRet) -> 0.42568372 | G28: =IF($F28>THR80,"> 0.80 Poor diversification",IF($F28>THR50,"0.50 – 0.80 Moderate / high",IF($F28>THR30,"0.30 – 0.50 Moderate","< 0.30 Strong diversification"))) -> > 0.80 Poor diversification | I28: =IF($F28>THR80,"Pair behaves close to one bet — review for redundancy",IF($F28>THR50,"Meaningful shared risk driver — monitor combined weight",IF($F28>THR30,"Some shared exposure; still adds diversification","Largely independent return drivers — diversifying"))) -> Pair behaves close to one bet — review for redundancy
A29: =RANK($F29,$F$17:$F$37,0) -> 13 | B29: HDFC Bank | D29: Cipla | F29: =CORREL(HdfRet,CipRet) -> 0.2452787 | G29: =IF($F29>THR80,"> 0.80 Poor diversification",IF($F29>THR50,"0.50 – 0.80 Moderate / high",IF($F29>THR30,"0.30 – 0.50 Moderate","< 0.30 Strong diversification"))) -> > 0.80 Poor diversification | I29: =IF($F29>THR80,"Pair behaves close to one bet — review for redundancy",IF($F29>THR50,"Meaningful shared risk driver — monitor combined weight",IF($F29>THR30,"Some shared exposure; still adds diversification","Largely independent return drivers — diversifying"))) -> Pair behaves close to one bet — review for redundancy
A30: =RANK($F30,$F$17:$F$37,0) -> 10 | B30: HDFC Bank | D30: Maruti Suzuki | F30: =CORREL(HdfRet,MarRet) -> 0.32132267 | G30: =IF($F30>THR80,"> 0.80 Poor diversification",IF($F30>THR50,"0.50 – 0.80 Moderate / high",IF($F30>THR30,"0.30 – 0.50 Moderate","< 0.30 Strong diversification"))) -> > 0.80 Poor diversification | I30: =IF($F30>THR80,"Pair behaves close to one bet — review for redundancy",IF($F30>THR50,"Meaningful shared risk driver — monitor combined weight",IF($F30>THR30,"Some shared exposure; still adds diversification","Largely independent return drivers — diversifying"))) -> Pair behaves close to one bet — review for redundancy
A31: =RANK($F31,$F$17:$F$37,0) -> 20 | B31: HDFC Bank | D31: HCL Technologies | F31: =CORREL(HdfRet,HclRet) -> 0.14603492 | G31: =IF($F31>THR80,"> 0.80 Poor diversification",IF($F31>THR50,"0.50 – 0.80 Moderate / high",IF($F31>THR30,"0.30 – 0.50 Moderate","< 0.30 Strong diversification"))) -> > 0.80 Poor diversification | I31: =IF($F31>THR80,"Pair behaves close to one bet — review for redundancy",IF($F31>THR50,"Meaningful shared risk driver — monitor combined weight",IF($F31>THR30,"Some shared exposure; still adds diversification","Largely independent return drivers — diversifying"))) -> Pair behaves close to one bet — review for redundancy
A32: =RANK($F32,$F$17:$F$37,0) -> 16 | B32: Larsen & Toubro | D32: Cipla | F32: =CORREL(LtRet,CipRet) -> 0.22740707 | G32: =IF($F32>THR80,"> 0.80 Poor diversification",IF($F32>THR50,"0.50 – 0.80 Moderate / high",IF($F32>THR30,"0.30 – 0.50 Moderate","< 0.30 Strong diversification"))) -> > 0.80 Poor diversification | I32: =IF($F32>THR80,"Pair behaves close to one bet — review for redundancy",IF($F32>THR50,"Meaningful shared risk driver — monitor combined weight",IF($F32>THR30,"Some shared exposure; still adds diversification","Largely independent return drivers — diversifying"))) -> Pair behaves close to one bet — review for redundancy
A33: =RANK($F33,$F$17:$F$37,0) -> 7 | B33: Larsen & Toubro | D33: Maruti Suzuki | F33: =CORREL(LtRet,MarRet) -> 0.37306295 | G33: =IF($F33>THR80,"> 0.80 Poor diversification",IF($F33>THR50,"0.50 – 0.80 Moderate / high",IF($F33>THR30,"0.30 – 0.50 Moderate","< 0.30 Strong diversification"))) -> > 0.80 Poor diversification | I33: =IF($F33>THR80,"Pair behaves close to one bet — review for redundancy",IF($F33>THR50,"Meaningful shared risk driver — monitor combined weight",IF($F33>THR30,"Some shared exposure; still adds diversification","Largely independent return drivers — diversifying"))) -> Pair behaves close to one bet — review for redundancy
A34: =RANK($F34,$F$17:$F$37,0) -> 14 | B34: Larsen & Toubro | D34: HCL Technologies | F34: =CORREL(LtRet,HclRet) -> 0.22900743 | G34: =IF($F34>THR80,"> 0.80 Poor diversification",IF($F34>THR50,"0.50 – 0.80 Moderate / high",IF($F34>THR30,"0.30 – 0.50 Moderate","< 0.30 Strong diversification"))) -> > 0.80 Poor diversification | I34: =IF($F34>THR80,"Pair behaves close to one bet — review for redundancy",IF($F34>THR50,"Meaningful shared risk driver — monitor combined weight",IF($F34>THR30,"Some shared exposure; still adds diversification","Largely independent return drivers — diversifying"))) -> Pair behaves close to one bet — review for redundancy
A35: =RANK($F35,$F$17:$F$37,0) -> 11 | B35: Cipla | D35: Maruti Suzuki | F35: =CORREL(CipRet,MarRet) -> 0.30138072 | G35: =IF($F35>THR80,"> 0.80 Poor diversification",IF($F35>THR50,"0.50 – 0.80 Moderate / high",IF($F35>THR30,"0.30 – 0.50 Moderate","< 0.30 Strong diversification"))) -> > 0.80 Poor diversification | I35: =IF($F35>THR80,"Pair behaves close to one bet — review for redundancy",IF($F35>THR50,"Meaningful shared risk driver — monitor combined weight",IF($F35>THR30,"Some shared exposure; still adds diversification","Largely independent return drivers — diversifying"))) -> Pair behaves close to one bet — review for redundancy
A36: =RANK($F36,$F$17:$F$37,0) -> 21 | B36: Cipla | D36: HCL Technologies | F36: =CORREL(CipRet,HclRet) -> -0.044990875 | G36: =IF($F36>THR80,"> 0.80 Poor diversification",IF($F36>THR50,"0.50 – 0.80 Moderate / high",IF($F36>THR30,"0.30 – 0.50 Moderate","< 0.30 Strong diversification"))) -> < 0.30 Strong diversification | I36: =IF($F36>THR80,"Pair behaves close to one bet — review for redundancy",IF($F36>THR50,"Meaningful shared risk driver — monitor combined weight",IF($F36>THR30,"Some shared exposure; still adds diversification","Largely independent return drivers — diversifying"))) -> Largely independent return drivers — diversifying
A37: =RANK($F37,$F$17:$F$37,0) -> 18 | B37: Maruti Suzuki | D37: HCL Technologies | F37: =CORREL(MarRet,HclRet) -> 0.20278159 | G37: =IF($F37>THR80,"> 0.80 Poor diversification",IF($F37>THR50,"0.50 – 0.80 Moderate / high",IF($F37>THR30,"0.30 – 0.50 Moderate","< 0.30 Strong diversification"))) -> > 0.80 Poor diversification | I37: =IF($F37>THR80,"Pair behaves close to one bet — review for redundancy",IF($F37>THR50,"Meaningful shared risk driver — monitor combined weight",IF($F37>THR30,"Some shared exposure; still adds diversification","Largely independent return drivers — diversifying"))) -> Pair behaves close to one bet — review for redundancy
A39: 3 · AUTOMATED DIVERSIFICATION OBSERVATIONS
A40: Observation | B40: Value | C40: Detail
A41: Highest correlated pair | B41: =MAX($F$17:$F$37) -> 0.42911332 | C41: ="Most correlated pair: "&INDEX($B$17:$B$37,MATCH(MAX($F$17:$F$37),$F$17:$F$37,0))&" / "&INDEX($D$17:$D$37,MATCH(MAX($F$17:$F$37),$F$17:$F$37,0))&" at ρ = "&TEXT(MAX($F$17:$F$37),"0.00")&". "&IF(MAX($F$17:$F$37)>THR80,"Above the 0.80 redundancy threshold — the pair is effectively one bet.",IF(MAX($F$17:$F$37)>THR50,"Meaningful shared risk driver, but below the 0.80 redundancy threshold.","Even the most correlated pair sits below 0.50 — no redundant holding in the book.")) -> Most correlated pair: Reliance Industries / Larsen & Toubro at ρ = 0.43. Above the 0.80 redundancy threshold — the pair is effectively one bet.
A42: Lowest correlated pair | B42: =MIN($F$17:$F$37) -> -0.044990875 | C42: ="Least correlated pair: "&INDEX($B$17:$B$37,MATCH(MIN($F$17:$F$37),$F$17:$F$37,0))&" / "&INDEX($D$17:$D$37,MATCH(MIN($F$17:$F$37),$F$17:$F$37,0))&" at ρ = "&TEXT(MIN($F$17:$F$37),"0.00")&" — the strongest diversifying relationship in the portfolio." -> Least correlated pair: Cipla / HCL Technologies at ρ = -0.04 — the strongest diversifying relationship in the portfolio.
A43: Average pairwise correlation | B43: =AVERAGE($F$17:$F$37) -> 0.28696097 | C43: ="Mean of all 21 unique pairs. Values below 0.40 indicate genuinely different return drivers across the book; values approaching 0.70+ would mean the sector labels are more diversified than the underlying risk." -> Mean of all 21 unique pairs. Values below 0.40 indicate genuinely different return drivers across the book; values approaching 0.70+ would mean the sector labels are more diversified than the underlying risk.
A44: Pairs above 0.80 | B44: =COUNTIF($F$17:$F$37,">"&THR80) -> 0 | C44: =IF(COUNTIF($F$17:$F$37,">"&THR80)=0,"No pair breaches the 0.80 redundancy threshold — no holding is a duplicate of another.","Review flagged pairs: overlapping exposure is consuming weight without adding diversification.") -> No pair breaches the 0.80 redundancy threshold — no holding is a duplicate of another.
A45: Pairs 0.50 – 0.80 | B45: =COUNTIFS($F$17:$F$37,">"&THR50,$F$17:$F$37,"<="&THR80) -> 0 | C45: Moderate-to-high relationships. Acceptable within a single-country equity book, where all names share market beta.
A46: Pairs below 0.30 | B46: =COUNTIF($F$17:$F$37,"<"&THR30) -> 0 | C46: Pairs contributing the strongest diversification benefit.

Sheet Drawdown
A1: DRAWDOWN ENGINE — GROWTH OF ₹100 AND PEAK-TO-TROUGH LOSS
A2: Cumulative value → running peak → drawdown. Both series start at exactly ₹100 so they are directly comparable.
A3: Value(t) = Value(t−1) × (1 + Return(t)) · Peak(t) = MAX($C$7:C t) · Drawdown(t) = Value(t) / Peak(t) − 1 · Maximum Drawdown = MIN(drawdown column)
B5: PORTFOLIO | F5: NIFTY 50 (BENCHMARK) | T5: NOTIONAL PORTFOLIO VALUE
A6: Date | B6: Weekly Return | C6: Value (₹100 base) | D6: Running Peak | E6: Drawdown | F6: Weekly Return | G6: Value (₹100 base) | H6: Running Peak | I6: Drawdown | J6: Chart Label | L6: Period | M6: Portfolio | N6: NIFTY 50 | P6: Period | Q6: Portfolio | R6: NIFTY 50 | T6: Period | U6: Portfolio Value (₹)
A7: =Prices!$A$4 -> 45544 | B7: — | C7: =IndexBase -> 100 | D7: =$C$7 -> 100 | E7: 0 | F7: — | G7: =IndexBase -> 100 | H7: =$G$7 -> 100 | I7: 0 | J7: =TEXT($A$7,"mmm-yy") -> Sep-24 | L7: =$J7 -> Sep-24 | M7: =$C7 -> 100 | N7: =$G7 -> 100 | P7: =$J7 -> Sep-24 | Q7: =$E7 -> 0 | R7: =$I7 -> 0 | T7: =$J7 -> Sep-24 | U7: =IF($A7="","",NotionalValue*$C7/IndexBase) -> 1000000
A8: =Returns!$A$6 -> 45551 | B8: =IF($A8="","",Returns!$J$6) -> 0.021723549 | C8: =IF($A8="","",C7*(1+$B8)) -> 102.17235 | D8: =IF($A8="","",MAX($C$7:C8)) -> 102.17235 | E8: =IF($A8="","",$C8/$D8-1) -> 0 | F8: =IF($A8="","",Returns!$I$6) -> 0.017939622 | G8: =IF($A8="","",G7*(1+$F8)) -> 101.79396 | H8: =IF($A8="","",MAX($G$7:G8)) -> 101.79396 | I8: =IF($A8="","",$G8/$H8-1) -> 0 | J8: =IF($A8="","",TEXT($A8,"mmm-yy")) -> Sep-24 | L8: =$J8 -> Sep-24 | M8: =$C8 -> 102.17235 | N8: =$G8 -> 101.79396 | P8: =$J8 -> Sep-24 | Q8: =$E8 -> 0 | R8: =$I8 -> 0 | T8: =$J8 -> Sep-24 | U8: =IF($A8="","",NotionalValue*$C8/IndexBase) -> 1021723.5
A9: =Returns!$A$7 -> 45558 | B9: =IF($A9="","",Returns!$J$7) -> 0.019295337 | C9: =IF($A9="","",C8*(1+$B9)) -> 104.1438 | D9: =IF($A9="","",MAX($C$7:C9)) -> 104.1438 | E9: =IF($A9="","",$C9/$D9-1) -> 0 | F9: =IF($A9="","",Returns!$I$7) -> 0.021876231 | G9: =IF($A9="","",G8*(1+$F9)) -> 104.02083 | H9: =IF($A9="","",MAX($G$7:G9)) -> 104.02083 | I9: =IF($A9="","",$G9/$H9-1) -> 0 | J9: =IF($A9="","",TEXT($A9,"mmm-yy")) -> Sep-24 | L9: =$J9 -> Sep-24 | M9: =$C9 -> 104.1438 | N9: =$G9 -> 104.02083 | P9: =$J9 -> Sep-24 | Q9: =$E9 -> 0 | R9: =$I9 -> 0 | T9: =$J9 -> Sep-24 | U9: =IF($A9="","",NotionalValue*$C9/IndexBase) -> 1041438
A10: =Returns!$A$8 -> 45565 | B10: =IF($A10="","",Returns!$J$8) -> -0.058302104 | C10: =IF($A10="","",C9*(1+$B10)) -> 98.072002 | D10: =IF($A10="","",MAX($C$7:C10)) -> 104.1438 | E10: =IF($A10="","",$C10/$D10-1) -> -0.058302104 | F10: =IF($A10="","",Returns!$I$8) -> -0.0049424003 | G10: =IF($A10="","",G9*(1+$F10)) -> 103.50672 | H10: =IF($A10="","",MAX($G$7:G10)) -> 104.02083 | I10: =IF($A10="","",$G10/$H10-1) -> -0.0049424003 | J10: =IF($A10="","",TEXT($A10,"mmm-yy")) -> Sep-24 | L10: =$J10 -> Sep-24 | M10: =$C10 -> 98.072002 | N10: =$G10 -> 103.50672 | P10: =$J10 -> Sep-24 | Q10: =$E10 -> -0.058302104 | R10: =$I10 -> -0.0049424003 | T10: =$J10 -> Sep-24 | U10: =IF($A10="","",NotionalValue*$C10/IndexBase) -> 980720.02
A11: =Returns!$A$9 -> 45572 | B11: =IF($A11="","",Returns!$J$9) -> 0.0035836358 | C11: =IF($A11="","",C10*(1+$B11)) -> 98.423456 | D11: =IF($A11="","",MAX($C$7:C11)) -> 104.1438 | E11: =IF($A11="","",$C11/$D11-1) -> -0.054927402 | F11: =IF($A11="","",Returns!$I$9) -> -0.039328407 | G11: =IF($A11="","",G10*(1+$F11)) -> 99.435964 | H11: =IF($A11="","",MAX($G$7:G11)) -> 104.02083 | I11: =IF($A11="","",$G11/$H11-1) -> -0.044076431 | J11: =IF($A11="","",TEXT($A11,"mmm-yy")) -> Oct-24 | L11: =$J11 -> Oct-24 | M11: =$C11 -> 98.423456 | N11: =$G11 -> 99.435964 | P11: =$J11 -> Oct-24 | Q11: =$E11 -> -0.054927402 | R11: =$I11 -> -0.044076431 | T11: =$J11 -> Oct-24 | U11: =IF($A11="","",NotionalValue*$C11/IndexBase) -> 984234.56
A12: =Returns!$A$10 -> 45579 | B12: =IF($A12="","",Returns!$J$10) -> -0.002432591 | C12: =IF($A12="","",C11*(1+$B12)) -> 98.184032 | D12: =IF($A12="","",MAX($C$7:C12)) -> 104.1438 | E12: =IF($A12="","",$C12/$D12-1) -> -0.057226377 | F12: =IF($A12="","",Returns!$I$10) -> 0.013397426 | G12: =IF($A12="","",G11*(1+$F12)) -> 100.76815 | H12: =IF($A12="","",MAX($G$7:G12)) -> 104.02083 | I12: =IF($A12="","",$G12/$H12-1) -> -0.031269516 | J12: =IF($A12="","",TEXT($A12,"mmm-yy")) -> Oct-24 | L12: =$J12 -> Oct-24 | M12: =$C12 -> 98.184032 | N12: =$G12 -> 100.76815 | P12: =$J12 -> Oct-24 | Q12: =$E12 -> -0.057226377 | R12: =$I12 -> -0.031269516 | T12: =$J12 -> Oct-24 | U12: =IF($A12="","",NotionalValue*$C12/IndexBase) -> 981840.32
A13: =Returns!$A$11 -> 45586 | B13: =IF($A13="","",Returns!$J$11) -> -0.024431011 | C13: =IF($A13="","",C12*(1+$B13)) -> 95.785297 | D13: =IF($A13="","",MAX($C$7:C13)) -> 104.1438 | E13: =IF($A13="","",$C13/$D13-1) -> -0.080259289 | F13: =IF($A13="","",Returns!$I$11) -> -0.013803339 | G13: =IF($A13="","",G12*(1+$F13)) -> 99.377213 | H13: =IF($A13="","",MAX($G$7:G13)) -> 104.02083 | I13: =IF($A13="","",$G13/$H13-1) -> -0.044641232 | J13: =IF($A13="","",TEXT($A13,"mmm-yy")) -> Oct-24 | L13: =$J13 -> Oct-24 | M13: =$C13 -> 95.785297 | N13: =$G13 -> 99.377213 | P13: =$J13 -> Oct-24 | Q13: =$E13 -> -0.080259289 | R13: =$I13 -> -0.044641232 | T13: =$J13 -> Oct-24 | U13: =IF($A13="","",NotionalValue*$C13/IndexBase) -> 957852.97
A14: =Returns!$A$12 -> 45593 | B14: =IF($A14="","",Returns!$J$12) -> 0.0064912391 | C14: =IF($A14="","",C13*(1+$B14)) -> 96.407062 | D14: =IF($A14="","",MAX($C$7:C14)) -> 104.1438 | E14: =IF($A14="","",$C14/$D14-1) -> -0.074289033 | F14: =IF($A14="","",Returns!$I$12) -> -0.017834125 | G14: =IF($A14="","",G13*(1+$F14)) -> 97.604907 | H14: =IF($A14="","",MAX($G$7:G14)) -> 104.02083 | I14: =IF($A14="","",$G14/$H14-1) -> -0.061679219 | J14: =IF($A14="","",TEXT($A14,"mmm-yy")) -> Oct-24 | L14: =$J14 -> Oct-24 | M14: =$C14 -> 96.407062 | N14: =$G14 -> 97.604907 | P14: =$J14 -> Oct-24 | Q14: =$E14 -> -0.074289033 | R14: =$I14 -> -0.061679219 | T14: =$J14 -> Oct-24 | U14: =IF($A14="","",NotionalValue*$C14/IndexBase) -> 964070.62
A15: =Returns!$A$13 -> 45600 | B15: =IF($A15="","",Returns!$J$13) -> -0.0022311125 | C15: =IF($A15="","",C14*(1+$B15)) -> 96.191967 | D15: =IF($A15="","",MAX($C$7:C15)) -> 104.1438 | E15: =IF($A15="","",$C15/$D15-1) -> -0.076354398 | F15: =IF($A15="","",Returns!$I$13) -> -0.014125422 | G15: =IF($A15="","",G14*(1+$F15)) -> 96.226196 | H15: =IF($A15="","",MAX($G$7:G15)) -> 104.02083 | I15: =IF($A15="","",$G15/$H15-1) -> -0.074933396 | J15: =IF($A15="","",TEXT($A15,"mmm-yy")) -> Nov-24 | L15: =$J15 -> Nov-24 | M15: =$C15 -> 96.191967 | N15: =$G15 -> 96.226196 | P15: =$J15 -> Nov-24 | Q15: =$E15 -> -0.076354398 | R15: =$I15 -> -0.074933396 | T15: =$J15 -> Nov-24 | U15: =IF($A15="","",NotionalValue*$C15/IndexBase) -> 961919.67
A16: =Returns!$A$14 -> 45607 | B16: =IF($A16="","",Returns!$J$14) -> -0.024247543 | C16: =IF($A16="","",C15*(1+$B16)) -> 93.859549 | D16: =IF($A16="","",MAX($C$7:C16)) -> 104.1438 | E16: =IF($A16="","",$C16/$D16-1) -> -0.098750534 | F16: =IF($A16="","",Returns!$I$14) -> 0.0060824774 | G16: =IF($A16="","",G15*(1+$F16)) -> 96.81149 | H16: =IF($A16="","",MAX($G$7:G16)) -> 104.02083 | I16: =IF($A16="","",$G16/$H16-1) -> -0.0693067 | J16: =IF($A16="","",TEXT($A16,"mmm-yy")) -> Nov-24 | L16: =$J16 -> Nov-24 | M16: =$C16 -> 93.859549 | N16: =$G16 -> 96.81149 | P16: =$J16 -> Nov-24 | Q16: =$E16 -> -0.098750534 | R16: =$I16 -> -0.0693067 | T16: =$J16 -> Nov-24 | U16: =IF($A16="","",NotionalValue*$C16/IndexBase) -> 938595.49
A17: =Returns!$A$15 -> 45614 | B17: =IF($A17="","",Returns!$J$15) -> 0.010647048 | C17: =IF($A17="","",C16*(1+$B17)) -> 94.858876 | D17: =IF($A17="","",MAX($C$7:C17)) -> 104.1438 | E17: =IF($A17="","",$C17/$D17-1) -> -0.089154888 | F17: =IF($A17="","",Returns!$I$15) -> -0.028478167 | G17: =IF($A17="","",G16*(1+$F17)) -> 94.054476 | H17: =IF($A17="","",MAX($G$7:G17)) -> 104.02083 | I17: =IF($A17="","",$G17/$H17-1) -> -0.095811139 | J17: =IF($A17="","",TEXT($A17,"mmm-yy")) -> Nov-24 | L17: =$J17 -> Nov-24 | M17: =$C17 -> 94.858876 | N17: =$G17 -> 94.054476 | P17: =$J17 -> Nov-24 | Q17: =$E17 -> -0.089154888 | R17: =$I17 -> -0.095811139 | T17: =$J17 -> Nov-24 | U17: =IF($A17="","",NotionalValue*$C17/IndexBase) -> 948588.76
A18: =Returns!$A$16 -> 45621 | B18: =IF($A18="","",Returns!$J$16) -> 0.021002937 | C18: =IF($A18="","",C17*(1+$B18)) -> 96.851191 | D18: =IF($A18="","",MAX($C$7:C18)) -> 104.1438 | E18: =IF($A18="","",$C18/$D18-1) -> -0.070024465 | F18: =IF($A18="","",Returns!$I$16) -> 0.032749473 | G18: =IF($A18="","",G17*(1+$F18)) -> 97.134711 | H18: =IF($A18="","",MAX($G$7:G18)) -> 104.02083 | I18: =IF($A18="","",$G18/$H18-1) -> -0.066199431 | J18: =IF($A18="","",TEXT($A18,"mmm-yy")) -> Nov-24 | L18: =$J18 -> Nov-24 | M18: =$C18 -> 96.851191 | N18: =$G18 -> 97.134711 | P18: =$J18 -> Nov-24 | Q18: =$E18 -> -0.070024465 | R18: =$I18 -> -0.066199431 | T18: =$J18 -> Nov-24 | U18: =IF($A18="","",NotionalValue*$C18/IndexBase) -> 968511.91
A19: =Returns!$A$17 -> 45628 | B19: =IF($A19="","",Returns!$J$17) -> 0.012927436 | C19: =IF($A19="","",C18*(1+$B19)) -> 98.103228 | D19: =IF($A19="","",MAX($C$7:C19)) -> 104.1438 | E19: =IF($A19="","",$C19/$D19-1) -> -0.058002265 | F19: =IF($A19="","",Returns!$I$17) -> 0.0022355963 | G19: =IF($A19="","",G18*(1+$F19)) -> 97.351865 | H19: =IF($A19="","",MAX($G$7:G19)) -> 104.02083 | I19: =IF($A19="","",$G19/$H19-1) -> -0.064111829 | J19: =IF($A19="","",TEXT($A19,"mmm-yy")) -> Dec-24 | L19: =$J19 -> Dec-24 | M19: =$C19 -> 98.103228 | N19: =$G19 -> 97.351865 | P19: =$J19 -> Dec-24 | Q19: =$E19 -> -0.058002265 | R19: =$I19 -> -0.064111829 | T19: =$J19 -> Dec-24 | U19: =IF($A19="","",NotionalValue*$C19/IndexBase) -> 981032.28
A20: =Returns!$A$18 -> 45635 | B20: =IF($A20="","",Returns!$J$18) -> 0.0023414089 | C20: =IF($A20="","",C19*(1+$B20)) -> 98.332928 | D20: =IF($A20="","",MAX($C$7:C20)) -> 104.1438 | E20: =IF($A20="","",$C20/$D20-1) -> -0.055796663 | F20: =IF($A20="","",Returns!$I$18) -> 0.01412706 | G20: =IF($A20="","",G19*(1+$F20)) -> 98.72716 | H20: =IF($A20="","",MAX($G$7:G20)) -> 104.02083 | I20: =IF($A20="","",$G20/$H20-1) -> -0.050890481 | J20: =IF($A20="","",TEXT($A20,"mmm-yy")) -> Dec-24 | L20: =$J20 -> Dec-24 | M20: =$C20 -> 98.332928 | N20: =$G20 -> 98.72716 | P20: =$J20 -> Dec-24 | Q20: =$E20 -> -0.055796663 | R20: =$I20 -> -0.050890481 | T20: =$J20 -> Dec-24 | U20: =IF($A20="","",NotionalValue*$C20/IndexBase) -> 983329.28
A21: =Returns!$A$19 -> 45642 | B21: =IF($A21="","",Returns!$J$19) -> -0.043275593 | C21: =IF($A21="","",C20*(1+$B21)) -> 94.077512 | D21: =IF($A21="","",MAX($C$7:C21)) -> 104.1438 | E21: =IF($A21="","",$C21/$D21-1) -> -0.096657623 | F21: =IF($A21="","",Returns!$I$19) -> 0.0020004874 | G21: =IF($A21="","",G20*(1+$F21)) -> 98.924663 | H21: =IF($A21="","",MAX($G$7:G21)) -> 104.02083 | I21: =IF($A21="","",$G21/$H21-1) -> -0.0489918 | J21: =IF($A21="","",TEXT($A21,"mmm-yy")) -> Dec-24 | L21: =$J21 -> Dec-24 | M21: =$C21 -> 94.077512 | N21: =$G21 -> 98.924663 | P21: =$J21 -> Dec-24 | Q21: =$E21 -> -0.096657623 | R21: =$I21 -> -0.0489918 | T21: =$J21 -> Dec-24 | U21: =IF($A21="","",NotionalValue*$C21/IndexBase) -> 940775.12
A22: =Returns!$A$20 -> 45649 | B22: =IF($A22="","",Returns!$J$20) -> 0.0088446671 | C22: =IF($A22="","",C21*(1+$B22)) -> 94.909597 | D22: =IF($A22="","",MAX($C$7:C22)) -> 104.1438 | E22: =IF($A22="","",$C22/$D22-1) -> -0.08866786 | F22: =IF($A22="","",Returns!$I$20) -> -0.037084138 | G22: =IF($A22="","",G21*(1+$F22)) -> 95.256127 | H22: =IF($A22="","",MAX($G$7:G22)) -> 104.02083 | I22: =IF($A22="","",$G22/$H22-1) -> -0.084259119 | J22: =IF($A22="","",TEXT($A22,"mmm-yy")) -> Dec-24 | L22: =$J22 -> Dec-24 | M22: =$C22 -> 94.909597 | N22: =$G22 -> 95.256127 | P22: =$J22 -> Dec-24 | Q22: =$E22 -> -0.08866786 | R22: =$I22 -> -0.084259119 | T22: =$J22 -> Dec-24 | U22: =IF($A22="","",NotionalValue*$C22/IndexBase) -> 949095.97
A23: =Returns!$A$21 -> 45656 | B23: =IF($A23="","",Returns!$J$21) -> 0.017357679 | C23: =IF($A23="","",C22*(1+$B23)) -> 96.557007 | D23: =IF($A23="","",MAX($C$7:C23)) -> 104.1438 | E23: =IF($A23="","",$C23/$D23-1) -> -0.072849249 | F23: =IF($A23="","",Returns!$I$21) -> -0.0045698133 | G23: =IF($A23="","",G22*(1+$F23)) -> 94.820824 | H23: =IF($A23="","",MAX($G$7:G23)) -> 104.02083 | I23: =IF($A23="","",$G23/$H23-1) -> -0.088443884 | J23: =IF($A23="","",TEXT($A23,"mmm-yy")) -> Dec-24 | L23: =$J23 -> Dec-24 | M23: =$C23 -> 96.557007 | N23: =$G23 -> 94.820824 | P23: =$J23 -> Dec-24 | Q23: =$E23 -> -0.072849249 | R23: =$I23 -> -0.088443884 | T23: =$J23 -> Dec-24 | U23: =IF($A23="","",NotionalValue*$C23/IndexBase) -> 965570.07
A24: =Returns!$A$22 -> 45663 | B24: =IF($A24="","",Returns!$J$22) -> -0.016941419 | C24: =IF($A24="","",C23*(1+$B24)) -> 94.921194 | D24: =IF($A24="","",MAX($C$7:C24)) -> 104.1438 | E24: =IF($A24="","",$C24/$D24-1) -> -0.088556499 | F24: =IF($A24="","",Returns!$I$22) -> -0.0012201197 | G24: =IF($A24="","",G23*(1+$F24)) -> 94.705131 | H24: =IF($A24="","",MAX($G$7:G24)) -> 104.02083 | I24: =IF($A24="","",$G24/$H24-1) -> -0.089556091 | J24: =IF($A24="","",TEXT($A24,"mmm-yy")) -> Jan-25 | L24: =$J24 -> Jan-25 | M24: =$C24 -> 94.921194 | N24: =$G24 -> 94.705131 | P24: =$J24 -> Jan-25 | Q24: =$E24 -> -0.088556499 | R24: =$I24 -> -0.089556091 | T24: =$J24 -> Jan-25 | U24: =IF($A24="","",NotionalValue*$C24/IndexBase) -> 949211.94
A25: =Returns!$A$23 -> 45670 | B25: =IF($A25="","",Returns!$J$23) -> 0.0057652559 | C25: =IF($A25="","",C24*(1+$B25)) -> 95.468439 | D25: =IF($A25="","",MAX($C$7:C25)) -> 104.1438 | E25: =IF($A25="","",$C25/$D25-1) -> -0.083301794 | F25: =IF($A25="","",Returns!$I$23) -> -0.022446664 | G25: =IF($A25="","",G24*(1+$F25)) -> 92.579317 | H25: =IF($A25="","",MAX($G$7:G25)) -> 104.02083 | I25: =IF($A25="","",$G25/$H25-1) -> -0.10999252 | J25: =IF($A25="","",TEXT($A25,"mmm-yy")) -> Jan-25 | L25: =$J25 -> Jan-25 | M25: =$C25 -> 95.468439 | N25: =$G25 -> 92.579317 | P25: =$J25 -> Jan-25 | Q25: =$E25 -> -0.083301794 | R25: =$I25 -> -0.10999252 | T25: =$J25 -> Jan-25 | U25: =IF($A25="","",NotionalValue*$C25/IndexBase) -> 954684.39
A26: =Returns!$A$24 -> 45677 | B26: =IF($A26="","",Returns!$J$24) -> -0.015478965 | C26: =IF($A26="","",C25*(1+$B26)) -> 93.990687 | D26: =IF($A26="","",MAX($C$7:C26)) -> 104.1438 | E26: =IF($A26="","",$C26/$D26-1) -> -0.097491333 | F26: =IF($A26="","",Returns!$I$24) -> 0.011210316 | G26: =IF($A26="","",G25*(1+$F26)) -> 93.617161 | H26: =IF($A26="","",MAX($G$7:G26)) -> 104.02083 | I26: =IF($A26="","",$G26/$H26-1) -> -0.10001526 | J26: =IF($A26="","",TEXT($A26,"mmm-yy")) -> Jan-25 | L26: =$J26 -> Jan-25 | M26: =$C26 -> 93.990687 | N26: =$G26 -> 93.617161 | P26: =$J26 -> Jan-25 | Q26: =$E26 -> -0.097491333 | R26: =$I26 -> -0.10001526 | T26: =$J26 -> Jan-25 | U26: =IF($A26="","",NotionalValue*$C26/IndexBase) -> 939906.87
A27: =Returns!$A$25 -> 45684 | B27: =IF($A27="","",Returns!$J$25) -> 0.011658455 | C27: =IF($A27="","",C26*(1+$B27)) -> 95.086473 | D27: =IF($A27="","",MAX($C$7:C27)) -> 104.1438 | E27: =IF($A27="","",$C27/$D27-1) -> -0.086969476 | F27: =IF($A27="","",Returns!$I$25) -> -0.02208632 | G27: =IF($A27="","",G26*(1+$F27)) -> 91.549502 | H27: =IF($A27="","",MAX($G$7:G27)) -> 104.02083 | I27: =IF($A27="","",$G27/$H27-1) -> -0.11989261 | J27: =IF($A27="","",TEXT($A27,"mmm-yy")) -> Jan-25 | L27: =$J27 -> Jan-25 | M27: =$C27 -> 95.086473 | N27: =$G27 -> 91.549502 | P27: =$J27 -> Jan-25 | Q27: =$E27 -> -0.086969476 | R27: =$I27 -> -0.11989261 | T27: =$J27 -> Jan-25 | U27: =IF($A27="","",NotionalValue*$C27/IndexBase) -> 950864.73
A28: =Returns!$A$26 -> 45691 | B28: =IF($A28="","",Returns!$J$26) -> 0.010189601 | C28: =IF($A28="","",C27*(1+$B28)) -> 96.055366 | D28: =IF($A28="","",MAX($C$7:C28)) -> 104.1438 | E28: =IF($A28="","",$C28/$D28-1) -> -0.077666059 | F28: =IF($A28="","",Returns!$I$26) -> 0.023299176 | G28: =IF($A28="","",G27*(1+$F28)) -> 93.68253 | H28: =IF($A28="","",MAX($G$7:G28)) -> 104.02083 | I28: =IF($A28="","",$G28/$H28-1) -> -0.099386829 | J28: =IF($A28="","",TEXT($A28,"mmm-yy")) -> Feb-25 | L28: =$J28 -> Feb-25 | M28: =$C28 -> 96.055366 | N28: =$G28 -> 93.68253 | P28: =$J28 -> Feb-25 | Q28: =$E28 -> -0.077666059 | R28: =$I28 -> -0.099386829 | T28: =$J28 -> Feb-25 | U28: =IF($A28="","",NotionalValue*$C28/IndexBase) -> 960553.66
A29: =Returns!$A$27 -> 45698 | B29: =IF($A29="","",Returns!$J$27) -> -0.018008464 | C29: =IF($A29="","",C28*(1+$B29)) -> 94.325556 | D29: =IF($A29="","",MAX($C$7:C29)) -> 104.1438 | E29: =IF($A29="","",$C29/$D29-1) -> -0.094275877 | F29: =IF($A29="","",Returns!$I$27) -> 0.00087961917 | G29: =IF($A29="","",G28*(1+$F29)) -> 93.764935 | H29: =IF($A29="","",MAX($G$7:G29)) -> 104.02083 | I29: =IF($A29="","",$G29/$H29-1) -> -0.098594632 | J29: =IF($A29="","",TEXT($A29,"mmm-yy")) -> Feb-25 | L29: =$J29 -> Feb-25 | M29: =$C29 -> 94.325556 | N29: =$G29 -> 93.764935 | P29: =$J29 -> Feb-25 | Q29: =$E29 -> -0.094275877 | R29: =$I29 -> -0.098594632 | T29: =$J29 -> Feb-25 | U29: =IF($A29="","",NotionalValue*$C29/IndexBase) -> 943255.56
A30: =Returns!$A$28 -> 45705 | B30: =IF($A30="","",Returns!$J$28) -> -0.0041871478 | C30: =IF($A30="","",C29*(1+$B30)) -> 93.930601 | D30: =IF($A30="","",MAX($C$7:C30)) -> 104.1438 | E30: =IF($A30="","",$C30/$D30-1) -> -0.098068278 | F30: =IF($A30="","",Returns!$I$28) -> -0.01805264 | G30: =IF($A30="","",G29*(1+$F30)) -> 92.07223 | H30: =IF($A30="","",MAX($G$7:G30)) -> 104.02083 | I30: =IF($A30="","",$G30/$H30-1) -> -0.11486738 | J30: =IF($A30="","",TEXT($A30,"mmm-yy")) -> Feb-25 | L30: =$J30 -> Feb-25 | M30: =$C30 -> 93.930601 | N30: =$G30 -> 92.07223 | P30: =$J30 -> Feb-25 | Q30: =$E30 -> -0.098068278 | R30: =$I30 -> -0.11486738 | T30: =$J30 -> Feb-25 | U30: =IF($A30="","",NotionalValue*$C30/IndexBase) -> 939306.01
A31: =Returns!$A$29 -> 45712 | B31: =IF($A31="","",Returns!$J$29) -> -0.030298649 | C31: =IF($A31="","",C30*(1+$B31)) -> 91.084631 | D31: =IF($A31="","",MAX($C$7:C31)) -> 104.1438 | E31: =IF($A31="","",$C31/$D31-1) -> -0.12539559 | F31: =IF($A31="","",Returns!$I$29) -> -0.017689862 | G31: =IF($A31="","",G30*(1+$F31)) -> 90.443485 | H31: =IF($A31="","",MAX($G$7:G31)) -> 104.02083 | I31: =IF($A31="","",$G31/$H31-1) -> -0.13052525 | J31: =IF($A31="","",TEXT($A31,"mmm-yy")) -> Feb-25 | L31: =$J31 -> Feb-25 | M31: =$C31 -> 91.084631 | N31: =$G31 -> 90.443485 | P31: =$J31 -> Feb-25 | Q31: =$E31 -> -0.12539559 | R31: =$I31 -> -0.13052525 | T31: =$J31 -> Feb-25 | U31: =IF($A31="","",NotionalValue*$C31/IndexBase) -> 910846.31
A32: =Returns!$A$30 -> 45719 | B32: =IF($A32="","",Returns!$J$30) -> 0.015683005 | C32: =IF($A32="","",C31*(1+$B32)) -> 92.513112 | D32: =IF($A32="","",MAX($C$7:C32)) -> 104.1438 | E32: =IF($A32="","",$C32/$D32-1) -> -0.11167917 | F32: =IF($A32="","",Returns!$I$30) -> -0.019245426 | G32: =IF($A32="","",G31*(1+$F32)) -> 88.702862 | H32: =IF($A32="","",MAX($G$7:G32)) -> 104.02083 | I32: =IF($A32="","",$G32/$H32-1) -> -0.14725867 | J32: =IF($A32="","",TEXT($A32,"mmm-yy")) -> Mar-25 | L32: =$J32 -> Mar-25 | M32: =$C32 -> 92.513112 | N32: =$G32 -> 88.702862 | P32: =$J32 -> Mar-25 | Q32: =$E32 -> -0.11167917 | R32: =$I32 -> -0.14725867 | T32: =$J32 -> Mar-25 | U32: =IF($A32="","",NotionalValue*$C32/IndexBase) -> 925131.12
A33: =Returns!$A$31 -> 45726 | B33: =IF($A33="","",Returns!$J$31) -> -0.0037232606 | C33: =IF($A33="","",C32*(1+$B33)) -> 92.168661 | D33: =IF($A33="","",MAX($C$7:C33)) -> 104.1438 | E33: =IF($A33="","",$C33/$D33-1) -> -0.11498662 | F33: =IF($A33="","",Returns!$I$31) -> 0.015416401 | G33: =IF($A33="","",G32*(1+$F33)) -> 90.070341 | H33: =IF($A33="","",MAX($G$7:G33)) -> 104.02083 | I33: =IF($A33="","",$G33/$H33-1) -> -0.13411246 | J33: =IF($A33="","",TEXT($A33,"mmm-yy")) -> Mar-25 | L33: =$J33 -> Mar-25 | M33: =$C33 -> 92.168661 | N33: =$G33 -> 90.070341 | P33: =$J33 -> Mar-25 | Q33: =$E33 -> -0.11498662 | R33: =$I33 -> -0.13411246 | T33: =$J33 -> Mar-25 | U33: =IF($A33="","",NotionalValue*$C33/IndexBase) -> 921686.61
A34: =Returns!$A$32 -> 45733 | B34: =IF($A34="","",Returns!$J$32) -> 0.038704139 | C34: =IF($A34="","",C33*(1+$B34)) -> 95.73597 | D34: =IF($A34="","",MAX($C$7:C34)) -> 104.1438 | E34: =IF($A34="","",$C34/$D34-1) -> -0.080732935 | F34: =IF($A34="","",Returns!$I$32) -> 0.0021571046 | G34: =IF($A34="","",G33*(1+$F34)) -> 90.264632 | H34: =IF($A34="","",MAX($G$7:G34)) -> 104.02083 | I34: =IF($A34="","",$G34/$H34-1) -> -0.13224465 | J34: =IF($A34="","",TEXT($A34,"mmm-yy")) -> Mar-25 | L34: =$J34 -> Mar-25 | M34: =$C34 -> 95.73597 | N34: =$G34 -> 90.264632 | P34: =$J34 -> Mar-25 | Q34: =$E34 -> -0.080732935 | R34: =$I34 -> -0.13224465 | T34: =$J34 -> Mar-25 | U34: =IF($A34="","",NotionalValue*$C34/IndexBase) -> 957359.7
A35: =Returns!$A$33 -> 45740 | B35: =IF($A35="","",Returns!$J$33) -> 0.0013638739 | C35: =IF($A35="","",C34*(1+$B35)) -> 95.866542 | D35: =IF($A35="","",MAX($C$7:C35)) -> 104.1438 | E35: =IF($A35="","",$C35/$D35-1) -> -0.07947917 | F35: =IF($A35="","",Returns!$I$33) -> 0.051073454 | G35: =IF($A35="","",G34*(1+$F35)) -> 94.874758 | H35: =IF($A35="","",MAX($G$7:G35)) -> 104.02083 | I35: =IF($A35="","",$G35/$H35-1) -> -0.087925391 | J35: =IF($A35="","",TEXT($A35,"mmm-yy")) -> Mar-25 | L35: =$J35 -> Mar-25 | M35: =$C35 -> 95.866542 | N35: =$G35 -> 94.874758 | P35: =$J35 -> Mar-25 | Q35: =$E35 -> -0.07947917 | R35: =$I35 -> -0.087925391 | T35: =$J35 -> Mar-25 | U35: =IF($A35="","",NotionalValue*$C35/IndexBase) -> 958665.42
A36: =Returns!$A$34 -> 45747 | B36: =IF($A36="","",Returns!$J$34) -> 0 | C36: =IF($A36="","",C35*(1+$B36)) -> 95.866542 | D36: =IF($A36="","",MAX($C$7:C36)) -> 104.1438 | E36: =IF($A36="","",$C36/$D36-1) -> -0.07947917 | F36: =IF($A36="","",Returns!$I$34) -> -0.020823532 | G36: =IF($A36="","",G35*(1+$F36)) -> 92.899131 | H36: =IF($A36="","",MAX($G$7:G36)) -> 104.02083 | I36: =IF($A36="","",$G36/$H36-1) -> -0.10691801 | J36: =IF($A36="","",TEXT($A36,"mmm-yy")) -> Mar-25 | L36: =$J36 -> Mar-25 | M36: =$C36 -> 95.866542 | N36: =$G36 -> 92.899131 | P36: =$J36 -> Mar-25 | Q36: =$E36 -> -0.07947917 | R36: =$I36 -> -0.10691801 | T36: =$J36 -> Mar-25 | U36: =IF($A36="","",NotionalValue*$C36/IndexBase) -> 958665.42
A37: =Returns!$A$35 -> 45754 | B37: =IF($A37="","",Returns!$J$35) -> -0.033845175 | C37: =IF($A37="","",C36*(1+$B37)) -> 92.621922 | D37: =IF($A37="","",MAX($C$7:C37)) -> 104.1438 | E37: =IF($A37="","",$C37/$D37-1) -> -0.11063436 | F37: =IF($A37="","",Returns!$I$35) -> -0.043344239 | G37: =IF($A37="","",G36*(1+$F37)) -> 88.872489 | H37: =IF($A37="","",MAX($G$7:G37)) -> 104.02083 | I37: =IF($A37="","",$G37/$H37-1) -> -0.14562796 | J37: =IF($A37="","",TEXT($A37,"mmm-yy")) -> Apr-25 | L37: =$J37 -> Apr-25 | M37: =$C37 -> 92.621922 | N37: =$G37 -> 88.872489 | P37: =$J37 -> Apr-25 | Q37: =$E37 -> -0.11063436 | R37: =$I37 -> -0.14562796 | T37: =$J37 -> Apr-25 | U37: =IF($A37="","",NotionalValue*$C37/IndexBase) -> 926219.22
A38: =Returns!$A$36 -> 45761 | B38: =IF($A38="","",Returns!$J$36) -> 0 | C38: =IF($A38="","",C37*(1+$B38)) -> 92.621922 | D38: =IF($A38="","",MAX($C$7:C38)) -> 104.1438 | E38: =IF($A38="","",$C38/$D38-1) -> -0.11063436 | F38: =IF($A38="","",Returns!$I$36) -> 0.05265645 | G38: =IF($A38="","",G37*(1+$F38)) -> 93.552198 | H38: =IF($A38="","",MAX($G$7:G38)) -> 104.02083 | I38: =IF($A38="","",$G38/$H38-1) -> -0.10063977 | J38: =IF($A38="","",TEXT($A38,"mmm-yy")) -> Apr-25 | L38: =$J38 -> Apr-25 | M38: =$C38 -> 92.621922 | N38: =$G38 -> 93.552198 | P38: =$J38 -> Apr-25 | Q38: =$E38 -> -0.11063436 | R38: =$I38 -> -0.10063977 | T38: =$J38 -> Apr-25 | U38: =IF($A38="","",NotionalValue*$C38/IndexBase) -> 926219.22
A39: =Returns!$A$37 -> 45768 | B39: =IF($A39="","",Returns!$J$37) -> 0.054554697 | C39: =IF($A39="","",C38*(1+$B39)) -> 97.674883 | D39: =IF($A39="","",MAX($C$7:C39)) -> 104.1438 | E39: =IF($A39="","",$C39/$D39-1) -> -0.062115286 | F39: =IF($A39="","",Returns!$I$37) -> 0.034164145 | G39: =IF($A39="","",G38*(1+$F39)) -> 96.748329 | H39: =IF($A39="","",MAX($G$7:G39)) -> 104.02083 | I39: =IF($A39="","",$G39/$H39-1) -> -0.069913892 | J39: =IF($A39="","",TEXT($A39,"mmm-yy")) -> Apr-25 | L39: =$J39 -> Apr-25 | M39: =$C39 -> 97.674883 | N39: =$G39 -> 96.748329 | P39: =$J39 -> Apr-25 | Q39: =$E39 -> -0.062115286 | R39: =$I39 -> -0.069913892 | T39: =$J39 -> Apr-25 | U39: =IF($A39="","",NotionalValue*$C39/IndexBase) -> 976748.83
A40: =Returns!$A$38 -> 45775 | B40: =IF($A40="","",Returns!$J$38) -> 0.035136356 | C40: =IF($A40="","",C39*(1+$B40)) -> 101.10682 | D40: =IF($A40="","",MAX($C$7:C40)) -> 104.1438 | E40: =IF($A40="","",$C40/$D40-1) -> -0.029161434 | F40: =IF($A40="","",Returns!$I$38) -> 0.0084122108 | G40: =IF($A40="","",G39*(1+$F40)) -> 97.562197 | H40: =IF($A40="","",MAX($G$7:G40)) -> 104.02083 | I40: =IF($A40="","",$G40/$H40-1) -> -0.062089812 | J40: =IF($A40="","",TEXT($A40,"mmm-yy")) -> Apr-25 | L40: =$J40 -> Apr-25 | M40: =$C40 -> 101.10682 | N40: =$G40 -> 97.562197 | P40: =$J40 -> Apr-25 | Q40: =$E40 -> -0.029161434 | R40: =$I40 -> -0.062089812 | T40: =$J40 -> Apr-25 | U40: =IF($A40="","",NotionalValue*$C40/IndexBase) -> 1011068.2
A41: =Returns!$A$39 -> 45782 | B41: =IF($A41="","",Returns!$J$39) -> -0.011046687 | C41: =IF($A41="","",C40*(1+$B41)) -> 99.989927 | D41: =IF($A41="","",MAX($C$7:C41)) -> 104.1438 | E41: =IF($A41="","",$C41/$D41-1) -> -0.039885984 | F41: =IF($A41="","",Returns!$I$39) -> 0.0054524689 | G41: =IF($A41="","",G40*(1+$F41)) -> 98.094152 | H41: =IF($A41="","",MAX($G$7:G41)) -> 104.02083 | I41: =IF($A41="","",$G41/$H41-1) -> -0.056975886 | J41: =IF($A41="","",TEXT($A41,"mmm-yy")) -> May-25 | L41: =$J41 -> May-25 | M41: =$C41 -> 99.989927 | N41: =$G41 -> 98.094152 | P41: =$J41 -> May-25 | Q41: =$E41 -> -0.039885984 | R41: =$I41 -> -0.056975886 | T41: =$J41 -> May-25 | U41: =IF($A41="","",NotionalValue*$C41/IndexBase) -> 999899.27
A42: =Returns!$A$40 -> 45789 | B42: =IF($A42="","",Returns!$J$40) -> 0.034645358 | C42: =IF($A42="","",C41*(1+$B42)) -> 103.45411 | D42: =IF($A42="","",MAX($C$7:C42)) -> 104.1438 | E42: =IF($A42="","",$C42/$D42-1) -> -0.0066224902 | F42: =IF($A42="","",Returns!$I$40) -> 0.01895041 | G42: =IF($A42="","",G41*(1+$F42)) -> 99.953076 | H42: =IF($A42="","",MAX($G$7:G42)) -> 104.02083 | I42: =IF($A42="","",$G42/$H42-1) -> -0.039105192 | J42: =IF($A42="","",TEXT($A42,"mmm-yy")) -> May-25 | L42: =$J42 -> May-25 | M42: =$C42 -> 103.45411 | N42: =$G42 -> 99.953076 | P42: =$J42 -> May-25 | Q42: =$E42 -> -0.0066224902 | R42: =$I42 -> -0.039105192 | T42: =$J42 -> May-25 | U42: =IF($A42="","",NotionalValue*$C42/IndexBase) -> 1034541.1
A43: =Returns!$A$41 -> 45796 | B43: =IF($A43="","",Returns!$J$41) -> -0.010378103 | C43: =IF($A43="","",C42*(1+$B43)) -> 102.38046 | D43: =IF($A43="","",MAX($C$7:C43)) -> 104.1438 | E43: =IF($A43="","",$C43/$D43-1) -> -0.016931864 | F43: =IF($A43="","",Returns!$I$41) -> 0.00083250754 | G43: =IF($A43="","",G42*(1+$F43)) -> 100.03629 | H43: =IF($A43="","",MAX($G$7:G43)) -> 104.02083 | I43: =IF($A43="","",$G43/$H43-1) -> -0.03830524 | J43: =IF($A43="","",TEXT($A43,"mmm-yy")) -> May-25 | L43: =$J43 -> May-25 | M43: =$C43 -> 102.38046 | N43: =$G43 -> 100.03629 | P43: =$J43 -> May-25 | Q43: =$E43 -> -0.016931864 | R43: =$I43 -> -0.03830524 | T43: =$J43 -> May-25 | U43: =IF($A43="","",NotionalValue*$C43/IndexBase) -> 1023804.6
A44: =Returns!$A$42 -> 45803 | B44: =IF($A44="","",Returns!$J$42) -> 0.0014359557 | C44: =IF($A44="","",C43*(1+$B44)) -> 102.52747 | D44: =IF($A44="","",MAX($C$7:C44)) -> 104.1438 | E44: =IF($A44="","",$C44/$D44-1) -> -0.015520222 | F44: =IF($A44="","",Returns!$I$42) -> 0.0022329192 | G44: =IF($A44="","",G43*(1+$F44)) -> 100.25966 | H44: =IF($A44="","",MAX($G$7:G44)) -> 104.02083 | I44: =IF($A44="","",$G44/$H44-1) -> -0.036157853 | J44: =IF($A44="","",TEXT($A44,"mmm-yy")) -> May-25 | L44: =$J44 -> May-25 | M44: =$C44 -> 102.52747 | N44: =$G44 -> 100.25966 | P44: =$J44 -> May-25 | Q44: =$E44 -> -0.015520222 | R44: =$I44 -> -0.036157853 | T44: =$J44 -> May-25 | U44: =IF($A44="","",NotionalValue*$C44/IndexBase) -> 1025274.7
A45: =Returns!$A$43 -> 45810 | B45: =IF($A45="","",Returns!$J$43) -> 0.011285776 | C45: =IF($A45="","",C44*(1+$B45)) -> 103.68457 | D45: =IF($A45="","",MAX($C$7:C45)) -> 104.1438 | E45: =IF($A45="","",$C45/$D45-1) -> -0.0044096033 | F45: =IF($A45="","",Returns!$I$43) -> -0.011381508 | G45: =IF($A45="","",G44*(1+$F45)) -> 99.118554 | H45: =IF($A45="","",MAX($G$7:G45)) -> 104.02083 | I45: =IF($A45="","",$G45/$H45-1) -> -0.04712783 | J45: =IF($A45="","",TEXT($A45,"mmm-yy")) -> Jun-25 | L45: =$J45 -> Jun-25 | M45: =$C45 -> 103.68457 | N45: =$G45 -> 99.118554 | P45: =$J45 -> Jun-25 | Q45: =$E45 -> -0.0044096033 | R45: =$I45 -> -0.04712783 | T45: =$J45 -> Jun-25 | U45: =IF($A45="","",NotionalValue*$C45/IndexBase) -> 1036845.7
A46: =Returns!$A$44 -> 45817 | B46: =IF($A46="","",Returns!$J$44) -> -0.0094205428 | C46: =IF($A46="","",C45*(1+$B46)) -> 102.70781 | D46: =IF($A46="","",MAX($C$7:C46)) -> 104.1438 | E46: =IF($A46="","",$C46/$D46-1) -> -0.013788605 | F46: =IF($A46="","",Returns!$I$44) -> 0.015641294 | G46: =IF($A46="","",G45*(1+$F46)) -> 100.6689 | H46: =IF($A46="","",MAX($G$7:G46)) -> 104.02083 | I46: =IF($A46="","",$G46/$H46-1) -> -0.032223676 | J46: =IF($A46="","",TEXT($A46,"mmm-yy")) -> Jun-25 | L46: =$J46 -> Jun-25 | M46: =$C46 -> 102.70781 | N46: =$G46 -> 100.6689 | P46: =$J46 -> Jun-25 | Q46: =$E46 -> -0.013788605 | R46: =$I46 -> -0.032223676 | T46: =$J46 -> Jun-25 | U46: =IF($A46="","",NotionalValue*$C46/IndexBase) -> 1027078.1
A47: =Returns!$A$45 -> 45824 | B47: =IF($A47="","",Returns!$J$45) -> 0.026246935 | C47: =IF($A47="","",C46*(1+$B47)) -> 105.40357 | D47: =IF($A47="","",MAX($C$7:C47)) -> 105.40357 | E47: =IF($A47="","",$C47/$D47-1) -> 0 | F47: =IF($A47="","",Returns!$I$45) -> -0.0062422011 | G47: =IF($A47="","",G46*(1+$F47)) -> 100.0405 | H47: =IF($A47="","",MAX($G$7:G47)) -> 104.02083 | I47: =IF($A47="","",$G47/$H47-1) -> -0.03826473 | J47: =IF($A47="","",TEXT($A47,"mmm-yy")) -> Jun-25 | L47: =$J47 -> Jun-25 | M47: =$C47 -> 105.40357 | N47: =$G47 -> 100.0405 | P47: =$J47 -> Jun-25 | Q47: =$E47 -> 0 | R47: =$I47 -> -0.03826473 | T47: =$J47 -> Jun-25 | U47: =IF($A47="","",NotionalValue*$C47/IndexBase) -> 1054035.7
A48: =Returns!$A$46 -> 45831 | B48: =IF($A48="","",Returns!$J$46) -> 0.017169229 | C48: =IF($A48="","",C47*(1+$B48)) -> 107.21327 | D48: =IF($A48="","",MAX($C$7:C48)) -> 107.21327 | E48: =IF($A48="","",$C48/$D48-1) -> 0 | F48: =IF($A48="","",Returns!$I$46) -> 0.0010181946 | G48: =IF($A48="","",G47*(1+$F48)) -> 100.14236 | H48: =IF($A48="","",MAX($G$7:G48)) -> 104.02083 | I48: =IF($A48="","",$G48/$H48-1) -> -0.037285497 | J48: =IF($A48="","",TEXT($A48,"mmm-yy")) -> Jun-25 | L48: =$J48 -> Jun-25 | M48: =$C48 -> 107.21327 | N48: =$G48 -> 100.14236 | P48: =$J48 -> Jun-25 | Q48: =$E48 -> 0 | R48: =$I48 -> -0.037285497 | T48: =$J48 -> Jun-25 | U48: =IF($A48="","",NotionalValue*$C48/IndexBase) -> 1072132.7
A49: =Returns!$A$47 -> 45838 | B49: =IF($A49="","",Returns!$J$47) -> -0.0030070597 | C49: =IF($A49="","",C48*(1+$B49)) -> 106.89087 | D49: =IF($A49="","",MAX($C$7:C49)) -> 107.21327 | E49: =IF($A49="","",$C49/$D49-1) -> -0.0030070597 | F49: =IF($A49="","",Returns!$I$47) -> 0.021830553 | G49: =IF($A49="","",G48*(1+$F49)) -> 102.32853 | H49: =IF($A49="","",MAX($G$7:G49)) -> 104.02083 | I49: =IF($A49="","",$G49/$H49-1) -> -0.016268907 | J49: =IF($A49="","",TEXT($A49,"mmm-yy")) -> Jun-25 | L49: =$J49 -> Jun-25 | M49: =$C49 -> 106.89087 | N49: =$G49 -> 102.32853 | P49: =$J49 -> Jun-25 | Q49: =$E49 -> -0.0030070597 | R49: =$I49 -> -0.016268907 | T49: =$J49 -> Jun-25 | U49: =IF($A49="","",NotionalValue*$C49/IndexBase) -> 1068908.7
A50: =Returns!$A$48 -> 45845 | B50: =IF($A50="","",Returns!$J$48) -> -0.021941371 | C50: =IF($A50="","",C49*(1+$B50)) -> 104.54554 | D50: =IF($A50="","",MAX($C$7:C50)) -> 107.21327 | E50: =IF($A50="","",$C50/$D50-1) -> -0.024882451 | F50: =IF($A50="","",Returns!$I$48) -> -0.0021848136 | G50: =IF($A50="","",G49*(1+$F50)) -> 102.10496 | H50: =IF($A50="","",MAX($G$7:G50)) -> 104.02083 | I50: =IF($A50="","",$G50/$H50-1) -> -0.018418176 | J50: =IF($A50="","",TEXT($A50,"mmm-yy")) -> Jul-25 | L50: =$J50 -> Jul-25 | M50: =$C50 -> 104.54554 | N50: =$G50 -> 102.10496 | P50: =$J50 -> Jul-25 | Q50: =$E50 -> -0.024882451 | R50: =$I50 -> -0.018418176 | T50: =$J50 -> Jul-25 | U50: =IF($A50="","",NotionalValue*$C50/IndexBase) -> 1045455.4
A51: =Returns!$A$49 -> 45852 | B51: =IF($A51="","",Returns!$J$49) -> -0.016184698 | C51: =IF($A51="","",C50*(1+$B51)) -> 102.8535 | D51: =IF($A51="","",MAX($C$7:C51)) -> 107.21327 | E51: =IF($A51="","",$C51/$D51-1) -> -0.040664434 | F51: =IF($A51="","",Returns!$I$49) -> -0.014885335 | G51: =IF($A51="","",G50*(1+$F51)) -> 100.58509 | H51: =IF($A51="","",MAX($G$7:G51)) -> 104.02083 | I51: =IF($A51="","",$G51/$H51-1) -> -0.033029351 | J51: =IF($A51="","",TEXT($A51,"mmm-yy")) -> Jul-25 | L51: =$J51 -> Jul-25 | M51: =$C51 -> 102.8535 | N51: =$G51 -> 100.58509 | P51: =$J51 -> Jul-25 | Q51: =$E51 -> -0.040664434 | R51: =$I51 -> -0.033029351 | T51: =$J51 -> Jul-25 | U51: =IF($A51="","",NotionalValue*$C51/IndexBase) -> 1028535
A52: =Returns!$A$50 -> 45859 | B52: =IF($A52="","",Returns!$J$50) -> -0.0066025012 | C52: =IF($A52="","",C51*(1+$B52)) -> 102.17441 | D52: =IF($A52="","",MAX($C$7:C52)) -> 107.21327 | E52: =IF($A52="","",$C52/$D52-1) -> -0.046998448 | F52: =IF($A52="","",Returns!$I$50) -> 0.00033483521 | G52: =IF($A52="","",G51*(1+$F52)) -> 100.61877 | H52: =IF($A52="","",MAX($G$7:G52)) -> 104.02083 | I52: =IF($A52="","",$G52/$H52-1) -> -0.032705575 | J52: =IF($A52="","",TEXT($A52,"mmm-yy")) -> Jul-25 | L52: =$J52 -> Jul-25 | M52: =$C52 -> 102.17441 | N52: =$G52 -> 100.61877 | P52: =$J52 -> Jul-25 | Q52: =$E52 -> -0.046998448 | R52: =$I52 -> -0.032705575 | T52: =$J52 -> Jul-25 | U52: =IF($A52="","",NotionalValue*$C52/IndexBase) -> 1021744.1
A53: =Returns!$A$51 -> 45866 | B53: =IF($A53="","",Returns!$J$51) -> -0.0029776016 | C53: =IF($A53="","",C52*(1+$B53)) -> 101.87018 | D53: =IF($A53="","",MAX($C$7:C53)) -> 107.21327 | E53: =IF($A53="","",$C53/$D53-1) -> -0.049836107 | F53: =IF($A53="","",Returns!$I$51) -> -0.016332699 | G53: =IF($A53="","",G52*(1+$F53)) -> 98.975393 | H53: =IF($A53="","",MAX($G$7:G53)) -> 104.02083 | I53: =IF($A53="","",$G53/$H53-1) -> -0.048504103 | J53: =IF($A53="","",TEXT($A53,"mmm-yy")) -> Jul-25 | L53: =$J53 -> Jul-25 | M53: =$C53 -> 101.87018 | N53: =$G53 -> 98.975393 | P53: =$J53 -> Jul-25 | Q53: =$E53 -> -0.049836107 | R53: =$I53 -> -0.048504103 | T53: =$J53 -> Jul-25 | U53: =IF($A53="","",NotionalValue*$C53/IndexBase) -> 1018701.8
A54: =Returns!$A$52 -> 45873 | B54: =IF($A54="","",Returns!$J$52) -> -0.0054762404 | C54: =IF($A54="","",C53*(1+$B54)) -> 101.31231 | D54: =IF($A54="","",MAX($C$7:C54)) -> 107.21327 | E54: =IF($A54="","",$C54/$D54-1) -> -0.055039433 | F54: =IF($A54="","",Returns!$I$52) -> 0.0016956273 | G54: =IF($A54="","",G53*(1+$F54)) -> 99.143219 | H54: =IF($A54="","",MAX($G$7:G54)) -> 104.02083 | I54: =IF($A54="","",$G54/$H54-1) -> -0.046890721 | J54: =IF($A54="","",TEXT($A54,"mmm-yy")) -> Aug-25 | L54: =$J54 -> Aug-25 | M54: =$C54 -> 101.31231 | N54: =$G54 -> 99.143219 | P54: =$J54 -> Aug-25 | Q54: =$E54 -> -0.055039433 | R54: =$I54 -> -0.046890721 | T54: =$J54 -> Aug-25 | U54: =IF($A54="","",NotionalValue*$C54/IndexBase) -> 1013123.1
A55: =Returns!$A$53 -> 45880 | B55: =IF($A55="","",Returns!$J$53) -> 0.016709485 | C55: =IF($A55="","",C54*(1+$B55)) -> 103.00519 | D55: =IF($A55="","",MAX($C$7:C55)) -> 107.21327 | E55: =IF($A55="","",$C55/$D55-1) -> -0.039249629 | F55: =IF($A55="","",Returns!$I$53) -> -0.0055697371 | G55: =IF($A55="","",G54*(1+$F55)) -> 98.591017 | H55: =IF($A55="","",MAX($G$7:G55)) -> 104.02083 | I55: =IF($A55="","",$G55/$H55-1) -> -0.052199289 | J55: =IF($A55="","",TEXT($A55,"mmm-yy")) -> Aug-25 | L55: =$J55 -> Aug-25 | M55: =$C55 -> 103.00519 | N55: =$G55 -> 98.591017 | P55: =$J55 -> Aug-25 | Q55: =$E55 -> -0.039249629 | R55: =$I55 -> -0.052199289 | T55: =$J55 -> Aug-25 | U55: =IF($A55="","",NotionalValue*$C55/IndexBase) -> 1030051.9
A56: =Returns!$A$54 -> 45887 | B56: =IF($A56="","",Returns!$J$54) -> 0.019499312 | C56: =IF($A56="","",C55*(1+$B56)) -> 105.01372 | D56: =IF($A56="","",MAX($C$7:C56)) -> 107.21327 | E56: =IF($A56="","",$C56/$D56-1) -> -0.020515657 | F56: =IF($A56="","",Returns!$I$54) -> 0.011873005 | G56: =IF($A56="","",G55*(1+$F56)) -> 99.761589 | H56: =IF($A56="","",MAX($G$7:G56)) -> 104.02083 | I56: =IF($A56="","",$G56/$H56-1) -> -0.040946046 | J56: =IF($A56="","",TEXT($A56,"mmm-yy")) -> Aug-25 | L56: =$J56 -> Aug-25 | M56: =$C56 -> 105.01372 | N56: =$G56 -> 99.761589 | P56: =$J56 -> Aug-25 | Q56: =$E56 -> -0.020515657 | R56: =$I56 -> -0.040946046 | T56: =$J56 -> Aug-25 | U56: =IF($A56="","",NotionalValue*$C56/IndexBase) -> 1050137.2
A57: =Returns!$A$55 -> 45894 | B57: =IF($A57="","",Returns!$J$55) -> -0.013690836 | C57: =IF($A57="","",C56*(1+$B57)) -> 103.57599 | D57: =IF($A57="","",MAX($C$7:C57)) -> 107.21327 | E57: =IF($A57="","",$C57/$D57-1) -> -0.033925616 | F57: =IF($A57="","",Returns!$I$55) -> 0.0036499966 | G57: =IF($A57="","",G56*(1+$F57)) -> 100.12572 | H57: =IF($A57="","",MAX($G$7:G57)) -> 104.02083 | I57: =IF($A57="","",$G57/$H57-1) -> -0.037445502 | J57: =IF($A57="","",TEXT($A57,"mmm-yy")) -> Aug-25 | L57: =$J57 -> Aug-25 | M57: =$C57 -> 103.57599 | N57: =$G57 -> 100.12572 | P57: =$J57 -> Aug-25 | Q57: =$E57 -> -0.033925616 | R57: =$I57 -> -0.037445502 | T57: =$J57 -> Aug-25 | U57: =IF($A57="","",NotionalValue*$C57/IndexBase) -> 1035759.9
A58: =Returns!$A$56 -> 45901 | B58: =IF($A58="","",Returns!$J$56) -> -0.00053907876 | C58: =IF($A58="","",C57*(1+$B58)) -> 103.52016 | D58: =IF($A58="","",MAX($C$7:C58)) -> 107.21327 | E58: =IF($A58="","",$C58/$D58-1) -> -0.034446406 | F58: =IF($A58="","",Returns!$I$56) -> -0.013725675 | G58: =IF($A58="","",G57*(1+$F58)) -> 98.751425 | H58: =IF($A58="","",MAX($G$7:G58)) -> 104.02083 | I58: =IF($A58="","",$G58/$H58-1) -> -0.050657212 | J58: =IF($A58="","",TEXT($A58,"mmm-yy")) -> Sep-25 | L58: =$J58 -> Sep-25 | M58: =$C58 -> 103.52016 | N58: =$G58 -> 98.751425 | P58: =$J58 -> Sep-25 | Q58: =$E58 -> -0.034446406 | R58: =$I58 -> -0.050657212 | T58: =$J58 -> Sep-25 | U58: =IF($A58="","",NotionalValue*$C58/IndexBase) -> 1035201.6
A59: =Returns!$A$57 -> 45908 | B59: =IF($A59="","",Returns!$J$57) -> 0.013721647 | C59: =IF($A59="","",C58*(1+$B59)) -> 104.94063 | D59: =IF($A59="","",MAX($C$7:C59)) -> 107.21327 | E59: =IF($A59="","",$C59/$D59-1) -> -0.021197421 | F59: =IF($A59="","",Returns!$I$57) -> 0.0060141849 | G59: =IF($A59="","",G58*(1+$F59)) -> 99.345335 | H59: =IF($A59="","",MAX($G$7:G59)) -> 104.02083 | I59: =IF($A59="","",$G59/$H59-1) -> -0.044947689 | J59: =IF($A59="","",TEXT($A59,"mmm-yy")) -> Sep-25 | L59: =$J59 -> Sep-25 | M59: =$C59 -> 104.94063 | N59: =$G59 -> 99.345335 | P59: =$J59 -> Sep-25 | Q59: =$E59 -> -0.021197421 | R59: =$I59 -> -0.044947689 | T59: =$J59 -> Sep-25 | U59: =IF($A59="","",NotionalValue*$C59/IndexBase) -> 1049406.3
A60: =Returns!$A$58 -> 45915 | B60: =IF($A60="","",Returns!$J$58) -> 0.014760048 | C60: =IF($A60="","",C59*(1+$B60)) -> 106.48955 | D60: =IF($A60="","",MAX($C$7:C60)) -> 107.21327 | E60: =IF($A60="","",$C60/$D60-1) -> -0.0067502476 | F60: =IF($A60="","",Returns!$I$58) -> 0.011950391 | G60: =IF($A60="","",G59*(1+$F60)) -> 100.53255 | H60: =IF($A60="","",MAX($G$7:G60)) -> 104.02083 | I60: =IF($A60="","",$G60/$H60-1) -> -0.033534441 | J60: =IF($A60="","",TEXT($A60,"mmm-yy")) -> Sep-25 | L60: =$J60 -> Sep-25 | M60: =$C60 -> 106.48955 | N60: =$G60 -> 100.53255 | P60: =$J60 -> Sep-25 | Q60: =$E60 -> -0.0067502476 | R60: =$I60 -> -0.033534441 | T60: =$J60 -> Sep-25 | U60: =IF($A60="","",NotionalValue*$C60/IndexBase) -> 1064895.5
A61: =Returns!$A$59 -> 45922 | B61: =IF($A61="","",Returns!$J$59) -> -0.01674773 | C61: =IF($A61="","",C60*(1+$B61)) -> 104.7061 | D61: =IF($A61="","",MAX($C$7:C61)) -> 107.21327 | E61: =IF($A61="","",$C61/$D61-1) -> -0.023384927 | F61: =IF($A61="","",Returns!$I$59) -> 0.0053113141 | G61: =IF($A61="","",G60*(1+$F61)) -> 101.06651 | H61: =IF($A61="","",MAX($G$7:G61)) -> 104.02083 | I61: =IF($A61="","",$G61/$H61-1) -> -0.028401239 | J61: =IF($A61="","",TEXT($A61,"mmm-yy")) -> Sep-25 | L61: =$J61 -> Sep-25 | M61: =$C61 -> 104.7061 | N61: =$G61 -> 101.06651 | P61: =$J61 -> Sep-25 | Q61: =$E61 -> -0.023384927 | R61: =$I61 -> -0.028401239 | T61: =$J61 -> Sep-25 | U61: =IF($A61="","",NotionalValue*$C61/IndexBase) -> 1047061
A62: =Returns!$A$60 -> 45929 | B62: =IF($A62="","",Returns!$J$60) -> -0.0027910874 | C62: =IF($A62="","",C61*(1+$B62)) -> 104.41385 | D62: =IF($A62="","",MAX($C$7:C62)) -> 107.21327 | E62: =IF($A62="","",$C62/$D62-1) -> -0.026110745 | F62: =IF($A62="","",Returns!$I$60) -> -0.022515727 | G62: =IF($A62="","",G61*(1+$F62)) -> 98.790924 | H62: =IF($A62="","",MAX($G$7:G62)) -> 104.02083 | I62: =IF($A62="","",$G62/$H62-1) -> -0.050277491 | J62: =IF($A62="","",TEXT($A62,"mmm-yy")) -> Sep-25 | L62: =$J62 -> Sep-25 | M62: =$C62 -> 104.41385 | N62: =$G62 -> 98.790924 | P62: =$J62 -> Sep-25 | Q62: =$E62 -> -0.026110745 | R62: =$I62 -> -0.050277491 | T62: =$J62 -> Sep-25 | U62: =IF($A62="","",NotionalValue*$C62/IndexBase) -> 1044138.5
A63: =Returns!$A$61 -> 45936 | B63: =IF($A63="","",Returns!$J$61) -> 0.024419607 | C63: =IF($A63="","",C62*(1+$B63)) -> 106.9636 | D63: =IF($A63="","",MAX($C$7:C63)) -> 107.21327 | E63: =IF($A63="","",$C63/$D63-1) -> -0.0023287519 | F63: =IF($A63="","",Returns!$I$61) -> 0.01797247 | G63: =IF($A63="","",G62*(1+$F63)) -> 100.56644 | H63: =IF($A63="","",MAX($G$7:G63)) -> 104.02083 | I63: =IF($A63="","",$G63/$H63-1) -> -0.033208632 | J63: =IF($A63="","",TEXT($A63,"mmm-yy")) -> Oct-25 | L63: =$J63 -> Oct-25 | M63: =$C63 -> 106.9636 | N63: =$G63 -> 100.56644 | P63: =$J63 -> Oct-25 | Q63: =$E63 -> -0.0023287519 | R63: =$I63 -> -0.033208632 | T63: =$J63 -> Oct-25 | U63: =IF($A63="","",NotionalValue*$C63/IndexBase) -> 1069636
A64: =Returns!$A$62 -> 45943 | B64: =IF($A64="","",Returns!$J$62) -> 0.018435936 | C64: =IF($A64="","",C63*(1+$B64)) -> 108.93557 | D64: =IF($A64="","",MAX($C$7:C64)) -> 108.93557 | E64: =IF($A64="","",$C64/$D64-1) -> 0 | F64: =IF($A64="","",Returns!$I$62) -> 0.0059694276 | G64: =IF($A64="","",G63*(1+$F64)) -> 101.16677 | H64: =IF($A64="","",MAX($G$7:G64)) -> 104.02083 | I64: =IF($A64="","",$G64/$H64-1) -> -0.027437441 | J64: =IF($A64="","",TEXT($A64,"mmm-yy")) -> Oct-25 | L64: =$J64 -> Oct-25 | M64: =$C64 -> 108.93557 | N64: =$G64 -> 101.16677 | P64: =$J64 -> Oct-25 | Q64: =$E64 -> 0 | R64: =$I64 -> -0.027437441 | T64: =$J64 -> Oct-25 | U64: =IF($A64="","",NotionalValue*$C64/IndexBase) -> 1089355.7
A65: =Returns!$A$63 -> 45950 | B65: =IF($A65="","",Returns!$J$63) -> 0.01002546 | C65: =IF($A65="","",C64*(1+$B65)) -> 110.0277 | D65: =IF($A65="","",MAX($C$7:C65)) -> 110.0277 | E65: =IF($A65="","",$C65/$D65-1) -> 0 | F65: =IF($A65="","",Returns!$I$63) -> 0.024410047 | G65: =IF($A65="","",G64*(1+$F65)) -> 103.63625 | H65: =IF($A65="","",MAX($G$7:G65)) -> 104.02083 | I65: =IF($A65="","",$G65/$H65-1) -> -0.0036971434 | J65: =IF($A65="","",TEXT($A65,"mmm-yy")) -> Oct-25 | L65: =$J65 -> Oct-25 | M65: =$C65 -> 110.0277 | N65: =$G65 -> 103.63625 | P65: =$J65 -> Oct-25 | Q65: =$E65 -> 0 | R65: =$I65 -> -0.0036971434 | T65: =$J65 -> Oct-25 | U65: =IF($A65="","",NotionalValue*$C65/IndexBase) -> 1100277
A66: =Returns!$A$64 -> 45957 | B66: =IF($A66="","",Returns!$J$64) -> 0.0048732901 | C66: =IF($A66="","",C65*(1+$B66)) -> 110.5639 | D66: =IF($A66="","",MAX($C$7:C66)) -> 110.5639 | E66: =IF($A66="","",$C66/$D66-1) -> 0 | F66: =IF($A66="","",Returns!$I$64) -> 0.0047556273 | G66: =IF($A66="","",G65*(1+$F66)) -> 104.12911 | H66: =IF($A66="","",MAX($G$7:G66)) -> 104.12911 | I66: =IF($A66="","",$G66/$H66-1) -> 0 | J66: =IF($A66="","",TEXT($A66,"mmm-yy")) -> Oct-25 | L66: =$J66 -> Oct-25 | M66: =$C66 -> 110.5639 | N66: =$G66 -> 104.12911 | P66: =$J66 -> Oct-25 | Q66: =$E66 -> 0 | R66: =$I66 -> 0 | T66: =$J66 -> Oct-25 | U66: =IF($A66="","",NotionalValue*$C66/IndexBase) -> 1105639
A67: =Returns!$A$65 -> 45964 | B67: =IF($A67="","",Returns!$J$65) -> -0.01769394 | C67: =IF($A67="","",C66*(1+$B67)) -> 108.60759 | D67: =IF($A67="","",MAX($C$7:C67)) -> 110.5639 | E67: =IF($A67="","",$C67/$D67-1) -> -0.01769394 | F67: =IF($A67="","",Returns!$I$65) -> -0.007806392 | G67: =IF($A67="","",G66*(1+$F67)) -> 103.31623 | H67: =IF($A67="","",MAX($G$7:G67)) -> 104.12911 | I67: =IF($A67="","",$G67/$H67-1) -> -0.007806392 | J67: =IF($A67="","",TEXT($A67,"mmm-yy")) -> Nov-25 | L67: =$J67 -> Nov-25 | M67: =$C67 -> 108.60759 | N67: =$G67 -> 103.31623 | P67: =$J67 -> Nov-25 | Q67: =$E67 -> -0.01769394 | R67: =$I67 -> -0.007806392 | T67: =$J67 -> Nov-25 | U67: =IF($A67="","",NotionalValue*$C67/IndexBase) -> 1086075.9
A68: =Returns!$A$66 -> 45971 | B68: =IF($A68="","",Returns!$J$66) -> 0.027917877 | C68: =IF($A68="","",C67*(1+$B68)) -> 111.63968 | D68: =IF($A68="","",MAX($C$7:C68)) -> 111.63968 | E68: =IF($A68="","",$C68/$D68-1) -> 0 | F68: =IF($A68="","",Returns!$I$66) -> -0.0073360026 | G68: =IF($A68="","",G67*(1+$F68)) -> 102.55831 | H68: =IF($A68="","",MAX($G$7:G68)) -> 104.12911 | I68: =IF($A68="","",$G68/$H68-1) -> -0.015085127 | J68: =IF($A68="","",TEXT($A68,"mmm-yy")) -> Nov-25 | L68: =$J68 -> Nov-25 | M68: =$C68 -> 111.63968 | N68: =$G68 -> 102.55831 | P68: =$J68 -> Nov-25 | Q68: =$E68 -> 0 | R68: =$I68 -> -0.015085127 | T68: =$J68 -> Nov-25 | U68: =IF($A68="","",NotionalValue*$C68/IndexBase) -> 1116396.8
A69: =Returns!$A$67 -> 45978 | B69: =IF($A69="","",Returns!$J$67) -> 0.012027214 | C69: =IF($A69="","",C68*(1+$B69)) -> 112.98239 | D69: =IF($A69="","",MAX($C$7:C69)) -> 112.98239 | E69: =IF($A69="","",$C69/$D69-1) -> 0 | F69: =IF($A69="","",Returns!$I$67) -> 0.017169532 | G69: =IF($A69="","",G68*(1+$F69)) -> 104.31918 | H69: =IF($A69="","",MAX($G$7:G69)) -> 104.31918 | I69: =IF($A69="","",$G69/$H69-1) -> 0 | J69: =IF($A69="","",TEXT($A69,"mmm-yy")) -> Nov-25 | L69: =$J69 -> Nov-25 | M69: =$C69 -> 112.98239 | N69: =$G69 -> 104.31918 | P69: =$J69 -> Nov-25 | Q69: =$E69 -> 0 | R69: =$I69 -> 0 | T69: =$J69 -> Nov-25 | U69: =IF($A69="","",NotionalValue*$C69/IndexBase) -> 1129823.9
A70: =Returns!$A$68 -> 45985 | B70: =IF($A70="","",Returns!$J$68) -> 0.0037366787 | C70: =IF($A70="","",C69*(1+$B70)) -> 113.40457 | D70: =IF($A70="","",MAX($C$7:C70)) -> 113.40457 | E70: =IF($A70="","",$C70/$D70-1) -> 0 | F70: =IF($A70="","",Returns!$I$68) -> -0.0020738972 | G70: =IF($A70="","",G69*(1+$F70)) -> 104.10284 | H70: =IF($A70="","",MAX($G$7:G70)) -> 104.31918 | I70: =IF($A70="","",$G70/$H70-1) -> -0.0020738972 | J70: =IF($A70="","",TEXT($A70,"mmm-yy")) -> Nov-25 | L70: =$J70 -> Nov-25 | M70: =$C70 -> 113.40457 | N70: =$G70 -> 104.10284 | P70: =$J70 -> Nov-25 | Q70: =$E70 -> 0 | R70: =$I70 -> -0.0020738972 | T70: =$J70 -> Nov-25 | U70: =IF($A70="","",NotionalValue*$C70/IndexBase) -> 1134045.7
A71: =Returns!$A$69 -> 45992 | B71: =IF($A71="","",Returns!$J$69) -> 0.00016491334 | C71: =IF($A71="","",C70*(1+$B71)) -> 113.42327 | D71: =IF($A71="","",MAX($C$7:C71)) -> 113.42327 | E71: =IF($A71="","",$C71/$D71-1) -> 0 | F71: =IF($A71="","",Returns!$I$69) -> 0.0083302837 | G71: =IF($A71="","",G70*(1+$F71)) -> 104.97004 | H71: =IF($A71="","",MAX($G$7:G71)) -> 104.97004 | I71: =IF($A71="","",$G71/$H71-1) -> 0 | J71: =IF($A71="","",TEXT($A71,"mmm-yy")) -> Dec-25 | L71: =$J71 -> Dec-25 | M71: =$C71 -> 113.42327 | N71: =$G71 -> 104.97004 | P71: =$J71 -> Dec-25 | Q71: =$E71 -> 0 | R71: =$I71 -> 0 | T71: =$J71 -> Dec-25 | U71: =IF($A71="","",NotionalValue*$C71/IndexBase) -> 1134232.7
A72: =Returns!$A$70 -> 45999 | B72: =IF($A72="","",Returns!$J$70) -> 0.0025190182 | C72: =IF($A72="","",C71*(1+$B72)) -> 113.70899 | D72: =IF($A72="","",MAX($C$7:C72)) -> 113.70899 | E72: =IF($A72="","",$C72/$D72-1) -> 0 | F72: =IF($A72="","",Returns!$I$70) -> -0.0082213201 | G72: =IF($A72="","",G71*(1+$F72)) -> 104.10705 | H72: =IF($A72="","",MAX($G$7:G72)) -> 104.97004 | I72: =IF($A72="","",$G72/$H72-1) -> -0.0082213201 | J72: =IF($A72="","",TEXT($A72,"mmm-yy")) -> Dec-25 | L72: =$J72 -> Dec-25 | M72: =$C72 -> 113.70899 | N72: =$G72 -> 104.10705 | P72: =$J72 -> Dec-25 | Q72: =$E72 -> 0 | R72: =$I72 -> -0.0082213201 | T72: =$J72 -> Dec-25 | U72: =IF($A72="","",NotionalValue*$C72/IndexBase) -> 1137089.9
A73: =Returns!$A$71 -> 46006 | B73: =IF($A73="","",Returns!$J$71) -> -0.0025814957 | C73: =IF($A73="","",C72*(1+$B73)) -> 113.41545 | D73: =IF($A73="","",MAX($C$7:C73)) -> 113.70899 | E73: =IF($A73="","",$C73/$D73-1) -> -0.0025814957 | F73: =IF($A73="","",Returns!$I$71) -> 0.0025712089 | G73: =IF($A73="","",G72*(1+$F73)) -> 104.37473 | H73: =IF($A73="","",MAX($G$7:G73)) -> 104.97004 | I73: =IF($A73="","",$G73/$H73-1) -> -0.0056712499 | J73: =IF($A73="","",TEXT($A73,"mmm-yy")) -> Dec-25 | L73: =$J73 -> Dec-25 | M73: =$C73 -> 113.41545 | N73: =$G73 -> 104.37473 | P73: =$J73 -> Dec-25 | Q73: =$E73 -> -0.0025814957 | R73: =$I73 -> -0.0056712499 | T73: =$J73 -> Dec-25 | U73: =IF($A73="","",NotionalValue*$C73/IndexBase) -> 1134154.5
A74: =Returns!$A$72 -> 46013 | B74: =IF($A74="","",Returns!$J$72) -> 0.0012540188 | C74: =IF($A74="","",C73*(1+$B74)) -> 113.55768 | D74: =IF($A74="","",MAX($C$7:C74)) -> 113.70899 | E74: =IF($A74="","",$C74/$D74-1) -> -0.0013307142 | F74: =IF($A74="","",Returns!$I$72) -> 0.0055749004 | G74: =IF($A74="","",G73*(1+$F74)) -> 104.95661 | H74: =IF($A74="","",MAX($G$7:G74)) -> 104.97004 | I74: =IF($A74="","",$G74/$H74-1) -> -0.00012796613 | J74: =IF($A74="","",TEXT($A74,"mmm-yy")) -> Dec-25 | L74: =$J74 -> Dec-25 | M74: =$C74 -> 113.55768 | N74: =$G74 -> 104.95661 | P74: =$J74 -> Dec-25 | Q74: =$E74 -> -0.0013307142 | R74: =$I74 -> -0.00012796613 | T74: =$J74 -> Dec-25 | U74: =IF($A74="","",NotionalValue*$C74/IndexBase) -> 1135576.8
A75: =Returns!$A$73 -> 46020 | B75: =IF($A75="","",Returns!$J$73) -> 0.012355604 | C75: =IF($A75="","",C74*(1+$B75)) -> 114.96075 | D75: =IF($A75="","",MAX($C$7:C75)) -> 114.96075 | E75: =IF($A75="","",$C75/$D75-1) -> 0 | F75: =IF($A75="","",Returns!$I$73) -> -0.0087993756 | G75: =IF($A75="","",G74*(1+$F75)) -> 104.03306 | H75: =IF($A75="","",MAX($G$7:G75)) -> 104.97004 | I75: =IF($A75="","",$G75/$H75-1) -> -0.0089262157 | J75: =IF($A75="","",TEXT($A75,"mmm-yy")) -> Dec-25 | L75: =$J75 -> Dec-25 | M75: =$C75 -> 114.96075 | N75: =$G75 -> 104.03306 | P75: =$J75 -> Dec-25 | Q75: =$E75 -> 0 | R75: =$I75 -> -0.0089262157 | T75: =$J75 -> Dec-25 | U75: =IF($A75="","",NotionalValue*$C75/IndexBase) -> 1149607.5
A76: =Returns!$A$74 -> 46027 | B76: =IF($A76="","",Returns!$J$74) -> -0.042290657 | C76: =IF($A76="","",C75*(1+$B76)) -> 110.09898 | D76: =IF($A76="","",MAX($C$7:C76)) -> 114.96075 | E76: =IF($A76="","",$C76/$D76-1) -> -0.042290657 | F76: =IF($A76="","",Returns!$I$74) -> 0.011880348 | G76: =IF($A76="","",G75*(1+$F76)) -> 105.26901 | H76: =IF($A76="","",MAX($G$7:G76)) -> 105.26901 | I76: =IF($A76="","",$G76/$H76-1) -> 0 | J76: =IF($A76="","",TEXT($A76,"mmm-yy")) -> Jan-26 | L76: =$J76 -> Jan-26 | M76: =$C76 -> 110.09898 | N76: =$G76 -> 105.26901 | P76: =$J76 -> Jan-26 | Q76: =$E76 -> -0.042290657 | R76: =$I76 -> 0 | T76: =$J76 -> Jan-26 | U76: =IF($A76="","",NotionalValue*$C76/IndexBase) -> 1100989.8
A77: =Returns!$A$75 -> 46034 | B77: =IF($A77="","",Returns!$J$75) -> -0.018907256 | C77: =IF($A77="","",C76*(1+$B77)) -> 108.01731 | D77: =IF($A77="","",MAX($C$7:C77)) -> 114.96075 | E77: =IF($A77="","",$C77/$D77-1) -> -0.060398313 | F77: =IF($A77="","",Returns!$I$75) -> -0.017525543 | G77: =IF($A77="","",G76*(1+$F77)) -> 103.42411 | H77: =IF($A77="","",MAX($G$7:G77)) -> 105.26901 | I77: =IF($A77="","",$G77/$H77-1) -> -0.017525543 | J77: =IF($A77="","",TEXT($A77,"mmm-yy")) -> Jan-26 | L77: =$J77 -> Jan-26 | M77: =$C77 -> 108.01731 | N77: =$G77 -> 103.42411 | P77: =$J77 -> Jan-26 | Q77: =$E77 -> -0.060398313 | R77: =$I77 -> -0.017525543 | T77: =$J77 -> Jan-26 | U77: =IF($A77="","",NotionalValue*$C77/IndexBase) -> 1080173.1
A78: =Returns!$A$76 -> 46041 | B78: =IF($A78="","",Returns!$J$76) -> -0.029747714 | C78: =IF($A78="","",C77*(1+$B78)) -> 104.80405 | D78: =IF($A78="","",MAX($C$7:C78)) -> 114.96075 | E78: =IF($A78="","",$C78/$D78-1) -> -0.088349316 | F78: =IF($A78="","",Returns!$I$76) -> -0.0079390467 | G78: =IF($A78="","",G77*(1+$F78)) -> 102.60302 | H78: =IF($A78="","",MAX($G$7:G78)) -> 105.26901 | I78: =IF($A78="","",$G78/$H78-1) -> -0.025325454 | J78: =IF($A78="","",TEXT($A78,"mmm-yy")) -> Jan-26 | L78: =$J78 -> Jan-26 | M78: =$C78 -> 104.80405 | N78: =$G78 -> 102.60302 | P78: =$J78 -> Jan-26 | Q78: =$E78 -> -0.088349316 | R78: =$I78 -> -0.025325454 | T78: =$J78 -> Jan-26 | U78: =IF($A78="","",NotionalValue*$C78/IndexBase) -> 1048040.5
A79: =Returns!$A$77 -> 46048 | B79: =IF($A79="","",Returns!$J$77) -> 0 | C79: =IF($A79="","",C78*(1+$B79)) -> 104.80405 | D79: =IF($A79="","",MAX($C$7:C79)) -> 114.96075 | E79: =IF($A79="","",$C79/$D79-1) -> -0.088349316 | F79: =IF($A79="","",Returns!$I$77) -> -0.016028595 | G79: =IF($A79="","",G78*(1+$F79)) -> 100.95844 | H79: =IF($A79="","",MAX($G$7:G79)) -> 105.26901 | I79: =IF($A79="","",$G79/$H79-1) -> -0.040948117 | J79: =IF($A79="","",TEXT($A79,"mmm-yy")) -> Jan-26 | L79: =$J79 -> Jan-26 | M79: =$C79 -> 104.80405 | N79: =$G79 -> 100.95844 | P79: =$J79 -> Jan-26 | Q79: =$E79 -> -0.088349316 | R79: =$I79 -> -0.040948117 | T79: =$J79 -> Jan-26 | U79: =IF($A79="","",NotionalValue*$C79/IndexBase) -> 1048040.5
A80: =Returns!$A$78 -> 46055 | B80: =IF($A80="","",Returns!$J$78) -> 0.022748782 | C80: =IF($A80="","",C79*(1+$B80)) -> 107.18821 | D80: =IF($A80="","",MAX($C$7:C80)) -> 114.96075 | E80: =IF($A80="","",$C80/$D80-1) -> -0.067610373 | F80: =IF($A80="","",Returns!$I$78) -> -0.0034557544 | G80: =IF($A80="","",G79*(1+$F80)) -> 100.60955 | H80: =IF($A80="","",MAX($G$7:G80)) -> 105.26901 | I80: =IF($A80="","",$G80/$H80-1) -> -0.044262365 | J80: =IF($A80="","",TEXT($A80,"mmm-yy")) -> Feb-26 | L80: =$J80 -> Feb-26 | M80: =$C80 -> 107.18821 | N80: =$G80 -> 100.60955 | P80: =$J80 -> Feb-26 | Q80: =$E80 -> -0.067610373 | R80: =$I80 -> -0.044262365 | T80: =$J80 -> Feb-26 | U80: =IF($A80="","",NotionalValue*$C80/IndexBase) -> 1071882.1
A81: =Returns!$A$79 -> 46062 | B81: =IF($A81="","",Returns!$J$79) -> -0.015480042 | C81: =IF($A81="","",C80*(1+$B81)) -> 105.52893 | D81: =IF($A81="","",MAX($C$7:C81)) -> 114.96075 | E81: =IF($A81="","",$C81/$D81-1) -> -0.082043803 | F81: =IF($A81="","",Returns!$I$79) -> 0.031046236 | G81: =IF($A81="","",G80*(1+$F81)) -> 103.7331 | H81: =IF($A81="","",MAX($G$7:G81)) -> 105.26901 | I81: =IF($A81="","",$G81/$H81-1) -> -0.014590309 | J81: =IF($A81="","",TEXT($A81,"mmm-yy")) -> Feb-26 | L81: =$J81 -> Feb-26 | M81: =$C81 -> 105.52893 | N81: =$G81 -> 103.7331 | P81: =$J81 -> Feb-26 | Q81: =$E81 -> -0.082043803 | R81: =$I81 -> -0.014590309 | T81: =$J81 -> Feb-26 | U81: =IF($A81="","",NotionalValue*$C81/IndexBase) -> 1055289.3
A82: =Returns!$A$80 -> 46069 | B82: =IF($A82="","",Returns!$J$80) -> 0.0038382645 | C82: =IF($A82="","",C81*(1+$B82)) -> 105.93398 | D82: =IF($A82="","",MAX($C$7:C82)) -> 114.96075 | E82: =IF($A82="","",$C82/$D82-1) -> -0.078520445 | F82: =IF($A82="","",Returns!$I$80) -> -0.0071345203 | G82: =IF($A82="","",G81*(1+$F82)) -> 102.99301 | H82: =IF($A82="","",MAX($G$7:G82)) -> 105.26901 | I82: =IF($A82="","",$G82/$H82-1) -> -0.021620734 | J82: =IF($A82="","",TEXT($A82,"mmm-yy")) -> Feb-26 | L82: =$J82 -> Feb-26 | M82: =$C82 -> 105.93398 | N82: =$G82 -> 102.99301 | P82: =$J82 -> Feb-26 | Q82: =$E82 -> -0.078520445 | R82: =$I82 -> -0.021620734 | T82: =$J82 -> Feb-26 | U82: =IF($A82="","",NotionalValue*$C82/IndexBase) -> 1059339.8
A83: =Returns!$A$81 -> 46076 | B83: =IF($A83="","",Returns!$J$81) -> -0.022103394 | C83: =IF($A83="","",C82*(1+$B83)) -> 103.59248 | D83: =IF($A83="","",MAX($C$7:C83)) -> 114.96075 | E83: =IF($A83="","",$C83/$D83-1) -> -0.09888827 | F83: =IF($A83="","",Returns!$I$81) -> 0.0011778334 | G83: =IF($A83="","",G82*(1+$F83)) -> 103.11432 | H83: =IF($A83="","",MAX($G$7:G83)) -> 105.26901 | I83: =IF($A83="","",$G83/$H83-1) -> -0.020468367 | J83: =IF($A83="","",TEXT($A83,"mmm-yy")) -> Feb-26 | L83: =$J83 -> Feb-26 | M83: =$C83 -> 103.59248 | N83: =$G83 -> 103.11432 | P83: =$J83 -> Feb-26 | Q83: =$E83 -> -0.09888827 | R83: =$I83 -> -0.020468367 | T83: =$J83 -> Feb-26 | U83: =IF($A83="","",NotionalValue*$C83/IndexBase) -> 1035924.8
A84: =Returns!$A$82 -> 46083 | B84: =IF($A84="","",Returns!$J$82) -> -0.024956913 | C84: =IF($A84="","",C83*(1+$B84)) -> 101.00713 | D84: =IF($A84="","",MAX($C$7:C84)) -> 114.96075 | E84: =IF($A84="","",$C84/$D84-1) -> -0.12137724 | F84: =IF($A84="","",Returns!$I$82) -> -0.032952234 | G84: =IF($A84="","",G83*(1+$F84)) -> 99.716474 | H84: =IF($A84="","",MAX($G$7:G84)) -> 105.26901 | I84: =IF($A84="","",$G84/$H84-1) -> -0.052746122 | J84: =IF($A84="","",TEXT($A84,"mmm-yy")) -> Mar-26 | L84: =$J84 -> Mar-26 | M84: =$C84 -> 101.00713 | N84: =$G84 -> 99.716474 | P84: =$J84 -> Mar-26 | Q84: =$E84 -> -0.12137724 | R84: =$I84 -> -0.052746122 | T84: =$J84 -> Mar-26 | U84: =IF($A84="","",NotionalValue*$C84/IndexBase) -> 1010071.3
A85: =Returns!$A$83 -> 46090 | B85: =IF($A85="","",Returns!$J$83) -> -0.050420401 | C85: =IF($A85="","",C84*(1+$B85)) -> 95.914311 | D85: =IF($A85="","",MAX($C$7:C85)) -> 114.96075 | E85: =IF($A85="","",$C85/$D85-1) -> -0.16567775 | F85: =IF($A85="","",Returns!$I$83) -> -0.033686905 | G85: =IF($A85="","",G84*(1+$F85)) -> 96.357335 | H85: =IF($A85="","",MAX($G$7:G85)) -> 105.26901 | I85: =IF($A85="","",$G85/$H85-1) -> -0.084656173 | J85: =IF($A85="","",TEXT($A85,"mmm-yy")) -> Mar-26 | L85: =$J85 -> Mar-26 | M85: =$C85 -> 95.914311 | N85: =$G85 -> 96.357335 | P85: =$J85 -> Mar-26 | Q85: =$E85 -> -0.16567775 | R85: =$I85 -> -0.084656173 | T85: =$J85 -> Mar-26 | U85: =IF($A85="","",NotionalValue*$C85/IndexBase) -> 959143.11
A86: =Returns!$A$84 -> 46097 | B86: =IF($A86="","",Returns!$J$84) -> -0.0023785189 | C86: =IF($A86="","",C85*(1+$B86)) -> 95.686177 | D86: =IF($A86="","",MAX($C$7:C86)) -> 114.96075 | E86: =IF($A86="","",$C86/$D86-1) -> -0.1676622 | F86: =IF($A86="","",Returns!$I$84) -> -0.025771962 | G86: =IF($A86="","",G85*(1+$F86)) -> 93.874017 | H86: =IF($A86="","",MAX($G$7:G86)) -> 105.26901 | I86: =IF($A86="","",$G86/$H86-1) -> -0.10824638 | J86: =IF($A86="","",TEXT($A86,"mmm-yy")) -> Mar-26 | L86: =$J86 -> Mar-26 | M86: =$C86 -> 95.686177 | N86: =$G86 -> 93.874017 | P86: =$J86 -> Mar-26 | Q86: =$E86 -> -0.1676622 | R86: =$I86 -> -0.10824638 | T86: =$J86 -> Mar-26 | U86: =IF($A86="","",NotionalValue*$C86/IndexBase) -> 956861.77
A87: =Returns!$A$85 -> 46104 | B87: =IF($A87="","",Returns!$J$85) -> -0.011644514 | C87: =IF($A87="","",C86*(1+$B87)) -> 94.571958 | D87: =IF($A87="","",MAX($C$7:C87)) -> 114.96075 | E87: =IF($A87="","",$C87/$D87-1) -> -0.17735437 | F87: =IF($A87="","",Returns!$I$85) -> -0.038282627 | G87: =IF($A87="","",G86*(1+$F87)) -> 90.280273 | H87: =IF($A87="","",MAX($G$7:G87)) -> 105.26901 | I87: =IF($A87="","",$G87/$H87-1) -> -0.14238505 | J87: =IF($A87="","",TEXT($A87,"mmm-yy")) -> Mar-26 | L87: =$J87 -> Mar-26 | M87: =$C87 -> 94.571958 | N87: =$G87 -> 90.280273 | P87: =$J87 -> Mar-26 | Q87: =$E87 -> -0.17735437 | R87: =$I87 -> -0.14238505 | T87: =$J87 -> Mar-26 | U87: =IF($A87="","",NotionalValue*$C87/IndexBase) -> 945719.58
A88: =Returns!$A$86 -> 46111 | B88: =IF($A88="","",Returns!$J$86) -> -0.0031089005 | C88: =IF($A88="","",C87*(1+$B88)) -> 94.277944 | D88: =IF($A88="","",MAX($C$7:C88)) -> 114.96075 | E88: =IF($A88="","",$C88/$D88-1) -> -0.17991189 | F88: =IF($A88="","",Returns!$I$86) -> -0.0080510289 | G88: =IF($A88="","",G87*(1+$F88)) -> 89.553424 | H88: =IF($A88="","",MAX($G$7:G88)) -> 105.26901 | I88: =IF($A88="","",$G88/$H88-1) -> -0.14928973 | J88: =IF($A88="","",TEXT($A88,"mmm-yy")) -> Mar-26 | L88: =$J88 -> Mar-26 | M88: =$C88 -> 94.277944 | N88: =$G88 -> 89.553424 | P88: =$J88 -> Mar-26 | Q88: =$E88 -> -0.17991189 | R88: =$I88 -> -0.14928973 | T88: =$J88 -> Mar-26 | U88: =IF($A88="","",NotionalValue*$C88/IndexBase) -> 942779.44
A89: =Returns!$A$87 -> 46118 | B89: =IF($A89="","",Returns!$J$87) -> 0.049102789 | C89: =IF($A89="","",C88*(1+$B89)) -> 98.907253 | D89: =IF($A89="","",MAX($C$7:C89)) -> 114.96075 | E89: =IF($A89="","",$C89/$D89-1) -> -0.13964328 | F89: =IF($A89="","",Returns!$I$87) -> 0.028518122 | G89: =IF($A89="","",G88*(1+$F89)) -> 92.10732 | H89: =IF($A89="","",MAX($G$7:G89)) -> 105.26901 | I89: =IF($A89="","",$G89/$H89-1) -> -0.12502907 | J89: =IF($A89="","",TEXT($A89,"mmm-yy")) -> Apr-26 | L89: =$J89 -> Apr-26 | M89: =$C89 -> 98.907253 | N89: =$G89 -> 92.10732 | P89: =$J89 -> Apr-26 | Q89: =$E89 -> -0.13964328 | R89: =$I89 -> -0.12502907 | T89: =$J89 -> Apr-26 | U89: =IF($A89="","",NotionalValue*$C89/IndexBase) -> 989072.53
A90: =Returns!$A$88 -> 46125 | B90: =IF($A90="","",Returns!$J$88) -> 0.0018682937 | C90: =IF($A90="","",C89*(1+$B90)) -> 99.092041 | D90: =IF($A90="","",MAX($C$7:C90)) -> 114.96075 | E90: =IF($A90="","",$C90/$D90-1) -> -0.13803588 | F90: =IF($A90="","",Returns!$I$88) -> 0.038069961 | G90: =IF($A90="","",G89*(1+$F90)) -> 95.613842 | H90: =IF($A90="","",MAX($G$7:G90)) -> 105.26901 | I90: =IF($A90="","",$G90/$H90-1) -> -0.091718964 | J90: =IF($A90="","",TEXT($A90,"mmm-yy")) -> Apr-26 | L90: =$J90 -> Apr-26 | M90: =$C90 -> 99.092041 | N90: =$G90 -> 95.613842 | P90: =$J90 -> Apr-26 | Q90: =$E90 -> -0.13803588 | R90: =$I90 -> -0.091718964 | T90: =$J90 -> Apr-26 | U90: =IF($A90="","",NotionalValue*$C90/IndexBase) -> 990920.41
A91: =Returns!$A$89 -> 46132 | B91: =IF($A91="","",Returns!$J$89) -> -0.027808343 | C91: =IF($A91="","",C90*(1+$B91)) -> 96.336456 | D91: =IF($A91="","",MAX($C$7:C91)) -> 114.96075 | E91: =IF($A91="","",$C91/$D91-1) -> -0.16200567 | F91: =IF($A91="","",Returns!$I$89) -> 0.021901895 | G91: =IF($A91="","",G90*(1+$F91)) -> 97.707966 | H91: =IF($A91="","",MAX($G$7:G91)) -> 105.26901 | I91: =IF($A91="","",$G91/$H91-1) -> -0.071825888 | J91: =IF($A91="","",TEXT($A91,"mmm-yy")) -> Apr-26 | L91: =$J91 -> Apr-26 | M91: =$C91 -> 96.336456 | N91: =$G91 -> 97.707966 | P91: =$J91 -> Apr-26 | Q91: =$E91 -> -0.16200567 | R91: =$I91 -> -0.071825888 | T91: =$J91 -> Apr-26 | U91: =IF($A91="","",NotionalValue*$C91/IndexBase) -> 963364.56
